Workbook
Name SegmentaciónDeDatos_Vendedor: #N/A

Sheet Datos
H2: Inversiones Agropecuarias Lom SAS | M2: 46036 | N2: 0.69438657
H4: 901399676-1
H5: AV CIUDAD DE CALI15A -91 LOCAL A19 - A20
H7: Cartera Por Edades | N7: R550103
A10: 4G FOOD SAS | J10: Telefono: | K10: 3112550306 | L10: Días Vencidos
A12: Tipo | B12: Numero | C12: Ven | D12: Factura | E12: Vencimiento | G12: Valor_Total | H12: Saldo | I12: Sin_Vencer | J12: 1_a_8 | K12: 9_a_15 | L12: 16_a_22 | M12: 23_a_30 | N12: >30
A13: 751 | B13: 18568 | C13: 8 | D13: 46007.561 | E13: 46022.561 | F13: 14 | G13: 1128900 | H13: 1128900 | I13: 0 | J13: 0 | K13: 1128900 | L13: 0 | M13: 0 | N13: 0
A14: 751 | B14: 18708 | C14: 8 | D14: 46010.552 | E14: 46025.552 | F14: 11 | G14: 524700 | H14: 524700 | I14: 0 | J14: 0 | K14: 524700 | L14: 0 | M14: 0 | N14: 0
A15: 751 | B15: 18988 | C15: 8 | D15: 46020.562 | E15: 46035.561 | F15: 1 | G15: 816200 | H15: 816200 | I15: 0 | J15: 816200 | K15: 0 | L15: 0 | M15: 0 | N15: 0
B16: Total: | D16: =SUBTOTAL(4,F13:F15) -> 14
G17: =SUBTOTAL(9,H13:H15) -> 2469800 | H17: =SUBTOTAL(9,I13:I15) -> 0 | I17: =SUBTOTAL(9,J13:J15) -> 816200 | K17: =SUBTOTAL(9,K13:K15) -> 1653600 | L17: =SUBTOTAL(9,L13:L15) -> 0 | M17: =SUBTOTAL(9,M13:M15) -> 0 | N17: =SUBTOTAL(9,N13:N15) -> 0
A18: A TEAM CG SAS | J18: Telefono: | K18: 6017044813 | L18: Días Vencidos
A20: Tipo | B20: Numero | C20: Ven | D20: Factura | E20: Vencimiento | G20: Valor_Total | H20: Saldo | I20: Sin_Vencer | J20: 1_a_8 | K20: 9_a_15 | L20: 16_a_22 | M20: 23_a_30 | N20: >30
A21: 151 | B21: 22568 | C21: 3 | D21: 45982.405 | E21: 46012.404 | F21: 24 | G21: 461500 | H21: 461500 | I21: 0 | J21: 0 | K21: 0 | L21: 0 | M21: 461500 | N21: 0
A22: 151 | B22: 22700 | C22: 3 | D22: 45987.306 | E22: 46017.305 | F22: 19 | G22: 248400 | H22: 248400 | I22: 0 | J22: 0 | K22: 0 | L22: 248400 | M22: 0 | N22: 0
A23: 151 | B23: 22763 | C23: 3 | D23: 45989.345 | E23: 46019.345 | F23: 17 | G23: 158900 | H23: 158900 | I23: 0 | J23: 0 | K23: 0 | L23: 158900 | M23: 0 | N23: 0
A24: 151 | B24: 22783 | C24: 3 | D24: 45990.292 | E24: 46020.29 | F24: 16 | G24: 800600 | H24: 800600 | I24: 0 | J24: 0 | K24: 0 | L24: 800600 | M24: 0 | N24: 0
A25: 151 | B25: 22942 | C25: 3 | D25: 45995.275 | E25: 46025.275 | F25: 11 | G25: 260000 | H25: 260000 | I25: 0 | J25: 0 | K25: 260000 | L25: 0 | M25: 0 | N25: 0
A26: 151 | B26: 23011 | C26: 3 | D26: 45997.255 | E26: 46027.255 | F26: 9 | G26: 464600 | H26: 464600 | I26: 0 | J26: 0 | K26: 464600 | L26: 0 | M26: 0 | N26: 0
A27: 151 | B27: 23072 | C27: 3 | D27: 46000.337 | E27: 46030.337 | F27: 6 | G27: 304500 | H27: 304500 | I27: 0 | J27: 304500 | K27: 0 | L27: 0 | M27: 0 | N27: 0
A28: 151 | B28: 23474 | C28: 3 | D28: 46011.331 | E28: 46041.33 | F28: -5 | G28: 154900 | H28: 154900 | I28: 154900 | J28: 0 | K28: 0 | L28: 0 | M28: 0 | N28: 0
A29: 151 | B29: 23695 | C29: 3 | D29: 46020.184 | E29: 46050.184 | F29: -14 | G29: 219700 | H29: 219700 | I29: 219700 | J29: 0 | K29: 0 | L29: 0 | M29: 0 | N29: 0
B30: Total: | D30: =SUBTOTAL(4,F21:F29) -> 24
G31: =SUBTOTAL(9,H21:H29) -> 3073100 | H31: =SUBTOTAL(9,I21:I29) -> 374600 | I31: =SUBTOTAL(9,J21:J29) -> 304500 | K31: =SUBTOTAL(9,K21:K29) -> 724600 | L31: =SUBTOTAL(9,L21:L29) -> 1207900 | M31: =SUBTOTAL(9,M21:M29) -> 461500 | N31: =SUBTOTAL(9,N21:N29) -> 0
A32: ABEL Y SOFIA SAS | J32: Telefono: | K32: 7044813 | L32: Días Vencidos
A34: Tipo | B34: Numero | C34: Ven | D34: Factura | E34: Vencimiento | G34: Valor_Total | H34: Saldo | I34: Sin_Vencer | J34: 1_a_8 | K34: 9_a_15 | L34: 16_a_22 | M34: 23_a_30 | N34: >30
A35: 151 | B35: 20290 | C35: 0 | D35: 45873.302 | E35: 45903.301 | F35: 133 | G35: 114299.99 | H35: 84299.99 | I35: 0 | J35: 0 | K35: 0 | L35: 0 | M35: 0 | N35: 84299.99
A36: 151 | B36: 21715 | C36: 0 | D36: 45945.312 | E36: 45975.312 | F36: 61 | G36: 393300 | H36: 371495 | I36: 0 | J36: 0 | K36: 0 | L36: 0 | M36: 0 | N36: 371495
A37: 151 | B37: 22119 | C37: 0 | D37: 45962.307 | E37: 45992.307 | F37: 44 | G37: 1772250 | H37: 1772250 | I37: 0 | J37: 0 | K37: 0 | L37: 0 | M37: 0 | N37: 1772250
A38: 151 | B38: 22121 | C38: 0 | D38: 45962.31 | E38: 45992.31 | F38: 44 | G38: 487600 | H38: 487600 | I38: 0 | J38: 0 | K38: 0 | L38: 0 | M38: 0 | N38: 487600
A39: 151 | B39: 22124 | C39: 0 | D39: 45962.317 | E39: 45992.317 | F39: 44 | G39: 150800 | H39: 150800 | I39: 0 | J39: 0 | K39: 0 | L39: 0 | M39: 0 | N39: 150800
A40: 151 | B40: 22125 | C40: 0 | D40: 45962.318 | E40: 45992.317 | F40: 44 | G40: 343300 | H40: 343300 | I40: 0 | J40: 0 | K40: 0 | L40: 0 | M40: 0 | N40: 343300
A41: 151 | B41: 22131 | C41: 0 | D41: 45962.377 | E41: 45992.377 | F41: 44 | G41: 1200000 | H41: 1200000 | I41: 0 | J41: 0 | K41: 0 | L41: 0 | M41: 0 | N41: 1200000
A42: 151 | B42: 22151 | C42: 0 | D42: 45965.291 | E42: 45995.287 | F42: 41 | G42: 195999.97 | H42: 195999.97 | I42: 0 | J42: 0 | K42: 0 | L42: 0 | M42: 0 | N42: 195999.97
A43: 151 | B43: 22152 | C43: 0 | D43: 45965.293 | E43: 45995.292 | F43: 41 | G43: 82899.99 | H43: 82899.99 | I43: 0 | J43: 0 | K43: 0 | L43: 0 | M43: 0 | N43: 82899.99
A44: 151 | B44: 22173 | C44: 0 | D44: 45966.285 | E44: 45996.284 | F44: 40 | G44: 178899.99 | H44: 178899.99 | I44: 0 | J44: 0 | K44: 0 | L44: 0 | M44: 0 | N44: 178899.99
A45: 151 | B45: 22174 | C45: 0 | D45: 45966.287 | E45: 45996.286 | F45: 40 | G45: 415850 | H45: 415850 | I45: 0 | J45: 0 | K45: 0 | L45: 0 | M45: 0 | N45: 415850
A46: 151 | B46: 22176 | C46: 0 | D46: 45966.288 | E46: 45996.288 | F46: 40 | G46: 342200 | H46: 342200 | I46: 0 | J46: 0 | K46: 0 | L46: 0 | M46: 0 | N46: 342200
... A206: 151 | B206: 23737 | C206: 0 | D206: 46021.345 | E206: 46051.344 | F206: -15 | G206: 1816900 | H206: 1816900 | I206: 1816900 | J206: 0 | K206: 0 | L206: 0 | M206: 0 | N206: 0
B207: Total: | D207: =SUBTOTAL(4,F35:F206) -> 133
G208: =SUBTOTAL(9,H35:H206) -> 2.1643376e+08 | H208: =SUBTOTAL(9,I35:I206) -> 56255000 | I208: =SUBTOTAL(9,J35:J206) -> 32641080 | K208: =SUBTOTAL(9,K35:K206) -> 32151750 | L208: =SUBTOTAL(9,L35:L206) -> 20271700 | M208: =SUBTOTAL(9,M35:M206) -> 30805190 | N208: =SUBTOTAL(9,N35:N206) -> 44309045
A209: ADRIANA BERMUDEZ RAMIREZ | J209: Telefono: | K209: 2735707 | L209: Días Vencidos
A211: Tipo | B211: Numero | C211: Ven | D211: Factura | E211: Vencimiento | G211: Valor_Total | H211: Saldo | I211: Sin_Vencer | J211: 1_a_8 | K211: 9_a_15 | L211: 16_a_22 | M211: 23_a_30 | N211: >30
A212: 751 | B212: 15707 | C212: 1 | D212: 45910.513 | E212: 45918.513 | F212: 118 | G212: 862400 | H212: 231640 | I212: 0 | J212: 0 | K212: 0 | L212: 0 | M212: 0 | N212: 231640
A213: 751 | B213: 18788 | C213: 1 | D213: 46013.475 | E213: 46021.475 | F213: 15 | G213: 319200 | H213: 319200 | I213: 0 | J213: 0 | K213: 319200 | L213: 0 | M213: 0 | N213: 0
A214: 751 | B214: 18809 | C214: 1 | D214: 46013.571 | E214: 46021.571 | F214: 15 | G214: 1454000 | H214: 1454000 | I214: 0 | J214: 0 | K214: 1454000 | L214: 0 | M214: 0 | N214: 0
B215: Total: | D215: =SUBTOTAL(4,F212:F214) -> 118
G216: =SUBTOTAL(9,H212:H214) -> 2004840 | H216: =SUBTOTAL(9,I212:I214) -> 0 | I216: =SUBTOTAL(9,J212:J214) -> 0 | K216: =SUBTOTAL(9,K212:K214) -> 1773200 | L216: =SUBTOTAL(9,L212:L214) -> 0 | M216: =SUBTOTAL(9,M212:M214) -> 0 | N216: =SUBTOTAL(9,N212:N214) -> 231640
A217: ALBA MARIA GONZALEZ IBAÑEZ | J217: Telefono: | K217: 3028122950 | L217: Días Vencidos
A219: Tipo | B219: Numero | C219: Ven | D219: Factura | E219: Vencimiento | G219: Valor_Total | H219: Saldo | I219: Sin_Vencer | J219: 1_a_8 | K219: 9_a_15 | L219: 16_a_22 | M219: 23_a_30 | N219: >30
A220: 151 | B220: 23759 | C220: 11 | D220: 46022.304 | E220: 46023.283 | F220: 13 | G220: 497700 | H220: 497700 | I220: 0 | J220: 0 | K220: 497700 | L220: 0 | M220: 0 | N220: 0
B221: Total: | D221: =SUBTOTAL(4,F220:F220) -> 13
G222: =SUBTOTAL(9,H220:H220) -> 497700 | H222: =SUBTOTAL(9,I220:I220) -> 0 | I222: =SUBTOTAL(9,J220:J220) -> 0 | K222: =SUBTOTAL(9,K220:K220) -> 497700 | L222: =SUBTOTAL(9,L220:L220) -> 0 | M222: =SUBTOTAL(9,M220:M220) -> 0 | N222: =SUBTOTAL(9,N220:N220) -> 0
A223: ALEJANDRO DURAN | J223: Telefono: | K223: 3134164472 | L223: Días Vencidos
A225: Tipo | B225: Numero | C225: Ven | D225: Factura | E225: Vencimiento | G225: Valor_Total | H225: Saldo | I225: Sin_Vencer | J225: 1_a_8 | K225: 9_a_15 | L225: 16_a_22 | M225: 23_a_30 | N225: >30
A226: 751 | B226: 16999 | C226: 7 | D226: 45957.477 | E226: 45958.477 | F226: 78 | G226: 1484405 | H226: 1484405 | I226: 0 | J226: 0 | K226: 0 | L226: 0 | M226: 0 | N226: 1484405
B227: Total: | D227: =SUBTOTAL(4,F226:F226) -> 78
G228: =SUBTOTAL(9,H226:H226) -> 1484405 | H228: =SUBTOTAL(9,I226:I226) -> 0 | I228: =SUBTOTAL(9,J226:J226) -> 0 | K228: =SUBTOTAL(9,K226:K226) -> 0 | L228: =SUBTOTAL(9,L226:L226) -> 0 | M228: =SUBTOTAL(9,M226:M226) -> 0 | N228: =SUBTOTAL(9,N226:N226) -> 1484405
A229: ALIANZA DOC SAS | J229: Telefono: | K229: 3138513218 | L229: Días Vencidos
A231: Tipo | B231: Numero | C231: Ven | D231: Factura | E231: Vencimiento | G231: Valor_Total | H231: Saldo | I231: Sin_Vencer | J231: 1_a_8 | K231: 9_a_15 | L231: 16_a_22 | M231: 23_a_30 | N231: >30
A232: 151 | B232: 23679 | C232: 12 | D232: 46018.295 | E232: 46026.293 | F232: 10 | G232: 1775100 | H232: 1775100 | I232: 0 | J232: 0 | K232: 1775100 | L232: 0 | M232: 0 | N232: 0
A233: 151 | B233: 23734 | C233: 12 | D233: 46021.313 | E233: 46029.305 | F233: 7 | G233: 4521700 | H233: 4521700 | I233: 0 | J233: 4521700 | K233: 0 | L233: 0 | M233: 0 | N233: 0
B234: Total: | D234: =SUBTOTAL(4,F232:F233) -> 10
G235: =SUBTOTAL(9,H232:H233) -> 6296800 | H235: =SUBTOTAL(9,I232:I233) -> 0 | I235: =SUBTOTAL(9,J232:J233) -> 4521700 | K235: =SUBTOTAL(9,K232:K233) -> 1775100 | L235: =SUBTOTAL(9,L232:L233) -> 0 | M235: =SUBTOTAL(9,M232:M233) -> 0 | N235: =SUBTOTAL(9,N232:N233) -> 0
A236: ALIMENTOS BENAL SAS | J236: Telefono: | K236: 3904031 | L236: Días Vencidos
A238: Tipo | B238: Numero | C238: Ven | D238: Factura | E238: Vencimiento | G238: Valor_Total | H238: Saldo | I238: Sin_Vencer | J238: 1_a_8 | K238: 9_a_15 | L238: 16_a_22 | M238: 23_a_30 | N238: >30
A239: 751 | B239: 18183 | C239: 4 | D239: 45996.269 | E239: 46026.268 | F239: 10 | G239: 5796300 | H239: 5796300 | I239: 0 | J239: 0 | K239: 5796300 | L239: 0 | M239: 0 | N239: 0
A240: 751 | B240: 18260 | C240: 4 | D240: 45997.589 | E240: 46027.589 | F240: 9 | G240: 7081600 | H240: 7081600 | I240: 0 | J240: 0 | K240: 7081600 | L240: 0 | M240: 0 | N240: 0
A241: 751 | B241: 18307 | C241: 4 | D241: 46000.561 | E241: 46030.561 | F241: 6 | G241: 97300 | H241: 97300 | I241: 0 | J241: 97300 | K241: 0 | L241: 0 | M241: 0 | N241: 0
A242: 751 | B242: 18332 | C242: 4 | D242: 46001.365 | E242: 46031.364 | F242: 5 | G242: 3973500 | H242: 3973500 | I242: 0 | J242: 3973500 | K242: 0 | L242: 0 | M242: 0 | N242: 0
A243: 751 | B243: 18371 | C243: 4 | D243: 46002.3 | E243: 46032.299 | F243: 4 | G243: 4460700 | H243: 4460700 | I243: 0 | J243: 4460700 | K243: 0 | L243: 0 | M243: 0 | N243: 0
A244: 751 | B244: 18396 | C244: 4 | D244: 46002.552 | E244: 46032.552 | F244: 4 | G244: 33600 | H244: 33600 | I244: 0 | J244: 33600 | K244: 0 | L244: 0 | M244: 0 | N244: 0
A245: 751 | B245: 18513 | C245: 4 | D245: 46006.312 | E245: 46036.312 | F245: 0 | G245: 6153000 | H245: 6153000 | I245: 6153000 | J245: 0 | K245: 0 | L245: 0 | M245: 0 | N245: 0
A246: 751 | B246: 18558 | C246: 4 | D246: 46007.542 | E246: 46037.536 | F246: -1 | G246: 7100800 | H246: 7100800 | I246: 7100800 | J246: 0 | K246: 0 | L246: 0 | M246: 0 | N246: 0
A247: 751 | B247: 18590 | C247: 4 | D247: 46008.36 | E247: 46038.36 | F247: -2 | G247: 882000 | H247: 882000 | I247: 882000 | J247: 0 | K247: 0 | L247: 0 | M247: 0 | N247: 0
A248: 751 | B248: 18629 | C248: 4 | D248: 46008.624 | E248: 46038.624 | F248: -2 | G248: 318000 | H248: 318000 | I248: 318000 | J248: 0 | K248: 0 | L248: 0 | M248: 0 | N248: 0
A249: 751 | B249: 18898 | C249: 4 | D249: 46017.213 | E249: 46047.213 | F249: -11 | G249: 11167200 | H249: 11167200 | I249: 11167200 | J249: 0 | K249: 0 | L249: 0 | M249: 0 | N249: 0
A250: 751 | B250: 18941 | C250: 4 | D250: 46018.508 | E250: 46048.508 | F250: -12 | G250: 4173600 | H250: 4173600 | I250: 4173600 | J250: 0 | K250: 0 | L250: 0 | M250: 0 | N250: 0
... A253: 751 | B253: 19039 | C253: 4 | D253: 46022.686 | E253: 46052.686 | F253: -16 | G253: 40950 | H253: 40950 | I253: 40950 | J253: 0 | K253: 0 | L253: 0 | M253: 0 | N253: 0
B254: Total: | D254: =SUBTOTAL(4,F239:F253) -> 10
G255: =SUBTOTAL(9,H239:H253) -> 51554700 | H255: =SUBTOTAL(9,I239:I253) -> 30111700 | I255: =SUBTOTAL(9,J239:J253) -> 8565100 | K255: =SUBTOTAL(9,K239:K253) -> 12877900 | L255: =SUBTOTAL(9,L239:L253) -> 0 | M255: =SUBTOTAL(9,M239:M253) -> 0 | N255: =SUBTOTAL(9,N239:N253) -> 0
A256: ALTO BISTRO SAS | J256: Telefono: | K256: 6017627135 | L256: Días Vencidos
A258: Tipo | B258: Numero | C258: Ven | D258: Factura | E258: Vencimiento | G258: Valor_Total | H258: Saldo | I258: Sin_Vencer | J258: 1_a_8 | K258: 9_a_15 | L258: 16_a_22 | M258: 23_a_30 | N258: >30
A259: 151 | B259: 22984 | C259: 4 | D259: 45996.352 | E259: 45997.346 | F259: 39 | G259: 357200 | H259: 339150 | I259: 0 | J259: 0 | K259: 0 | L259: 0 | M259: 0 | N259: 339150
A260: 151 | B260: 23324 | C260: 4 | D260: 46008.38 | E260: 46009.379 | F260: 27 | G260: 552900 | H260: 547200 | I260: 0 | J260: 0 | K260: 0 | L260: 0 | M260: 547200 | N260: 0
B261: Total: | D261: =SUBTOTAL(4,F259:F260) -> 39
G262: =SUBTOTAL(9,H259:H260) -> 886350 | H262: =SUBTOTAL(9,I259:I260) -> 0 | I262: =SUBTOTAL(9,J259:J260) -> 0 | K262: =SUBTOTAL(9,K259:K260) -> 0 | L262: =SUBTOTAL(9,L259:L260) -> 0 | M262: =SUBTOTAL(9,M259:M260) -> 547200 | N262: =SUBTOTAL(9,N259:N260) -> 339150
A263: ANA MARIA DANGOND | J263: Telefono: | K263: 3114816118 | L263: Días Vencidos
A265: Tipo | B265: Numero | C265: Ven | D265: Factura | E265: Vencimiento | G265: Valor_Total | H265: Saldo | I265: Sin_Vencer | J265: 1_a_8 | K265: 9_a_15 | L265: 16_a_22 | M265: 23_a_30 | N265: >30
A266: 751 | B266: 18401 | C266: 1 | D266: 46002.579 | E266: 46003.577 | F266: 33 | G266: 444600 | H266: 444600 | I266: 0 | J266: 0 | K266: 0 | L266: 0 | M266: 0 | N266: 444600
B267: Total: | D267: =SUBTOTAL(4,F266:F266) -> 33
G268: =SUBTOTAL(9,H266:H266) -> 444600 | H268: =SUBTOTAL(9,I266:I266) -> 0 | I268: =SUBTOTAL(9,J266:J266) -> 0 | K268: =SUBTOTAL(9,K266:K266) -> 0 | L268: =SUBTOTAL(9,L266:L266) -> 0 | M268: =SUBTOTAL(9,M266:M266) -> 0 | N268: =SUBTOTAL(9,N266:N266) -> 444600
A269: AVICOLA RENACER MC SAS | J269: Telefono: | K269: 3214254060 | L269: Días Vencidos
A271: Tipo | B271: Numero | C271: Ven | D271: Factura | E271: Vencimiento | G271: Valor_Total | H271: Saldo | I271: Sin_Vencer | J271: 1_a_8 | K271: 9_a_15 | L271: 16_a_22 | M271: 23_a_30 | N271: >30
A272: 151 | B272: 23750 | C272: 13 | D272: 46022.246 | E272: 46023.246 | F272: 13 | G272: 299360 | H272: 299360 | I272: 0 | J272: 0 | K272: 299360 | L272: 0 | M272: 0 | N272: 0
B273: Total: | D273: =SUBTOTAL(4,F272:F272) -> 13
G274: =SUBTOTAL(9,H272:H272) -> 299360 | H274: =SUBTOTAL(9,I272:I272) -> 0 | I274: =SUBTOTAL(9,J272:J272) -> 0 | K274: =SUBTOTAL(9,K272:K272) -> 299360 | L274: =SUBTOTAL(9,L272:L272) -> 0 | M274: =SUBTOTAL(9,M272:M272) -> 0 | N274: =SUBTOTAL(9,N272:N272) -> 0
A275: AZOTEA BARBECUE S.A.S. | J275: Telefono: | K275: 3143116000 | L275: Días Vencidos
A277: Tipo | B277: Numero | C277: Ven | D277: Factura | E277: Vencimiento | G277: Valor_Total | H277: Saldo | I277: Sin_Vencer | J277: 1_a_8 | K277: 9_a_15 | L277: 16_a_22 | M277: 23_a_30 | N277: >30
A278: 151 | B278: 23549 | C278: 11 | D278: 46014.35 | E278: 46022.35 | F278: 14 | G278: 98200 | H278: 98200 | I278: 0 | J278: 0 | K278: 98200 | L278: 0 | M278: 0 | N278: 0
...

Sheet Datos (3)
A11: Forma de Pago | B11: Fecha | C11: Tipo | D11: Documento | E11: Numero | F11: Valor | G11: Asociado | H11: Usuario
A12: COLPATRIA | B12: 45995 | C12: 707 | D12: Recibos de Caja Galan | E12: 7743 | F12: 73803088 | G12: 0 | H12: OFICINA
A13: COLPATRIA | B13: 45995 | C13: 707 | D13: Recibos de Caja Galan | E13: 7750 | F13: 2908500 | G13: 0 | H13: OFICINA
A14: Datafono | B14: 45996.274 | C14: 155 | D14: Venta Electronica POS LOM | E14: 56985 | F14: 339763 | G14: 0 | H14: CAJAL2
A15: Datafono | B15: 45992.324 | C15: 155 | D15: Venta Electronica POS LOM | E15: 56765 | F15: 115864 | G15: 0 | H15: caja1
A16: Datafono | B16: 45992.328 | C16: 155 | D16: Venta Electronica POS LOM | E16: 56766 | F16: 64760 | G16: 0 | H16: caja1
A17: Datafono | B17: 45992.441 | C17: 155 | D17: Venta Electronica POS LOM | E17: 56777 | F17: 20160 | G17: 0 | H17: CAJAL3
A18: Datafono | B18: 45992.446 | C18: 155 | D18: Venta Electronica POS LOM | E18: 56778 | F18: 65376 | G18: 0 | H18: CAJAL3
A19: Datafono | B19: 45992.38 | C19: 155 | D19: Venta Electronica POS LOM | E19: 56771 | F19: 42580 | G19: 0 | H19: CAJAL3
A20: Datafono | B20: 45992.387 | C20: 155 | D20: Venta Electronica POS LOM | E20: 56772 | F20: 105948 | G20: 0 | H20: CAJAL3
A21: Datafono | B21: 45993.2 | C21: 155 | D21: Venta Electronica POS LOM | E21: 56785 | F21: 302698 | G21: 0 | H21: CAJAL2
A22: Datafono | B22: 45993.223 | C22: 155 | D22: Venta Electronica POS LOM | E22: 56789 | F22: 112892 | G22: 0 | H22: CAJAL2
A23: Datafono | B23: 45993.269 | C23: 155 | D23: Venta Electronica POS LOM | E23: 56797 | F23: 186280 | G23: 0 | H23: CAJAL2
... A1088: Transferencia Bancolombia | B1088: 45995.61 | C1088: 755 | D1088: Venta Electronica POS M.GALAN | E1088: 75969 | F1088: 30005 | G1088: 0 | H1088: CAJAG4

Sheet Datos (2)
I1: Inversiones Agropecuarias Lom SAS
I4: 901399676-1
I5: AV CIUDAD DE CALI15A -91 LOCAL A19 - A20
I7: Cartera Por Edades
A9: Cliente | B9: Tipo | C9: Numero | D9: Ven | E9: Factura | F9: Vencimiento | H9: Valor_Total | I9: Saldo | J9: Sin_Vencer | K9: 1_a_8 | L9: 9_a_15 | M9: 16_a_22 | N9: 23_a_30 | O9: >30
A10: 4G FOOD SAS | B10: 751 | C10: 18568 | D10: 8 | E10: 46007 | F10: 46022 | G10: -7 | H10: 1128900 | I10: 1128900 | J10: 1128900 | K10: 0 | L10: 0 | M10: 0 | N10: 0 | O10: 0
A11: 4G FOOD SAS | B11: 751 | C11: 18708 | D11: 8 | E11: 46010 | F11: 46025 | G11: -10 | H11: 524700 | I11: 524700 | J11: 524700 | K11: 0 | L11: 0 | M11: 0 | N11: 0 | O11: 0
A12: A MANO SAS | B12: 751 | C12: 18742 | D12: 4 | E12: 46011 | F12: 46019 | G12: -4 | H12: 354200 | I12: 354200 | J12: 354200 | K12: 0 | L12: 0 | M12: 0 | N12: 0 | O12: 0
A13: A TEAM CG SAS | B13: 151 | C13: 22568 | D13: 3 | E13: 45982 | F13: 46012 | G13: 3 | H13: 461500 | I13: 461500 | J13: 0 | K13: 461500 | L13: 0 | M13: 0 | N13: 0 | O13: 0
A14: A TEAM CG SAS | B14: 151 | C14: 22700 | D14: 3 | E14: 45987 | F14: 46017 | G14: -2 | H14: 248400 | I14: 248400 | J14: 248400 | K14: 0 | L14: 0 | M14: 0 | N14: 0 | O14: 0
A15: A TEAM CG SAS | B15: 151 | C15: 22763 | D15: 3 | E15: 45989 | F15: 46019 | G15: -4 | H15: 158900 | I15: 158900 | J15: 158900 | K15: 0 | L15: 0 | M15: 0 | N15: 0 | O15: 0
A16: A TEAM CG SAS | B16: 151 | C16: 22783 | D16: 3 | E16: 45990 | F16: 46020 | G16: -5 | H16: 800600 | I16: 800600 | J16: 800600 | K16: 0 | L16: 0 | M16: 0 | N16: 0 | O16: 0
A17: A TEAM CG SAS | B17: 151 | C17: 22942 | D17: 3 | E17: 45995 | F17: 46025 | G17: -10 | H17: 260000 | I17: 260000 | J17: 260000 | K17: 0 | L17: 0 | M17: 0 | N17: 0 | O17: 0
A18: A TEAM CG SAS | B18: 151 | C18: 23011 | D18: 3 | E18: 45997 | F18: 46027 | G18: -12 | H18: 464600 | I18: 464600 | J18: 464600 | K18: 0 | L18: 0 | M18: 0 | N18: 0 | O18: 0
A19: A TEAM CG SAS | B19: 151 | C19: 23072 | D19: 3 | E19: 46000 | F19: 46030 | G19: -15 | H19: 304500 | I19: 304500 | J19: 304500 | K19: 0 | L19: 0 | M19: 0 | N19: 0 | O19: 0
A20: A TEAM CG SAS | B20: 151 | C20: 23474 | D20: 3 | E20: 46011 | F20: 46041 | G20: -26 | H20: 154900 | I20: 154900 | J20: 154900 | K20: 0 | L20: 0 | M20: 0 | N20: 0 | O20: 0
A21: ABDONINO POLOCHE BOSOS | B21: 751 | C21: 18767 | D21: 7 | E21: 46011 | F21: 46012 | G21: 3 | H21: 49990 | I21: 49990 | J21: 0 | K21: 49990 | L21: 0 | M21: 0 | N21: 0 | O21: 0
... A1568: YUDY CATERINY MORALES ROJAS | B1568: 151 | C1568: 23575 | D1568: 13 | E1568: 46015 | F1568: 46016 | G1568: -1 | H1568: 130500 | I1568: 130500 | J1568: 130500 | K1568: 0 | L1568: 0 | M1568: 0 | N1568: 0 | O1568: 0

Sheet Cartera por edades
A1: Cartera Por Edades | E1: Fecha actual | F1: =+TODAY() -> 46044
E2: Fecha cartera | F2: 46022
A5: =SI([@Tipo]>0;B13;"") | H5: =700000000/320 -> 2187500 | I5: 434332
A6: Nombre tercero | B6: Tipo | C6: Numero FAC | D6: V | E6: Emision | F6: Vencimiento | G6: Dias | H6: Valor_Total | I6: Saldo | J6: Sin_Vencer | K6: 1_a_8 | L6: 9_a_15 | M6: 16_a_22 | N6: 23_a_30 | O6: >30 | P6: Total vencido | Q6: De 9 a 30 | R6: Mas de 9 | S6: Dias >9 | T6: Mas de 100 | U6: Dias >100 | V6: Plazo cliente | W6: Local | X6: Vendedor | Y6: Revisar
A7: 4G FOOD SAS | B7: 751 | C7: 18568 | D7: 8 | E7: 46007.561 | F7: 46022.561 | G7: 14 | H7: 1128900 | I7: 1128900 | J7: 0 | K7: 0 | L7: 1128900 | M7: 0 | N7: 0 | O7: 0 | P7: =SUM(Cartera[[#This Row],[1_a_8]:[>30]]) -> 1128900 | Q7: =+Cartera[[#This Row],[9_a_15]]+Cartera[[#This Row],[16_a_22]]+Cartera[[#This Row],[23_a_30]] -> 1128900 | R7: =IF(Cartera[[#This Row],[Dias]]>8,Cartera[[#This Row],[Total vencido]],0) -> 1128900 | S7: =IF(Cartera[[#This Row],[Mas de 9]]>0,Cartera[[#This Row],[Dias]],0) -> 14 | T7: =IF(Cartera[[#This Row],[Dias]]>99,Cartera[[#This Row],[Total vencido]],0) -> 0 | U7: =IF(Cartera[[#This Row],[Mas de 100]]>0,Cartera[[#This Row],[Dias]],0) -> 0 | V7: =Cartera[[#This Row],[Vencimiento]]-Cartera[[#This Row],[Emision]] -> 14.999861 | W7: =+IF(Cartera[[#This Row],[Tipo]]=151,"Lom",IF(Cartera[[#This Row],[Tipo]]=153,"Lom",IF(Cartera[[#This Row],[Tipo]]=155,"Lom",IF(Cartera[[#This Row],[Tipo]]=200,"Lom",IF(Cartera[[#This Row],[Tipo]]=224,"Lom",IF(Cartera[[#This Row],[Tipo]]=251,"Lom",IF(Cartera[[#This Row],[Tipo]]=651,"Magra",IF(Cartera[[#This Row],[Tipo]]=655,"Magra",IF(Cartera[[#This Row],[Tipo]]=601,"Magra",IF(Cartera[[#This Row],[Tipo]]=751,"Galan",IF(Cartera[[#This Row],[Tipo]]=757,"Galan",IF(Cartera[[#This Row],[Tipo]]=701,"Galan",IF(Cartera[[#This Row],[Tipo]]=755,"Galan",IF(Cartera[[#This Row],[Tipo]]="CO","Conciliacion Cartera","")))))))))))))) | X7: =_xlfn.XLOOKUP(Cartera[[#This Row],[Nombre tercero]],Vendedor[Nombre],Vendedor[Vendedor],"",0,-1) -> WILLIAM DARIO PADILLA
A8: =+A7 -> 4G FOOD SAS | B8: 751 | C8: 18708 | D8: 8 | E8: 46010.552 | F8: 46025.552 | G8: 11 | H8: 524700 | I8: 524700 | J8: 0 | K8: 0 | L8: 524700 | M8: 0 | N8: 0 | O8: 0 | P8: =SUM(Cartera[[#This Row],[1_a_8]:[>30]]) -> 524700 | Q8: =+Cartera[[#This Row],[9_a_15]]+Cartera[[#This Row],[16_a_22]]+Cartera[[#This Row],[23_a_30]] -> 524700 | R8: =IF(Cartera[[#This Row],[Dias]]>8,Cartera[[#This Row],[Total vencido]],0) -> 524700 | S8: =IF(Cartera[[#This Row],[Mas de 9]]>0,Cartera[[#This Row],[Dias]],0) -> 11 | T8: =IF(Cartera[[#This Row],[Dias]]>99,Cartera[[#This Row],[Total vencido]],0) -> 0 | U8: =IF(Cartera[[#This Row],[Mas de 100]]>0,Cartera[[#This Row],[Dias]],0) -> 0 | V8: =Cartera[[#This Row],[Vencimiento]]-Cartera[[#This Row],[Emision]] -> 14.999757 | W8: =+IF(Cartera[[#This Row],[Tipo]]=151,"Lom",IF(Cartera[[#This Row],[Tipo]]=153,"Lom",IF(Cartera[[#This Row],[Tipo]]=155,"Lom",IF(Cartera[[#This Row],[Tipo]]=200,"Lom",IF(Cartera[[#This Row],[Tipo]]=224,"Lom",IF(Cartera[[#This Row],[Tipo]]=251,"Lom",IF(Cartera[[#This Row],[Tipo]]=651,"Magra",IF(Cartera[[#This Row],[Tipo]]=655,"Magra",IF(Cartera[[#This Row],[Tipo]]=601,"Magra",IF(Cartera[[#This Row],[Tipo]]=751,"Galan",IF(Cartera[[#This Row],[Tipo]]=757,"Galan",IF(Cartera[[#This Row],[Tipo]]=701,"Galan",IF(Cartera[[#This Row],[Tipo]]=755,"Galan",IF(Cartera[[#This Row],[Tipo]]="CO","Conciliacion Cartera","")))))))))))))) | X8: =_xlfn.XLOOKUP(Cartera[[#This Row],[Nombre tercero]],Vendedor[Nombre],Vendedor[Vendedor],"",0,-1) -> WILLIAM DARIO PADILLA
A9: =+A8 -> 4G FOOD SAS | B9: 751 | C9: 18988 | D9: 8 | E9: 46020.562 | F9: 46035.561 | G9: 1 | H9: 816200 | I9: 816200 | J9: 0 | K9: 816200 | L9: 0 | M9: 0 | N9: 0 | O9: 0 | P9: =SUM(Cartera[[#This Row],[1_a_8]:[>30]]) -> 816200 | Q9: =+Cartera[[#This Row],[9_a_15]]+Cartera[[#This Row],[16_a_22]]+Cartera[[#This Row],[23_a_30]] -> 0 | R9: =IF(Cartera[[#This Row],[Dias]]>8,Cartera[[#This Row],[Total vencido]],0) -> 0 | S9: =IF(Cartera[[#This Row],[Mas de 9]]>0,Cartera[[#This Row],[Dias]],0) -> 0 | T9: =IF(Cartera[[#This Row],[Dias]]>99,Cartera[[#This Row],[Total vencido]],0) -> 0 | U9: =IF(Cartera[[#This Row],[Mas de 100]]>0,Cartera[[#This Row],[Dias]],0) -> 0 | V9: =Cartera[[#This Row],[Vencimiento]]-Cartera[[#This Row],[Emision]] -> 14.999005 | W9: =+IF(Cartera[[#This Row],[Tipo]]=151,"Lom",IF(Cartera[[#This Row],[Tipo]]=153,"Lom",IF(Cartera[[#This Row],[Tipo]]=155,"Lom",IF(Cartera[[#This Row],[Tipo]]=200,"Lom",IF(Cartera[[#This Row],[Tipo]]=224,"Lom",IF(Cartera[[#This Row],[Tipo]]=251,"Lom",IF(Cartera[[#This Row],[Tipo]]=651,"Magra",IF(Cartera[[#This Row],[Tipo]]=655,"Magra",IF(Cartera[[#This Row],[Tipo]]=601,"Magra",IF(Cartera[[#This Row],[Tipo]]=751,"Galan",IF(Cartera[[#This Row],[Tipo]]=757,"Galan",IF(Cartera[[#This Row],[Tipo]]=701,"Galan",IF(Cartera[[#This Row],[Tipo]]=755,"Galan",IF(Cartera[[#This Row],[Tipo]]="CO","Conciliacion Cartera","")))))))))))))) | X9: =_xlfn.XLOOKUP(Cartera[[#This Row],[Nombre tercero]],Vendedor[Nombre],Vendedor[Vendedor],"",0,-1) -> WILLIAM DARIO PADILLA
A10: A TEAM CG SAS | B10: 151 | C10: 22568 | D10: 3 | E10: 45982.405 | F10: 46012.404 | G10: 24 | H10: 461500 | I10: 461500 | J10: 0 | K10: 0 | L10: 0 | M10: 0 | N10: 461500 | O10: 0 | P10: =SUM(Cartera[[#This Row],[1_a_8]:[>30]]) -> 461500 | Q10: =+Cartera[[#This Row],[9_a_15]]+Cartera[[#This Row],[16_a_22]]+Cartera[[#This Row],[23_a_30]] -> 461500 | R10: =IF(Cartera[[#This Row],[Dias]]>8,Cartera[[#This Row],[Total vencido]],0) -> 461500 | S10: =IF(Cartera[[#This Row],[Mas de 9]]>0,Cartera[[#This Row],[Dias]],0) -> 24 | T10: =IF(Cartera[[#This Row],[Dias]]>99,Cartera[[#This Row],[Total vencido]],0) -> 0 | U10: =IF(Cartera[[#This Row],[Mas de 100]]>0,Cartera[[#This Row],[Dias]],0) -> 0 | V10: =Cartera[[#This Row],[Vencimiento]]-Cartera[[#This Row],[Emision]] -> 29.998819 | W10: =+IF(Cartera[[#This Row],[Tipo]]=151,"Lom",IF(Cartera[[#This Row],[Tipo]]=153,"Lom",IF(Cartera[[#This Row],[Tipo]]=155,"Lom",IF(Cartera[[#This Row],[Tipo]]=200,"Lom",IF(Cartera[[#This Row],[Tipo]]=224,"Lom",IF(Cartera[[#This Row],[Tipo]]=251,"Lom",IF(Cartera[[#This Row],[Tipo]]=651,"Magra",IF(Cartera[[#This Row],[Tipo]]=655,"Magra",IF(Cartera[[#This Row],[Tipo]]=601,"Magra",IF(Cartera[[#This Row],[Tipo]]=751,"Galan",IF(Cartera[[#This Row],[Tipo]]=757,"Galan",IF(Cartera[[#This Row],[Tipo]]=701,"Galan",IF(Cartera[[#This Row],[Tipo]]=755,"Galan",IF(Cartera[[#This Row],[Tipo]]="CO","Conciliacion Cartera","")))))))))))))) | X10: =_xlfn.XLOOKUP(Cartera[[#This Row],[Nombre tercero]],Vendedor[Nombre],Vendedor[Vendedor],"",0,-1) -> ANGELA SILVESTRE | Y10: BONO
A11: =+A10 -> A TEAM CG SAS | B11: 151 | C11: 22700 | D11: 3 | E11: 45987.306 | F11: 46017.305 | G11: 19 | H11: 248400 | I11: 248400 | J11: 0 | K11: 0 | L11: 0 | M11: 248400 | N11: 0 | O11: 0 | P11: =SUM(Cartera[[#This Row],[1_a_8]:[>30]]) -> 248400 | Q11: =+Cartera[[#This Row],[9_a_15]]+Cartera[[#This Row],[16_a_22]]+Cartera[[#This Row],[23_a_30]] -> 248400 | R11: =IF(Cartera[[#This Row],[Dias]]>8,Cartera[[#This Row],[Total vencido]],0) -> 248400 | S11: =IF(Cartera[[#This Row],[Mas de 9]]>0,Cartera[[#This Row],[Dias]],0) -> 19 | T11: =IF(Cartera[[#This Row],[Dias]]>99,Cartera[[#This Row],[Total vencido]],0) -> 0 | U11: =IF(Cartera[[#This Row],[Mas de 100]]>0,Cartera[[#This Row],[Dias]],0) -> 0 | V11: =Cartera[[#This Row],[Vencimiento]]-Cartera[[#This Row],[Emision]] -> 29.99963 | W11: =+IF(Cartera[[#This Row],[Tipo]]=151,"Lom",IF(Cartera[[#This Row],[Tipo]]=153,"Lom",IF(Cartera[[#This Row],[Tipo]]=155,"Lom",IF(Cartera[[#This Row],[Tipo]]=200,"Lom",IF(Cartera[[#This Row],[Tipo]]=224,"Lom",IF(Cartera[[#This Row],[Tipo]]=251,"Lom",IF(Cartera[[#This Row],[Tipo]]=651,"Magra",IF(Cartera[[#This Row],[Tipo]]=655,"Magra",IF(Cartera[[#This Row],[Tipo]]=601,"Magra",IF(Cartera[[#This Row],[Tipo]]=751,"Galan",IF(Cartera[[#This Row],[Tipo]]=757,"Galan",IF(Cartera[[#This Row],[Tipo]]=701,"Galan",IF(Cartera[[#This Row],[Tipo]]=755,"Galan",IF(Cartera[[#This Row],[Tipo]]="CO","Conciliacion Cartera","")))))))))))))) | X11: =_xlfn.XLOOKUP(Cartera[[#This Row],[Nombre tercero]],Vendedor[Nombre],Vendedor[Vendedor],"",0,-1) -> ANGELA SILVESTRE
A12: =+A11 -> A TEAM CG SAS | B12: 151 | C12: 22763 | D12: 3 | E12: 45989.345 | F12: 46019.345 | G12: 17 | H12: 158900 | I12: 158900 | J12: 0 | K12: 0 | L12: 0 | M12: 158900 | N12: 0 | O12: 0 | P12: =SUM(Cartera[[#This Row],[1_a_8]:[>30]]) -> 158900 | Q12: =+Cartera[[#This Row],[9_a_15]]+Cartera[[#This Row],[16_a_22]]+Cartera[[#This Row],[23_a_30]] -> 158900 | R12: =IF(Cartera[[#This Row],[Dias]]>8,Cartera[[#This Row],[Total vencido]],0) -> 158900 | S12: =IF(Cartera[[#This Row],[Mas de 9]]>0,Cartera[[#This Row],[Dias]],0) -> 17 | T12: =IF(Cartera[[#This Row],[Dias]]>99,Cartera[[#This Row],[Total vencido]],0) -> 0 | U12: =IF(Cartera[[#This Row],[Mas de 100]]>0,Cartera[[#This Row],[Dias]],0) -> 0 | V12: =Cartera[[#This Row],[Vencimiento]]-Cartera[[#This Row],[Emision]] -> 29.99985 | W12: =+IF(Cartera[[#This Row],[Tipo]]=151,"Lom",IF(Cartera[[#This Row],[Tipo]]=153,"Lom",IF(Cartera[[#This Row],[Tipo]]=155,"Lom",IF(Cartera[[#This Row],[Tipo]]=200,"Lom",IF(Cartera[[#This Row],[Tipo]]=224,"Lom",IF(Cartera[[#This Row],[Tipo]]=251,"Lom",IF(Cartera[[#This Row],[Tipo]]=651,"Magra",IF(Cartera[[#This Row],[Tipo]]=655,"Magra",IF(Cartera[[#This Row],[Tipo]]=601,"Magra",IF(Cartera[[#This Row],[Tipo]]=751,"Galan",IF(Cartera[[#This Row],[Tipo]]=757,"Galan",IF(Cartera[[#This Row],[Tipo]]=701,"Galan",IF(Cartera[[#This Row],[Tipo]]=755,"Galan",IF(Cartera[[#This Row],[Tipo]]="CO","Conciliacion Cartera","")))))))))))))) | X12: =_xlfn.XLOOKUP(Cartera[[#This Row],[Nombre tercero]],Vendedor[Nombre],Vendedor[Vendedor],"",0,-1) -> ANGELA SILVESTRE
A13: =+A12 -> A TEAM CG SAS | B13: 151 | C13: 22783 | D13: 3 | E13: 45990.292 | F13: 46020.29 | G13: 16 | H13: 800600 | I13: 800600 | J13: 0 | K13: 0 | L13: 0 | M13: 800600 | N13: 0 | O13: 0 | P13: =SUM(Cartera[[#This Row],[1_a_8]:[>30]]) -> 800600 | Q13: =+Cartera[[#This Row],[9_a_15]]+Cartera[[#This Row],[16_a_22]]+Cartera[[#This Row],[23_a_30]] -> 800600 | R13: =IF(Cartera[[#This Row],[Dias]]>8,Cartera[[#This Row],[Total vencido]],0) -> 800600 | S13: =IF(Cartera[[#This Row],[Mas de 9]]>0,Cartera[[#This Row],[Dias]],0) -> 16 | T13: =IF(Cartera[[#This Row],[Dias]]>99,Cartera[[#This Row],[Total vencido]],0) -> 0 | U13: =IF(Cartera[[#This Row],[Mas de 100]]>0,Cartera[[#This Row],[Dias]],0) -> 0 | V13: =Cartera[[#This Row],[Vencimiento]]-Cartera[[#This Row],[Emision]] -> 29.99794 | W13: =+IF(Cartera[[#This Row],[Tipo]]=151,"Lom",IF(Cartera[[#This Row],[Tipo]]=153,"Lom",IF(Cartera[[#This Row],[Tipo]]=155,"Lom",IF(Cartera[[#This Row],[Tipo]]=200,"Lom",IF(Cartera[[#This Row],[Tipo]]=224,"Lom",IF(Cartera[[#This Row],[Tipo]]=251,"Lom",IF(Cartera[[#This Row],[Tipo]]=651,"Magra",IF(Cartera[[#This Row],[Tipo]]=655,"Magra",IF(Cartera[[#This Row],[Tipo]]=601,"Magra",IF(Cartera[[#This Row],[Tipo]]=751,"Galan",IF(Cartera[[#This Row],[Tipo]]=757,"Galan",IF(Cartera[[#This Row],[Tipo]]=701,"Galan",IF(Cartera[[#This Row],[Tipo]]=755,"Galan",IF(Cartera[[#This Row],[Tipo]]="CO","Conciliacion Cartera","")))))))))))))) | X13: =_xlfn.XLOOKUP(Cartera[[#This Row],[Nombre tercero]],Vendedor[Nombre],Vendedor[Vendedor],"",0,-1) -> ANGELA SILVESTRE
A14: =+A13 -> A TEAM CG SAS | B14: 151 | C14: 22942 | D14: 3 | E14: 45995.275 | F14: 46025.275 | G14: 11 | H14: 260000 | I14: 260000 | J14: 0 | K14: 0 | L14: 260000 | M14: 0 | N14: 0 | O14: 0 | P14: =SUM(Cartera[[#This Row],[1_a_8]:[>30]]) -> 260000 | Q14: =+Cartera[[#This Row],[9_a_15]]+Cartera[[#This Row],[16_a_22]]+Cartera[[#This Row],[23_a_30]] -> 260000 | R14: =IF(Cartera[[#This Row],[Dias]]>8,Cartera[[#This Row],[Total vencido]],0) -> 260000 | S14: =IF(Cartera[[#This Row],[Mas de 9]]>0,Cartera[[#This Row],[Dias]],0) -> 11 | T14: =IF(Cartera[[#This Row],[Dias]]>99,Cartera[[#This Row],[Total vencido]],0) -> 0 | U14: =IF(Cartera[[#This Row],[Mas de 100]]>0,Cartera[[#This Row],[Dias]],0) -> 0 | V14: =Cartera[[#This Row],[Vencimiento]]-Cartera[[#This Row],[Emision]] -> 29.999884 | W14: =+IF(Cartera[[#This Row],[Tipo]]=151,"Lom",IF(Cartera[[#This Row],[Tipo]]=153,"Lom",IF(Cartera[[#This Row],[Tipo]]=155,"Lom",IF(Cartera[[#This Row],[Tipo]]=200,"Lom",IF(Cartera[[#This Row],[Tipo]]=224,"Lom",IF(Cartera[[#This Row],[Tipo]]=251,"Lom",IF(Cartera[[#This Row],[Tipo]]=651,"Magra",IF(Cartera[[#This Row],[Tipo]]=655,"Magra",IF(Cartera[[#This Row],[Tipo]]=601,"Magra",IF(Cartera[[#This Row],[Tipo]]=751,"Galan",IF(Cartera[[#This Row],[Tipo]]=757,"Galan",IF(Cartera[[#This Row],[Tipo]]=701,"Galan",IF(Cartera[[#This Row],[Tipo]]=755,"Galan",IF(Cartera[[#This Row],[Tipo]]="CO","Conciliacion Cartera","")))))))))))))) | X14: =_xlfn.XLOOKUP(Cartera[[#This Row],[Nombre tercero]],Vendedor[Nombre],Vendedor[Vendedor],"",0,-1) -> ANGELA SILVESTRE
A15: =+A14 -> A TEAM CG SAS | B15: 151 | C15: 23011 | D15: 3 | E15: 45997.255 | F15: 46027.255 | G15: 9 | H15: 464600 | I15: 464600 | J15: 0 | K15: 0 | L15: 464600 | M15: 0 | N15: 0 | O15: 0 | P15: =SUM(Cartera[[#This Row],[1_a_8]:[>30]]) -> 464600 | Q15: =+Cartera[[#This Row],[9_a_15]]+Cartera[[#This Row],[16_a_22]]+Cartera[[#This Row],[23_a_30]] -> 464600 | R15: =IF(Cartera[[#This Row],[Dias]]>8,Cartera[[#This Row],[Total vencido]],0) -> 464600 | S15: =IF(Cartera[[#This Row],[Mas de 9]]>0,Cartera[[#This Row],[Dias]],0) -> 9 | T15: =IF(Cartera[[#This Row],[Dias]]>99,Cartera[[#This Row],[Total vencido]],0) -> 0 | U15: =IF(Cartera[[#This Row],[Mas de 100]]>0,Cartera[[#This Row],[Dias]],0) -> 0 | V15: =Cartera[[#This Row],[Vencimiento]]-Cartera[[#This Row],[Emision]] -> 29.999873 | W15: =+IF(Cartera[[#This Row],[Tipo]]=151,"Lom",IF(Cartera[[#This Row],[Tipo]]=153,"Lom",IF(Cartera[[#This Row],[Tipo]]=155,"Lom",IF(Cartera[[#This Row],[Tipo]]=200,"Lom",IF(Cartera[[#This Row],[Tipo]]=224,"Lom",IF(Cartera[[#This Row],[Tipo]]=251,"Lom",IF(Cartera[[#This Row],[Tipo]]=651,"Magra",IF(Cartera[[#This Row],[Tipo]]=655,"Magra",IF(Cartera[[#This Row],[Tipo]]=601,"Magra",IF(Cartera[[#This Row],[Tipo]]=751,"Galan",IF(Cartera[[#This Row],[Tipo]]=757,"Galan",IF(Cartera[[#This Row],[Tipo]]=701,"Galan",IF(Cartera[[#This Row],[Tipo]]=755,"Galan",IF(Cartera[[#This Row],[Tipo]]="CO","Conciliacion Cartera","")))))))))))))) | X15: =_xlfn.XLOOKUP(Cartera[[#This Row],[Nombre tercero]],Vendedor[Nombre],Vendedor[Vendedor],"",0,-1) -> ANGELA SILVESTRE
A16: =+A15 -> A TEAM CG SAS | B16: 151 | C16: 23072 | D16: 3 | E16: 46000.337 | F16: 46030.337 | G16: 6 | H16: 304500 | I16: 304500 | J16: 0 | K16: 304500 | L16: 0 | M16: 0 | N16: 0 | O16: 0 | P16: =SUM(Cartera[[#This Row],[1_a_8]:[>30]]) -> 304500 | Q16: =+Cartera[[#This Row],[9_a_15]]+Cartera[[#This Row],[16_a_22]]+Cartera[[#This Row],[23_a_30]] -> 0 | R16: =IF(Cartera[[#This Row],[Dias]]>8,Cartera[[#This Row],[Total vencido]],0) -> 0 | S16: =IF(Cartera[[#This Row],[Mas de 9]]>0,Cartera[[#This Row],[Dias]],0) -> 0 | T16: =IF(Cartera[[#This Row],[Dias]]>99,Cartera[[#This Row],[Total vencido]],0) -> 0 | U16: =IF(Cartera[[#This Row],[Mas de 100]]>0,Cartera[[#This Row],[Dias]],0) -> 0 | V16: =Cartera[[#This Row],[Vencimiento]]-Cartera[[#This Row],[Emision]] -> 29.999884 | W16: =+IF(Cartera[[#This Row],[Tipo]]=151,"Lom",IF(Cartera[[#This Row],[Tipo]]=153,"Lom",IF(Cartera[[#This Row],[Tipo]]=155,"Lom",IF(Cartera[[#This Row],[Tipo]]=200,"Lom",IF(Cartera[[#This Row],[Tipo]]=224,"Lom",IF(Cartera[[#This Row],[Tipo]]=251,"Lom",IF(Cartera[[#This Row],[Tipo]]=651,"Magra",IF(Cartera[[#This Row],[Tipo]]=655,"Magra",IF(Cartera[[#This Row],[Tipo]]=601,"Magra",IF(Cartera[[#This Row],[Tipo]]=751,"Galan",IF(Cartera[[#This Row],[Tipo]]=757,"Galan",IF(Cartera[[#This Row],[Tipo]]=701,"Galan",IF(Cartera[[#This Row],[Tipo]]=755,"Galan",IF(Cartera[[#This Row],[Tipo]]="CO","Conciliacion Cartera","")))))))))))))) | X16: =_xlfn.XLOOKUP(Cartera[[#This Row],[Nombre tercero]],Vendedor[Nombre],Vendedor[Vendedor],"",0,-1) -> ANGELA SILVESTRE
A17: =+A16 -> A TEAM CG SAS | B17: 151 | C17: 23474 | D17: 3 | E17: 46011.331 | F17: 46041.33 | G17: -5 | H17: 154900 | I17: 154900 | J17: 154900 | K17: 0 | L17: 0 | M17: 0 | N17: 0 | O17: 0 | P17: =SUM(Cartera[[#This Row],[1_a_8]:[>30]]) -> 0 | Q17: =+Cartera[[#This Row],[9_a_15]]+Cartera[[#This Row],[16_a_22]]+Cartera[[#This Row],[23_a_30]] -> 0 | R17: =IF(Cartera[[#This Row],[Dias]]>8,Cartera[[#This Row],[Total vencido]],0) -> 0 | S17: =IF(Cartera[[#This Row],[Mas de 9]]>0,Cartera[[#This Row],[Dias]],0) -> 0 | T17: =IF(Cartera[[#This Row],[Dias]]>99,Cartera[[#This Row],[Total vencido]],0) -> 0 | U17: =IF(Cartera[[#This Row],[Mas de 100]]>0,Cartera[[#This Row],[Dias]],0) -> 0 | V17: =Cartera[[#This Row],[Vencimiento]]-Cartera[[#This Row],[Emision]] -> 29.999792 | W17: =+IF(Cartera[[#This Row],[Tipo]]=151,"Lom",IF(Cartera[[#This Row],[Tipo]]=153,"Lom",IF(Cartera[[#This Row],[Tipo]]=155,"Lom",IF(Cartera[[#This Row],[Tipo]]=200,"Lom",IF(Cartera[[#This Row],[Tipo]]=224,"Lom",IF(Cartera[[#This Row],[Tipo]]=251,"Lom",IF(Cartera[[#This Row],[Tipo]]=651,"Magra",IF(Cartera[[#This Row],[Tipo]]=655,"Magra",IF(Cartera[[#This Row],[Tipo]]=601,"Magra",IF(Cartera[[#This Row],[Tipo]]=751,"Galan",IF(Cartera[[#This Row],[Tipo]]=757,"Galan",IF(Cartera[[#This Row],[Tipo]]=701,"Galan",IF(Cartera[[#This Row],[Tipo]]=755,"Galan",IF(Cartera[[#This Row],[Tipo]]="CO","Conciliacion Cartera","")))))))))))))) | X17: =_xlfn.XLOOKUP(Cartera[[#This Row],[Nombre tercero]],Vendedor[Nombre],Vendedor[Vendedor],"",0,-1) -> ANGELA SILVESTRE
A18: =+A17 -> A TEAM CG SAS | B18: 151 | C18: 23695 | D18: 3 | E18: 46020.184 | F18: 46050.184 | G18: -14 | H18: 219700 | I18: 219700 | J18: 219700 | K18: 0 | L18: 0 | M18: 0 | N18: 0 | O18: 0 | P18: =SUM(Cartera[[#This Row],[1_a_8]:[>30]]) -> 0 | Q18: =+Cartera[[#This Row],[9_a_15]]+Cartera[[#This Row],[16_a_22]]+Cartera[[#This Row],[23_a_30]] -> 0 | R18: =IF(Cartera[[#This Row],[Dias]]>8,Cartera[[#This Row],[Total vencido]],0) -> 0 | S18: =IF(Cartera[[#This Row],[Mas de 9]]>0,Cartera[[#This Row],[Dias]],0) -> 0 | T18: =IF(Cartera[[#This Row],[Dias]]>99,Cartera[[#This Row],[Total vencido]],0) -> 0 | U18: =IF(Cartera[[#This Row],[Mas de 100]]>0,Cartera[[#This Row],[Dias]],0) -> 0 | V18: =Cartera[[#This Row],[Vencimiento]]-Cartera[[#This Row],[Emision]] -> 29.999757 | W18: =+IF(Cartera[[#This Row],[Tipo]]=151,"Lom",IF(Cartera[[#This Row],[Tipo]]=153,"Lom",IF(Cartera[[#This Row],[Tipo]]=155,"Lom",IF(Cartera[[#This Row],[Tipo]]=200,"Lom",IF(Cartera[[#This Row],[Tipo]]=224,"Lom",IF(Cartera[[#This Row],[Tipo]]=251,"Lom",IF(Cartera[[#This Row],[Tipo]]=651,"Magra",IF(Cartera[[#This Row],[Tipo]]=655,"Magra",IF(Cartera[[#This Row],[Tipo]]=601,"Magra",IF(Cartera[[#This Row],[Tipo]]=751,"Galan",IF(Cartera[[#This Row],[Tipo]]=757,"Galan",IF(Cartera[[#This Row],[Tipo]]=701,"Galan",IF(Cartera[[#This Row],[Tipo]]=755,"Galan",IF(Cartera[[#This Row],[Tipo]]="CO","Conciliacion Cartera","")))))))))))))) | X18: =_xlfn.XLOOKUP(Cartera[[#This Row],[Nombre tercero]],Vendedor[Nombre],Vendedor[Vendedor],"",0,-1) -> ANGELA SILVESTRE
A19: ABEL Y SOFIA SAS | B19: 151 | C19: 20290 | D19: 0 | E19: 45873.302 | F19: 45903.301 | G19: 133 | H19: 114299.99 | I19: 84299.99 | J19: 0 | K19: 0 | L19: 0 | M19: 0 | N19: 0 | O19: 84299.99 | P19: =SUM(Cartera[[#This Row],[1_a_8]:[>30]]) -> 84299.99 | Q19: =+Cartera[[#This Row],[9_a_15]]+Cartera[[#This Row],[16_a_22]]+Cartera[[#This Row],[23_a_30]] -> 0 | R19: =IF(Cartera[[#This Row],[Dias]]>8,Cartera[[#This Row],[Total vencido]],0) -> 84299.99 | S19: =IF(Cartera[[#This Row],[Mas de 9]]>0,Cartera[[#This Row],[Dias]],0) -> 133 | T19: =IF(Cartera[[#This Row],[Dias]]>99,Cartera[[#This Row],[Total vencido]],0) -> 84299.99 | U19: =IF(Cartera[[#This Row],[Mas de 100]]>0,Cartera[[#This Row],[Dias]],0) -> 133 | V19: =Cartera[[#This Row],[Vencimiento]]-Cartera[[#This Row],[Emision]] -> 29.998981 | W19: =+IF(Cartera[[#This Row],[Tipo]]=151,"Lom",IF(Cartera[[#This Row],[Tipo]]=153,"Lom",IF(Cartera[[#This Row],[Tipo]]=155,"Lom",IF(Cartera[[#This Row],[Tipo]]=200,"Lom",IF(Cartera[[#This Row],[Tipo]]=224,"Lom",IF(Cartera[[#This Row],[Tipo]]=251,"Lom",IF(Cartera[[#This Row],[Tipo]]=651,"Magra",IF(Cartera[[#This Row],[Tipo]]=655,"Magra",IF(Cartera[[#This Row],[Tipo]]=601,"Magra",IF(Cartera[[#This Row],[Tipo]]=751,"Galan",IF(Cartera[[#This Row],[Tipo]]=757,"Galan",IF(Cartera[[#This Row],[Tipo]]=701,"Galan",IF(Cartera[[#This Row],[Tipo]]=755,"Galan",IF(Cartera[[#This Row],[Tipo]]="CO","Conciliacion Cartera","")))))))))))))) | X19: =_xlfn.XLOOKUP(Cartera[[#This Row],[Nombre tercero]],Vendedor[Nombre],Vendedor[Vendedor],"",0,-1) -> ANGELA SILVESTRE
A20: =+A19 -> ABEL Y SOFIA SAS | B20: 151 | C20: 21715 | D20: 0 | E20: 45945.312 | F20: 45975.312 | G20: 61 | H20: 393300 | I20: 371495 | J20: 0 | K20: 0 | L20: 0 | M20: 0 | N20: 0 | O20: 371495 | P20: =SUM(Cartera[[#This Row],[1_a_8]:[>30]]) -> 371495 | Q20: =+Cartera[[#This Row],[9_a_15]]+Cartera[[#This Row],[16_a_22]]+Cartera[[#This Row],[23_a_30]] -> 0 | R20: =IF(Cartera[[#This Row],[Dias]]>8,Cartera[[#This Row],[Total vencido]],0) -> 371495 | S20: =IF(Cartera[[#This Row],[Mas de 9]]>0,Cartera[[#This Row],[Dias]],0) -> 61 | T20: =IF(Cartera[[#This Row],[Dias]]>99,Cartera[[#This Row],[Total vencido]],0) -> 0 | U20: =IF(Cartera[[#This Row],[Mas de 100]]>0,Cartera[[#This Row],[Dias]],0) -> 0 | V20: =Cartera[[#This Row],[Vencimiento]]-Cartera[[#This Row],[Emision]] -> 29.99985 | W20: =+IF(Cartera[[#This Row],[Tipo]]=151,"Lom",IF(Cartera[[#This Row],[Tipo]]=153,"Lom",IF(Cartera[[#This Row],[Tipo]]=155,"Lom",IF(Cartera[[#This Row],[Tipo]]=200,"Lom",IF(Cartera[[#This Row],[Tipo]]=224,"Lom",IF(Cartera[[#This Row],[Tipo]]=251,"Lom",IF(Cartera[[#This Row],[Tipo]]=651,"Magra",IF(Cartera[[#This Row],[Tipo]]=655,"Magra",IF(Cartera[[#This Row],[Tipo]]=601,"Magra",IF(Cartera[[#This Row],[Tipo]]=751,"Galan",IF(Cartera[[#This Row],[Tipo]]=757,"Galan",IF(Cartera[[#This Row],[Tipo]]=701,"Galan",IF(Cartera[[#This Row],[Tipo]]=755,"Galan",IF(Cartera[[#This Row],[Tipo]]="CO","Conciliacion Cartera","")))))))))))))) | X20: =_xlfn.XLOOKUP(Cartera[[#This Row],[Nombre tercero]],Vendedor[Nombre],Vendedor[Vendedor],"",0,-1) -> ANGELA SILVESTRE
A21: =+A20 -> ABEL Y SOFIA SAS | B21: 151 | C21: 22119 | D21: 0 | E21: 45962.307 | F21: 45992.307 | G21: 44 | H21: 1772250 | I21: 1772250 | J21: 0 | K21: 0 | L21: 0 | M21: 0 | N21: 0 | O21: 1772250 | P21: =SUM(Cartera[[#This Row],[1_a_8]:[>30]]) -> 1772250 | Q21: =+Cartera[[#This Row],[9_a_15]]+Cartera[[#This Row],[16_a_22]]+Cartera[[#This Row],[23_a_30]] -> 0 | R21: =IF(Cartera[[#This Row],[Dias]]>8,Cartera[[#This Row],[Total vencido]],0) -> 1772250 | S21: =IF(Cartera[[#This Row],[Mas de 9]]>0,Cartera[[#This Row],[Dias]],0) -> 44 | T21: =IF(Cartera[[#This Row],[Dias]]>99,Cartera[[#This Row],[Total vencido]],0) -> 0 | U21: =IF(Cartera[[#This Row],[Mas de 100]]>0,Cartera[[#This Row],[Dias]],0) -> 0 | V21: =Cartera[[#This Row],[Vencimiento]]-Cartera[[#This Row],[Emision]] -> 29.999896 | W21: =+IF(Cartera[[#This Row],[Tipo]]=151,"Lom",IF(Cartera[[#This Row],[Tipo]]=153,"Lom",IF(Cartera[[#This Row],[Tipo]]=155,"Lom",IF(Cartera[[#This Row],[Tipo]]=200,"Lom",IF(Cartera[[#This Row],[Tipo]]=224,"Lom",IF(Cartera[[#This Row],[Tipo]]=251,"Lom",IF(Cartera[[#This Row],[Tipo]]=651,"Magra",IF(Cartera[[#This Row],[Tipo]]=655,"Magra",IF(Cartera[[#This Row],[Tipo]]=601,"Magra",IF(Cartera[[#This Row],[Tipo]]=751,"Galan",IF(Cartera[[#This Row],[Tipo]]=757,"Galan",IF(Cartera[[#This Row],[Tipo]]=701,"Galan",IF(Cartera[[#This Row],[Tipo]]=755,"Galan",IF(Cartera[[#This Row],[Tipo]]="CO","Conciliacion Cartera","")))))))))))))) | X21: =_xlfn.XLOOKUP(Cartera[[#This Row],[Nombre tercero]],Vendedor[Nombre],Vendedor[Vendedor],"",0,-1) -> ANGELA SILVESTRE
A22: =+A21 -> ABEL Y SOFIA SAS | B22: 151 | C22: 22121 | D22: 0 | E22: 45962.31 | F22: 45992.31 | G22: 44 | H22: 487600 | I22: 487600 | J22: 0 | K22: 0 | L22: 0 | M22: 0 | N22: 0 | O22: 487600 | P22: =SUM(Cartera[[#This Row],[1_a_8]:[>30]]) -> 487600 | Q22: =+Cartera[[#This Row],[9_a_15]]+Cartera[[#This Row],[16_a_22]]+Cartera[[#This Row],[23_a_30]] -> 0 | R22: =IF(Cartera[[#This Row],[Dias]]>8,Cartera[[#This Row],[Total vencido]],0) -> 487600 | S22: =IF(Cartera[[#This Row],[Mas de 9]]>0,Cartera[[#This Row],[Dias]],0) -> 44 | T22: =IF(Cartera[[#This Row],[Dias]]>99,Cartera[[#This Row],[Total vencido]],0) -> 0 | U22: =IF(Cartera[[#This Row],[Mas de 100]]>0,Cartera[[#This Row],[Dias]],0) -> 0 | V22: =Cartera[[#This Row],[Vencimiento]]-Cartera[[#This Row],[Emision]] -> 29.999884 | W22: =+IF(Cartera[[#This Row],[Tipo]]=151,"Lom",IF(Cartera[[#This Row],[Tipo]]=153,"Lom",IF(Cartera[[#This Row],[Tipo]]=155,"Lom",IF(Cartera[[#This Row],[Tipo]]=200,"Lom",IF(Cartera[[#This Row],[Tipo]]=224,"Lom",IF(Cartera[[#This Row],[Tipo]]=251,"Lom",IF(Cartera[[#This Row],[Tipo]]=651,"Magra",IF(Cartera[[#This Row],[Tipo]]=655,"Magra",IF(Cartera[[#This Row],[Tipo]]=601,"Magra",IF(Cartera[[#This Row],[Tipo]]=751,"Galan",IF(Cartera[[#This Row],[Tipo]]=757,"Galan",IF(Cartera[[#This Row],[Tipo]]=701,"Galan",IF(Cartera[[#This Row],[Tipo]]=755,"Galan",IF(Cartera[[#This Row],[Tipo]]="CO","Conciliacion Cartera","")))))))))))))) | X22: =_xlfn.XLOOKUP(Cartera[[#This Row],[Nombre tercero]],Vendedor[Nombre],Vendedor[Vendedor],"",0,-1) -> ANGELA SILVESTRE
A23: =+A22 -> ABEL Y SOFIA SAS | B23: 151 | C23: 22124 | D23: 0 | E23: 45962.317 | F23: 45992.317 | G23: 44 | H23: 150800 | I23: 150800 | J23: 0 | K23: 0 | L23: 0 | M23: 0 | N23: 0 | O23: 150800 | P23: =SUM(Cartera[[#This Row],[1_a_8]:[>30]]) -> 150800 | Q23: =+Cartera[[#This Row],[9_a_15]]+Cartera[[#This Row],[16_a_22]]+Cartera[[#This Row],[23_a_30]] -> 0 | R23: =IF(Cartera[[#This Row],[Dias]]>8,Cartera[[#This Row],[Total vencido]],0) -> 150800 | S23: =IF(Cartera[[#This Row],[Mas de 9]]>0,Cartera[[#This Row],[Dias]],0) -> 44 | T23: =IF(Cartera[[#This Row],[Dias]]>99,Cartera[[#This Row],[Total vencido]],0) -> 0 | U23: =IF(Cartera[[#This Row],[Mas de 100]]>0,Cartera[[#This Row],[Dias]],0) -> 0 | V23: =Cartera[[#This Row],[Vencimiento]]-Cartera[[#This Row],[Emision]] -> 29.999861 | W23: =+IF(Cartera[[#This Row],[Tipo]]=151,"Lom",IF(Cartera[[#This Row],[Tipo]]=153,"Lom",IF(Cartera[[#This Row],[Tipo]]=155,"Lom",IF(Cartera[[#This Row],[Tipo]]=200,"Lom",IF(Cartera[[#This Row],[Tipo]]=224,"Lom",IF(Cartera[[#This Row],[Tipo]]=251,"Lom",IF(Cartera[[#This Row],[Tipo]]=651,"Magra",IF(Cartera[[#This Row],[Tipo]]=655,"Magra",IF(Cartera[[#This Row],[Tipo]]=601,"Magra",IF(Cartera[[#This Row],[Tipo]]=751,"Galan",IF(Cartera[[#This Row],[Tipo]]=757,"Galan",IF(Cartera[[#This Row],[Tipo]]=701,"Galan",IF(Cartera[[#This Row],[Tipo]]=755,"Galan",IF(Cartera[[#This Row],[Tipo]]="CO","Conciliacion Cartera","")))))))))))))) | X23: =_xlfn.XLOOKUP(Cartera[[#This Row],[Nombre tercero]],Vendedor[Nombre],Vendedor[Vendedor],"",0,-1) -> ANGELA SILVESTRE
A24: =+A23 -> ABEL Y SOFIA SAS | B24: 151 | C24: 22125 | D24: 0 | E24: 45962.318 | F24: 45992.317 | G24: 44 | H24: 343300 | I24: 343300 | J24: 0 | K24: 0 | L24: 0 | M24: 0 | N24: 0 | O24: 343300 | P24: =SUM(Cartera[[#This Row],[1_a_8]:[>30]]) -> 343300 | Q24: =+Cartera[[#This Row],[9_a_15]]+Cartera[[#This Row],[16_a_22]]+Cartera[[#This Row],[23_a_30]] -> 0 | R24: =IF(Cartera[[#This Row],[Dias]]>8,Cartera[[#This Row],[Total vencido]],0) -> 343300 | S24: =IF(Cartera[[#This Row],[Mas de 9]]>0,Cartera[[#This Row],[Dias]],0) -> 44 | T24: =IF(Cartera[[#This Row],[Dias]]>99,Cartera[[#This Row],[Total vencido]],0) -> 0 | U24: =IF(Cartera[[#This Row],[Mas de 100]]>0,Cartera[[#This Row],[Dias]],0) -> 0 | V24: =Cartera[[#This Row],[Vencimiento]]-Cartera[[#This Row],[Emision]] -> 29.999687 | W24: =+IF(Cartera[[#This Row],[Tipo]]=151,"Lom",IF(Cartera[[#This Row],[Tipo]]=153,"Lom",IF(Cartera[[#This Row],[Tipo]]=155,"Lom",IF(Cartera[[#This Row],[Tipo]]=200,"Lom",IF(Cartera[[#This Row],[Tipo]]=224,"Lom",IF(Cartera[[#This Row],[Tipo]]=251,"Lom",IF(Cartera[[#This Row],[Tipo]]=651,"Magra",IF(Cartera[[#This Row],[Tipo]]=655,"Magra",IF(Cartera[[#This Row],[Tipo]]=601,"Magra",IF(Cartera[[#This Row],[Tipo]]=751,"Galan",IF(Cartera[[#This Row],[Tipo]]=757,"Galan",IF(Cartera[[#This Row],[Tipo]]=701,"Galan",IF(Cartera[[#This Row],[Tipo]]=755,"Galan",IF(Cartera[[#This Row],[Tipo]]="CO","Conciliacion Cartera","")))))))))))))) | X24: =_xlfn.XLOOKUP(Cartera[[#This Row],[Nombre tercero]],Vendedor[Nombre],Vendedor[Vendedor],"",0,-1) -> ANGELA SILVESTRE
A25: =+A24 -> ABEL Y SOFIA SAS | B25: 151 | C25: 22131 | D25: 0 | E25: 45962.377 | F25: 45992.377 | G25: 44 | H25: 1200000 | I25: 1200000 | J25: 0 | K25: 0 | L25: 0 | M25: 0 | N25: 0 | O25: 1200000 | P25: =SUM(Cartera[[#This Row],[1_a_8]:[>30]]) -> 1200000 | Q25: =+Cartera[[#This Row],[9_a_15]]+Cartera[[#This Row],[16_a_22]]+Cartera[[#This Row],[23_a_30]] -> 0 | R25: =IF(Cartera[[#This Row],[Dias]]>8,Cartera[[#This Row],[Total vencido]],0) -> 1200000 | S25: =IF(Cartera[[#This Row],[Mas de 9]]>0,Cartera[[#This Row],[Dias]],0) -> 44 | T25: =IF(Cartera[[#This Row],[Dias]]>99,Cartera[[#This Row],[Total vencido]],0) -> 0 | U25: =IF(Cartera[[#This Row],[Mas de 100]]>0,Cartera[[#This Row],[Dias]],0) -> 0 | V25: =Cartera[[#This Row],[Vencimiento]]-Cartera[[#This Row],[Emision]] -> 29.999537 | W25: =+IF(Cartera[[#This Row],[Tipo]]=151,"Lom",IF(Cartera[[#This Row],[Tipo]]=153,"Lom",IF(Cartera[[#This Row],[Tipo]]=155,"Lom",IF(Cartera[[#This Row],[Tipo]]=200,"Lom",IF(Cartera[[#This Row],[Tipo]]=224,"Lom",IF(Cartera[[#This Row],[Tipo]]=251,"Lom",IF(Cartera[[#This Row],[Tipo]]=651,"Magra",IF(Cartera[[#This Row],[Tipo]]=655,"Magra",IF(Cartera[[#This Row],[Tipo]]=601,"Magra",IF(Cartera[[#This Row],[Tipo]]=751,"Galan",IF(Cartera[[#This Row],[Tipo]]=757,"Galan",IF(Cartera[[#This Row],[Tipo]]=701,"Galan",IF(Cartera[[#This Row],[Tipo]]=755,"Galan",IF(Cartera[[#This Row],[Tipo]]="CO","Conciliacion Cartera","")))))))))))))) | X25: =_xlfn.XLOOKUP(Cartera[[#This Row],[Nombre tercero]],Vendedor[Nombre],Vendedor[Vendedor],"",0,-1) -> ANGELA SILVESTRE
A26: =+A25 -> ABEL Y SOFIA SAS | B26: 151 | C26: 22151 | D26: 0 | E26: 45965.291 | F26: 45995.287 | G26: 41 | H26: 195999.97 | I26: 195999.97 | J26: 0 | K26: 0 | L26: 0 | M26: 0 | N26: 0 | O26: 195999.97 | P26: =SUM(Cartera[[#This Row],[1_a_8]:[>30]]) -> 195999.97 | Q26: =+Cartera[[#This Row],[9_a_15]]+Cartera[[#This Row],[16_a_22]]+Cartera[[#This Row],[23_a_30]] -> 0 | R26: =IF(Cartera[[#This Row],[Dias]]>8,Cartera[[#This Row],[Total vencido]],0) -> 195999.97 | S26: =IF(Cartera[[#This Row],[Mas de 9]]>0,Cartera[[#This Row],[Dias]],0) -> 41 | T26: =IF(Cartera[[#This Row],[Dias]]>99,Cartera[[#This Row],[Total vencido]],0) -> 0 | U26: =IF(Cartera[[#This Row],[Mas de 100]]>0,Cartera[[#This Row],[Dias]],0) -> 0 | V26: =Cartera[[#This Row],[Vencimiento]]-Cartera[[#This Row],[Emision]] -> 29.996343 | W26: =+IF(Cartera[[#This Row],[Tipo]]=151,"Lom",IF(Cartera[[#This Row],[Tipo]]=153,"Lom",IF(Cartera[[#This Row],[Tipo]]=155,"Lom",IF(Cartera[[#This Row],[Tipo]]=200,"Lom",IF(Cartera[[#This Row],[Tipo]]=224,"Lom",IF(Cartera[[#This Row],[Tipo]]=251,"Lom",IF(Cartera[[#This Row],[Tipo]]=651,"Magra",IF(Cartera[[#This Row],[Tipo]]=655,"Magra",IF(Cartera[[#This Row],[Tipo]]=601,"Magra",IF(Cartera[[#This Row],[Tipo]]=751,"Galan",IF(Cartera[[#This Row],[Tipo]]=757,"Galan",IF(Cartera[[#This Row],[Tipo]]=701,"Galan",IF(Cartera[[#This Row],[Tipo]]=755,"Galan",IF(Cartera[[#This Row],[Tipo]]="CO","Conciliacion Cartera","")))))))))))))) | X26: =_xlfn.XLOOKUP(Cartera[[#This Row],[Nombre tercero]],Vendedor[Nombre],Vendedor[Vendedor],"",0,-1) -> ANGELA SILVESTRE
A27: =+A26 -> ABEL Y SOFIA SAS | B27: 151 | C27: 22152 | D27: 0 | E27: 45965.293 | F27: 45995.292 | G27: 41 | H27: 82899.99 | I27: 82899.99 | J27: 0 | K27: 0 | L27: 0 | M27: 0 | N27: 0 | O27: 82899.99 | P27: =SUM(Cartera[[#This Row],[1_a_8]:[>30]]) -> 82899.99 | Q27: =+Cartera[[#This Row],[9_a_15]]+Cartera[[#This Row],[16_a_22]]+Cartera[[#This Row],[23_a_30]] -> 0 | R27: =IF(Cartera[[#This Row],[Dias]]>8,Cartera[[#This Row],[Total vencido]],0) -> 82899.99 | S27: =IF(Cartera[[#This Row],[Mas de 9]]>0,Cartera[[#This Row],[Dias]],0) -> 41 | T27: =IF(Cartera[[#This Row],[Dias]]>99,Cartera[[#This Row],[Total vencido]],0) -> 0 | U27: =IF(Cartera[[#This Row],[Mas de 100]]>0,Cartera[[#This Row],[Dias]],0) -> 0 | V27: =Cartera[[#This Row],[Vencimiento]]-Cartera[[#This Row],[Emision]] -> 29.999155 | W27: =+IF(Cartera[[#This Row],[Tipo]]=151,"Lom",IF(Cartera[[#This Row],[Tipo]]=153,"Lom",IF(Cartera[[#This Row],[Tipo]]=155,"Lom",IF(Cartera[[#This Row],[Tipo]]=200,"Lom",IF(Cartera[[#This Row],[Tipo]]=224,"Lom",IF(Cartera[[#This Row],[Tipo]]=251,"Lom",IF(Cartera[[#This Row],[Tipo]]=651,"Magra",IF(Cartera[[#This Row],[Tipo]]=655,"Magra",IF(Cartera[[#This Row],[Tipo]]=601,"Magra",IF(Cartera[[#This Row],[Tipo]]=751,"Galan",IF(Cartera[[#This Row],[Tipo]]=757,"Galan",IF(Cartera[[#This Row],[Tipo]]=701,"Galan",IF(Cartera[[#This Row],[Tipo]]=755,"Galan",IF(Cartera[[#This Row],[Tipo]]="CO","Conciliacion Cartera","")))))))))))))) | X27: =_xlfn.XLOOKUP(Cartera[[#This Row],[Nombre tercero]],Vendedor[Nombre],Vendedor[Vendedor],"",0,-1) -> ANGELA SILVESTRE
A28: =+A27 -> ABEL Y SOFIA SAS | B28: 151 | C28: 22173 | D28: 0 | E28: 45966.285 | F28: 45996.284 | G28: 40 | H28: 178899.99 | I28: 178899.99 | J28: 0 | K28: 0 | L28: 0 | M28: 0 | N28: 0 | O28: 178899.99 | P28: =SUM(Cartera[[#This Row],[1_a_8]:[>30]]) -> 178899.99 | Q28: =+Cartera[[#This Row],[9_a_15]]+Cartera[[#This Row],[16_a_22]]+Cartera[[#This Row],[23_a_30]] -> 0 | R28: =IF(Cartera[[#This Row],[Dias]]>8,Cartera[[#This Row],[Total vencido]],0) -> 178899.99 | S28: =IF(Cartera[[#This Row],[Mas de 9]]>0,Cartera[[#This Row],[Dias]],0) -> 40 | T28: =IF(Cartera[[#This Row],[Dias]]>99,Cartera[[#This Row],[Total vencido]],0) -> 0 | U28: =IF(Cartera[[#This Row],[Mas de 100]]>0,Cartera[[#This Row],[Dias]],0) -> 0 | V28: =Cartera[[#This Row],[Vencimiento]]-Cartera[[#This Row],[Emision]] -> 29.999213 | W28: =+IF(Cartera[[#This Row],[Tipo]]=151,"Lom",IF(Cartera[[#This Row],[Tipo]]=153,"Lom",IF(Cartera[[#This Row],[Tipo]]=155,"Lom",IF(Cartera[[#This Row],[Tipo]]=200,"Lom",IF(Cartera[[#This Row],[Tipo]]=224,"Lom",IF(Cartera[[#This Row],[Tipo]]=251,"Lom",IF(Cartera[[#This Row],[Tipo]]=651,"Magra",IF(Cartera[[#This Row],[Tipo]]=655,"Magra",IF(Cartera[[#This Row],[Tipo]]=601,"Magra",IF(Cartera[[#This Row],[Tipo]]=751,"Galan",IF(Cartera[[#This Row],[Tipo]]=757,"Galan",IF(Cartera[[#This Row],[Tipo]]=701,"Galan",IF(Cartera[[#This Row],[Tipo]]=755,"Galan",IF(Cartera[[#This Row],[Tipo]]="CO","Conciliacion Cartera","")))))))))))))) | X28: =_xlfn.XLOOKUP(Cartera[[#This Row],[Nombre tercero]],Vendedor[Nombre],Vendedor[Vendedor],"",0,-1) -> ANGELA SILVESTRE
A29: =+A28 -> ABEL Y SOFIA SAS | B29: 151 | C29: 22174 | D29: 0 | E29: 45966.287 | F29: 45996.286 | G29: 40 | H29: 415850 | I29: 415850 | J29: 0 | K29: 0 | L29: 0 | M29: 0 | N29: 0 | O29: 415850 | P29: =SUM(Cartera[[#This Row],[1_a_8]:[>30]]) -> 415850 | Q29: =+Cartera[[#This Row],[9_a_15]]+Cartera[[#This Row],[16_a_22]]+Cartera[[#This Row],[23_a_30]] -> 0 | R29: =IF(Cartera[[#This Row],[Dias]]>8,Cartera[[#This Row],[Total vencido]],0) -> 415850 | S29: =IF(Cartera[[#This Row],[Mas de 9]]>0,Cartera[[#This Row],[Dias]],0) -> 40 | T29: =IF(Cartera[[#This Row],[Dias]]>99,Cartera[[#This Row],[Total vencido]],0) -> 0 | U29: =IF(Cartera[[#This Row],[Mas de 100]]>0,Cartera[[#This Row],[Dias]],0) -> 0 | V29: =Cartera[[#This Row],[Vencimiento]]-Cartera[[#This Row],[Emision]] -> 29.99985 | W29: =+IF(Cartera[[#This Row],[Tipo]]=151,"Lom",IF(Cartera[[#This Row],[Tipo]]=153,"Lom",IF(Cartera[[#This Row],[Tipo]]=155,"Lom",IF(Cartera[[#This Row],[Tipo]]=200,"Lom",IF(Cartera[[#This Row],[Tipo]]=224,"Lom",IF(Cartera[[#This Row],[Tipo]]=251,"Lom",IF(Cartera[[#This Row],[Tipo]]=651,"Magra",IF(Cartera[[#This Row],[Tipo]]=655,"Magra",IF(Cartera[[#This Row],[Tipo]]=601,"Magra",IF(Cartera[[#This Row],[Tipo]]=751,"Galan",IF(Cartera[[#This Row],[Tipo]]=757,"Galan",IF(Cartera[[#This Row],[Tipo]]=701,"Galan",IF(Cartera[[#This Row],[Tipo]]=755,"Galan",IF(Cartera[[#This Row],[Tipo]]="CO","Conciliacion Cartera","")))))))))))))) | X29: =_xlfn.XLOOKUP(Cartera[[#This Row],[Nombre tercero]],Vendedor[Nombre],Vendedor[Vendedor],"",0,-1) -> ANGELA SILVESTRE
A30: =+A29 -> ABEL Y SOFIA SAS | B30: 151 | C30: 22176 | D30: 0 | E30: 45966.288 | F30: 45996.288 | G30: 40 | H30: 342200 | I30: 342200 | J30: 0 | K30: 0 | L30: 0 | M30: 0 | N30: 0 | O30: 342200 | P30: =SUM(Cartera[[#This Row],[1_a_8]:[>30]]) -> 342200 | Q30: =+Cartera[[#This Row],[9_a_15]]+Cartera[[#This Row],[16_a_22]]+Cartera[[#This Row],[23_a_30]] -> 0 | R30: =IF(Cartera[[#This Row],[Dias]]>8,Cartera[[#This Row],[Total vencido]],0) -> 342200 | S30: =IF(Cartera[[#This Row],[Mas de 9]]>0,Cartera[[#This Row],[Dias]],0) -> 40 | T30: =IF(Cartera[[#This Row],[Dias]]>99,Cartera[[#This Row],[Total vencido]],0) -> 0 | U30: =IF(Cartera[[#This Row],[Mas de 100]]>0,Cartera[[#This Row],[Dias]],0) -> 0 | V30: =Cartera[[#This Row],[Vencimiento]]-Cartera[[#This Row],[Emision]] -> 29.999792 | W30: =+IF(Cartera[[#This Row],[Tipo]]=151,"Lom",IF(Cartera[[#This Row],[Tipo]]=153,"Lom",IF(Cartera[[#This Row],[Tipo]]=155,"Lom",IF(Cartera[[#This Row],[Tipo]]=200,"Lom",IF(Cartera[[#This Row],[Tipo]]=224,"Lom",IF(Cartera[[#This Row],[Tipo]]=251,"Lom",IF(Cartera[[#This Row],[Tipo]]=651,"Magra",IF(Cartera[[#This Row],[Tipo]]=655,"Magra",IF(Cartera[[#This Row],[Tipo]]=601,"Magra",IF(Cartera[[#This Row],[Tipo]]=751,"Galan",IF(Cartera[[#This Row],[Tipo]]=757,"Galan",IF(Cartera[[#This Row],[Tipo]]=701,"Galan",IF(Cartera[[#This Row],[Tipo]]=755,"Galan",IF(Cartera[[#This Row],[Tipo]]="CO","Conciliacion Cartera","")))))))))))))) | X30: =_xlfn.XLOOKUP(Cartera[[#This Row],[Nombre tercero]],Vendedor[Nombre],Vendedor[Vendedor],"",0,-1) -> ANGELA SILVESTRE
A31: =+A30 -> ABEL Y SOFIA SAS | B31: 151 | C31: 22177 | D31: 0 | E31: 45966.289 | F31: 45996.289 | G31: 40 | H31: 615500 | I31: 615500 | J31: 0 | K31: 0 | L31: 0 | M31: 0 | N31: 0 | O31: 615500 | P31: =SUM(Cartera[[#This Row],[1_a_8]:[>30]]) -> 615500 | Q31: =+Cartera[[#This Row],[9_a_15]]+Cartera[[#This Row],[16_a_22]]+Cartera[[#This Row],[23_a_30]] -> 0 | R31: =IF(Cartera[[#This Row],[Dias]]>8,Cartera[[#This Row],[Total vencido]],0) -> 615500 | S31: =IF(Cartera[[#This Row],[Mas de 9]]>0,Cartera[[#This Row],[Dias]],0) -> 40 | T31: =IF(Cartera[[#This Row],[Dias]]>99,Cartera[[#This Row],[Total vencido]],0) -> 0 | U31: =IF(Cartera[[#This Row],[Mas de 100]]>0,Cartera[[#This Row],[Dias]],0) -> 0 | V31: =Cartera[[#This Row],[Vencimiento]]-Cartera[[#This Row],[Emision]] -> 29.99985 | W31: =+IF(Cartera[[#This Row],[Tipo]]=151,"Lom",IF(Cartera[[#This Row],[Tipo]]=153,"Lom",IF(Cartera[[#This Row],[Tipo]]=155,"Lom",IF(Cartera[[#This Row],[Tipo]]=200,"Lom",IF(Cartera[[#This Row],[Tipo]]=224,"Lom",IF(Cartera[[#This Row],[Tipo]]=251,"Lom",IF(Cartera[[#This Row],[Tipo]]=651,"Magra",IF(Cartera[[#This Row],[Tipo]]=655,"Magra",IF(Cartera[[#This Row],[Tipo]]=601,"Magra",IF(Cartera[[#This Row],[Tipo]]=751,"Galan",IF(Cartera[[#This Row],[Tipo]]=757,"Galan",IF(Cartera[[#This Row],[Tipo]]=701,"Galan",IF(Cartera[[#This Row],[Tipo]]=755,"Galan",IF(Cartera[[#This Row],[Tipo]]="CO","Conciliacion Cartera","")))))))))))))) | X31: =_xlfn.XLOOKUP(Cartera[[#This Row],[Nombre tercero]],Vendedor[Nombre],Vendedor[Vendedor],"",0,-1) -> ANGELA SILVESTRE
... A190: =+A189 -> ABEL Y SOFIA SAS | B190: 151 | C190: 23737 | D190: 0 | E190: 46021.345 | F190: 46051.344 | G190: -15 | H190: 1816900 | I190: 1816900 | J190: 1816900 | K190: 0 | L190: 0 | M190: 0 | N190: 0 | O190: 0 | P190: =SUM(Cartera[[#This Row],[1_a_8]:[>30]]) -> 0 | Q190: =+Cartera[[#This Row],[9_a_15]]+Cartera[[#This Row],[16_a_22]]+Cartera[[#This Row],[23_a_30]] -> 0 | R190: =IF(Cartera[[#This Row],[Dias]]>8,Cartera[[#This Row],[Total vencido]],0) -> 0 | S190: =IF(Cartera[[#This Row],[Mas de 9]]>0,Cartera[[#This Row],[Dias]],0) -> 0 | T190: =IF(Cartera[[#This Row],[Dias]]>99,Cartera[[#This Row],[Total vencido]],0) -> 0 | U190: =IF(Cartera[[#This Row],[Mas de 100]]>0,Cartera[[#This Row],[Dias]],0) -> 0 | V190: =Cartera[[#This Row],[Vencimiento]]-Cartera[[#This Row],[Emision]] -> 29.999016 | W190: =+IF(Cartera[[#This Row],[Tipo]]=151,"Lom",IF(Cartera[[#This Row],[Tipo]]=153,"Lom",IF(Cartera[[#This Row],[Tipo]]=155,"Lom",IF(Cartera[[#This Row],[Tipo]]=200,"Lom",IF(Cartera[[#This Row],[Tipo]]=224,"Lom",IF(Cartera[[#This Row],[Tipo]]=251,"Lom",IF(Cartera[[#This Row],[Tipo]]=651,"Magra",IF(Cartera[[#This Row],[Tipo]]=655,"Magra",IF(Cartera[[#This Row],[Tipo]]=601,"Magra",IF(Cartera[[#This Row],[Tipo]]=751,"Galan",IF(Cartera[[#This Row],[Tipo]]=757,"Galan",IF(Cartera[[#This Row],[Tipo]]=701,"Galan",IF(Cartera[[#This Row],[Tipo]]=755,"Galan",IF(Cartera[[#This Row],[Tipo]]="CO","Conciliacion Cartera","")))))))))))))) | X190: =_xlfn.XLOOKUP(Cartera[[#This Row],[Nombre tercero]],Vendedor[Nombre],Vendedor[Vendedor],"",0,-1) -> ANGELA SILVESTRE
A191: ADRIANA BERMUDEZ RAMIREZ | B191: 751 | C191: 15707 | D191: 1 | E191: 45910.513 | F191: 45918.513 | G191: 118 | H191: 862400 | I191: 231640 | J191: 0 | K191: 0 | L191: 0 | M191: 0 | N191: 0 | O191: 231640 | P191: =SUM(Cartera[[#This Row],[1_a_8]:[>30]]) -> 231640 | Q191: =+Cartera[[#This Row],[9_a_15]]+Cartera[[#This Row],[16_a_22]]+Cartera[[#This Row],[23_a_30]] -> 0 | R191: =IF(Cartera[[#This Row],[Dias]]>8,Cartera[[#This Row],[Total vencido]],0) -> 231640 | S191: =IF(Cartera[[#This Row],[Mas de 9]]>0,Cartera[[#This Row],[Dias]],0) -> 118 | T191: =IF(Cartera[[#This Row],[Dias]]>99,Cartera[[#This Row],[Total vencido]],0) -> 231640 | U191: =IF(Cartera[[#This Row],[Mas de 100]]>0,Cartera[[#This Row],[Dias]],0) -> 118 | V191: =Cartera[[#This Row],[Vencimiento]]-Cartera[[#This Row],[Emision]] -> 7.999838 | W191: =+IF(Cartera[[#This Row],[Tipo]]=151,"Lom",IF(Cartera[[#This Row],[Tipo]]=153,"Lom",IF(Cartera[[#This Row],[Tipo]]=155,"Lom",IF(Cartera[[#This Row],[Tipo]]=200,"Lom",IF(Cartera[[#This Row],[Tipo]]=224,"Lom",IF(Cartera[[#This Row],[Tipo]]=251,"Lom",IF(Cartera[[#This Row],[Tipo]]=651,"Magra",IF(Cartera[[#This Row],[Tipo]]=655,"Magra",IF(Cartera[[#This Row],[Tipo]]=601,"Magra",IF(Cartera[[#This Row],[Tipo]]=751,"Galan",IF(Cartera[[#This Row],[Tipo]]=757,"Galan",IF(Cartera[[#This Row],[Tipo]]=701,"Galan",IF(Cartera[[#This Row],[Tipo]]=755,"Galan",IF(Cartera[[#This Row],[Tipo]]="CO","Conciliacion Cartera","")))))))))))))) | X191: =_xlfn.XLOOKUP(Cartera[[#This Row],[Nombre tercero]],Vendedor[Nombre],Vendedor[Vendedor],"",0,-1) -> JORGE PARDO
A192: =+A191 -> ADRIANA BERMUDEZ RAMIREZ | B192: 751 | C192: 18788 | D192: 1 | E192: 46013.475 | F192: 46021.475 | G192: 15 | H192: 319200 | I192: 319200 | J192: 0 | K192: 0 | L192: 319200 | M192: 0 | N192: 0 | O192: 0 | P192: =SUM(Cartera[[#This Row],[1_a_8]:[>30]]) -> 319200 | Q192: =+Cartera[[#This Row],[9_a_15]]+Cartera[[#This Row],[16_a_22]]+Cartera[[#This Row],[23_a_30]] -> 319200 | R192: =IF(Cartera[[#This Row],[Dias]]>8,Cartera[[#This Row],[Total vencido]],0) -> 319200 | S192: =IF(Cartera[[#This Row],[Mas de 9]]>0,Cartera[[#This Row],[Dias]],0) -> 15 | T192: =IF(Cartera[[#This Row],[Dias]]>99,Cartera[[#This Row],[Total vencido]],0) -> 0 | U192: =IF(Cartera[[#This Row],[Mas de 100]]>0,Cartera[[#This Row],[Dias]],0) -> 0 | V192: =Cartera[[#This Row],[Vencimiento]]-Cartera[[#This Row],[Emision]] -> 7.9998843 | W192: =+IF(Cartera[[#This Row],[Tipo]]=151,"Lom",IF(Cartera[[#This Row],[Tipo]]=153,"Lom",IF(Cartera[[#This Row],[Tipo]]=155,"Lom",IF(Cartera[[#This Row],[Tipo]]=200,"Lom",IF(Cartera[[#This Row],[Tipo]]=224,"Lom",IF(Cartera[[#This Row],[Tipo]]=251,"Lom",IF(Cartera[[#This Row],[Tipo]]=651,"Magra",IF(Cartera[[#This Row],[Tipo]]=655,"Magra",IF(Cartera[[#This Row],[Tipo]]=601,"Magra",IF(Cartera[[#This Row],[Tipo]]=751,"Galan",IF(Cartera[[#This Row],[Tipo]]=757,"Galan",IF(Cartera[[#This Row],[Tipo]]=701,"Galan",IF(Cartera[[#This Row],[Tipo]]=755,"Galan",IF(Cartera[[#This Row],[Tipo]]="CO","Conciliacion Cartera","")))))))))))))) | X192: =_xlfn.XLOOKUP(Cartera[[#This Row],[Nombre tercero]],Vendedor[Nombre],Vendedor[Vendedor],"",0,-1) -> JORGE PARDO
A193: =+A192 -> ADRIANA BERMUDEZ RAMIREZ | B193: 751 | C193: 18809 | D193: 1 | E193: 46013.571 | F193: 46021.571 | G193: 15 | H193: 1454000 | I193: 1454000 | J193: 0 | K193: 0 | L193: 1454000 | M193: 0 | N193: 0 | O193: 0 | P193: =SUM(Cartera[[#This Row],[1_a_8]:[>30]]) -> 1454000 | Q193: =+Cartera[[#This Row],[9_a_15]]+Cartera[[#This Row],[16_a_22]]+Cartera[[#This Row],[23_a_30]] -> 1454000 | R193: =IF(Cartera[[#This Row],[Dias]]>8,Cartera[[#This Row],[Total vencido]],0) -> 1454000 | S193: =IF(Cartera[[#This Row],[Mas de 9]]>0,Cartera[[#This Row],[Dias]],0) -> 15 | T193: =IF(Cartera[[#This Row],[Dias]]>99,Cartera[[#This Row],[Total vencido]],0) -> 0 | U193: =IF(Cartera[[#This Row],[Mas de 100]]>0,Cartera[[#This Row],[Dias]],0) -> 0 | V193: =Cartera[[#This Row],[Vencimiento]]-Cartera[[#This Row],[Emision]] -> 7.9997685 | W193: =+IF(Cartera[[#This Row],[Tipo]]=151,"Lom",IF(Cartera[[#This Row],[Tipo]]=153,"Lom",IF(Cartera[[#This Row],[Tipo]]=155,"Lom",IF(Cartera[[#This Row],[Tipo]]=200,"Lom",IF(Cartera[[#This Row],[Tipo]]=224,"Lom",IF(Cartera[[#This Row],[Tipo]]=251,"Lom",IF(Cartera[[#This Row],[Tipo]]=651,"Magra",IF(Cartera[[#This Row],[Tipo]]=655,"Magra",IF(Cartera[[#This Row],[Tipo]]=601,"Magra",IF(Cartera[[#This Row],[Tipo]]=751,"Galan",IF(Cartera[[#This Row],[Tipo]]=757,"Galan",IF(Cartera[[#This Row],[Tipo]]=701,"Galan",IF(Cartera[[#This Row],[Tipo]]=755,"Galan",IF(Cartera[[#This Row],[Tipo]]="CO","Conciliacion Cartera","")))))))))))))) | X193: =_xlfn.XLOOKUP(Cartera[[#This Row],[Nombre tercero]],Vendedor[Nombre],Vendedor[Vendedor],"",0,-1) -> JORGE PARDO
A194: ALBA MARIA GONZALEZ IBAÑEZ | B194: 151 | C194: 23759 | D194: 11 | E194: 46022.304 | F194: 46023.283 | G194: 13 | H194: 497700 | I194: 497700 | J194: 0 | K194: 0 | L194: 497700 | M194: 0 | N194: 0 | O194: 0 | P194: =SUM(Cartera[[#This Row],[1_a_8]:[>30]]) -> 497700 | Q194: =+Cartera[[#This Row],[9_a_15]]+Cartera[[#This Row],[16_a_22]]+Cartera[[#This Row],[23_a_30]] -> 497700 | R194: =IF(Cartera[[#This Row],[Dias]]>8,Cartera[[#This Row],[Total vencido]],0) -> 497700 | S194: =IF(Cartera[[#This Row],[Mas de 9]]>0,Cartera[[#This Row],[Dias]],0) -> 13 | T194: =IF(Cartera[[#This Row],[Dias]]>99,Cartera[[#This Row],[Total vencido]],0) -> 0 | U194: =IF(Cartera[[#This Row],[Mas de 100]]>0,Cartera[[#This Row],[Dias]],0) -> 0 | V194: =Cartera[[#This Row],[Vencimiento]]-Cartera[[#This Row],[Emision]] -> 0.97866898 | W194: =+IF(Cartera[[#This Row],[Tipo]]=151,"Lom",IF(Cartera[[#This Row],[Tipo]]=153,"Lom",IF(Cartera[[#This Row],[Tipo]]=155,"Lom",IF(Cartera[[#This Row],[Tipo]]=200,"Lom",IF(Cartera[[#This Row],[Tipo]]=224,"Lom",IF(Cartera[[#This Row],[Tipo]]=251,"Lom",IF(Cartera[[#This Row],[Tipo]]=651,"Magra",IF(Cartera[[#This Row],[Tipo]]=655,"Magra",IF(Cartera[[#This Row],[Tipo]]=601,"Magra",IF(Cartera[[#This Row],[Tipo]]=751,"Galan",IF(Cartera[[#This Row],[Tipo]]=757,"Galan",IF(Cartera[[#This Row],[Tipo]]=701,"Galan",IF(Cartera[[#This Row],[Tipo]]=755,"Galan",IF(Cartera[[#This Row],[Tipo]]="CO","Conciliacion Cartera","")))))))))))))) | X194: =_xlfn.XLOOKUP(Cartera[[#This Row],[Nombre tercero]],Vendedor[Nombre],Vendedor[Vendedor],"",0,-1) -> ANGELA SILVESTRE
A195: ALEJANDRO DURAN | B195: 751 | C195: 16999 | D195: 7 | E195: 45957.477 | F195: 45958.477 | G195: 78 | H195: 1484405 | I195: 1484405 | J195: 0 | K195: 0 | L195: 0 | M195: 0 | N195: 0 | O195: 1484405 | P195: =SUM(Cartera[[#This Row],[1_a_8]:[>30]]) -> 1484405 | Q195: =+Cartera[[#This Row],[9_a_15]]+Cartera[[#This Row],[16_a_22]]+Cartera[[#This Row],[23_a_30]] -> 0 | R195: =IF(Cartera[[#This Row],[Dias]]>8,Cartera[[#This Row],[Total vencido]],0) -> 1484405 | S195: =IF(Cartera[[#This Row],[Mas de 9]]>0,Cartera[[#This Row],[Dias]],0) -> 78 | T195: =IF(Cartera[[#This Row],[Dias]]>99,Cartera[[#This Row],[Total vencido]],0) -> 0 | U195: =IF(Cartera[[#This Row],[Mas de 100]]>0,Cartera[[#This Row],[Dias]],0) -> 0 | V195: =Cartera[[#This Row],[Vencimiento]]-Cartera[[#This Row],[Emision]] -> 0.99988426 | W195: =+IF(Cartera[[#This Row],[Tipo]]=151,"Lom",IF(Cartera[[#This Row],[Tipo]]=153,"Lom",IF(Cartera[[#This Row],[Tipo]]=155,"Lom",IF(Cartera[[#This Row],[Tipo]]=200,"Lom",IF(Cartera[[#This Row],[Tipo]]=224,"Lom",IF(Cartera[[#This Row],[Tipo]]=251,"Lom",IF(Cartera[[#This Row],[Tipo]]=651,"Magra",IF(Cartera[[#This Row],[Tipo]]=655,"Magra",IF(Cartera[[#This Row],[Tipo]]=601,"Magra",IF(Cartera[[#This Row],[Tipo]]=751,"Galan",IF(Cartera[[#This Row],[Tipo]]=757,"Galan",IF(Cartera[[#This Row],[Tipo]]=701,"Galan",IF(Cartera[[#This Row],[Tipo]]=755,"Galan",IF(Cartera[[#This Row],[Tipo]]="CO","Conciliacion Cartera","")))))))))))))) | X195: =_xlfn.XLOOKUP(Cartera[[#This Row],[Nombre tercero]],Vendedor[Nombre],Vendedor[Vendedor],"",0,-1) -> ANGELA SILVESTRE
A196: ALIANZA DOC SAS | B196: 151 | C196: 23679 | D196: 12 | E196: 46018.295 | F196: 46026.293 | G196: 10 | H196: 1775100 | I196: 1775100 | J196: 0 | K196: 0 | L196: 1775100 | M196: 0 | N196: 0 | O196: 0 | P196: =SUM(Cartera[[#This Row],[1_a_8]:[>30]]) -> 1775100 | Q196: =+Cartera[[#This Row],[9_a_15]]+Cartera[[#This Row],[16_a_22]]+Cartera[[#This Row],[23_a_30]] -> 1775100 | R196: =IF(Cartera[[#This Row],[Dias]]>8,Cartera[[#This Row],[Total vencido]],0) -> 1775100 | S196: =IF(Cartera[[#This Row],[Mas de 9]]>0,Cartera[[#This Row],[Dias]],0) -> 10 | T196: =IF(Cartera[[#This Row],[Dias]]>99,Cartera[[#This Row],[Total vencido]],0) -> 0 | U196: =IF(Cartera[[#This Row],[Mas de 100]]>0,Cartera[[#This Row],[Dias]],0) -> 0 | V196: =Cartera[[#This Row],[Vencimiento]]-Cartera[[#This Row],[Emision]] -> 7.9978125 | W196: =+IF(Cartera[[#This Row],[Tipo]]=151,"Lom",IF(Cartera[[#This Row],[Tipo]]=153,"Lom",IF(Cartera[[#This Row],[Tipo]]=155,"Lom",IF(Cartera[[#This Row],[Tipo]]=200,"Lom",IF(Cartera[[#This Row],[Tipo]]=224,"Lom",IF(Cartera[[#This Row],[Tipo]]=251,"Lom",IF(Cartera[[#This Row],[Tipo]]=651,"Magra",IF(Cartera[[#This Row],[Tipo]]=655,"Magra",IF(Cartera[[#This Row],[Tipo]]=601,"Magra",IF(Cartera[[#This Row],[Tipo]]=751,"Galan",IF(Cartera[[#This Row],[Tipo]]=757,"Galan",IF(Cartera[[#This Row],[Tipo]]=701,"Galan",IF(Cartera[[#This Row],[Tipo]]=755,"Galan",IF(Cartera[[#This Row],[Tipo]]="CO","Conciliacion Cartera","")))))))))))))) | X196: =_xlfn.XLOOKUP(Cartera[[#This Row],[Nombre tercero]],Vendedor[Nombre],Vendedor[Vendedor],"",0,-1) -> JENNIFER GONZALEZ TRIANA
A197: =+A196 -> ALIANZA DOC SAS | B197: 151 | C197: 23734 | D197: 12 | E197: 46021.313 | F197: 46029.305 | G197: 7 | H197: 4521700 | I197: 4521700 | J197: 0 | K197: 4521700 | L197: 0 | M197: 0 | N197: 0 | O197: 0 | P197: =SUM(Cartera[[#This Row],[1_a_8]:[>30]]) -> 4521700 | Q197: =+Cartera[[#This Row],[9_a_15]]+Cartera[[#This Row],[16_a_22]]+Cartera[[#This Row],[23_a_30]] -> 0 | R197: =IF(Cartera[[#This Row],[Dias]]>8,Cartera[[#This Row],[Total vencido]],0) -> 0 | S197: =IF(Cartera[[#This Row],[Mas de 9]]>0,Cartera[[#This Row],[Dias]],0) -> 0 | T197: =IF(Cartera[[#This Row],[Dias]]>99,Cartera[[#This Row],[Total vencido]],0) -> 0 | U197: =IF(Cartera[[#This Row],[Mas de 100]]>0,Cartera[[#This Row],[Dias]],0) -> 0 | V197: =Cartera[[#This Row],[Vencimiento]]-Cartera[[#This Row],[Emision]] -> 7.9920833 | W197: =+IF(Cartera[[#This Row],[Tipo]]=151,"Lom",IF(Cartera[[#This Row],[Tipo]]=153,"Lom",IF(Cartera[[#This Row],[Tipo]]=155,"Lom",IF(Cartera[[#This Row],[Tipo]]=200,"Lom",IF(Cartera[[#This Row],[Tipo]]=224,"Lom",IF(Cartera[[#This Row],[Tipo]]=251,"Lom",IF(Cartera[[#This Row],[Tipo]]=651,"Magra",IF(Cartera[[#This Row],[Tipo]]=655,"Magra",IF(Cartera[[#This Row],[Tipo]]=601,"Magra",IF(Cartera[[#This Row],[Tipo]]=751,"Galan",IF(Cartera[[#This Row],[Tipo]]=757,"Galan",IF(Cartera[[#This Row],[Tipo]]=701,"Galan",IF(Cartera[[#This Row],[Tipo]]=755,"Galan",IF(Cartera[[#This Row],[Tipo]]="CO","Conciliacion Cartera","")))))))))))))) | X197: =_xlfn.XLOOKUP(Cartera[[#This Row],[Nombre tercero]],Vendedor[Nombre],Vendedor[Vendedor],"",0,-1) -> JENNIFER GONZALEZ TRIANA
A198: ALIMENTOS BENAL SAS | B198: 751 | C198: 18183 | D198: 4 | E198: 45996.269 | F198: 46026.268 | G198: 10 | H198: 5796300 | I198: 5796300 | J198: 0 | K198: 0 | L198: 5796300 | M198: 0 | N198: 0 | O198: 0 | P198: =SUM(Cartera[[#This Row],[1_a_8]:[>30]]) -> 5796300 | Q198: =+Cartera[[#This Row],[9_a_15]]+Cartera[[#This Row],[16_a_22]]+Cartera[[#This Row],[23_a_30]] -> 5796300 | R198: =IF(Cartera[[#This Row],[Dias]]>8,Cartera[[#This Row],[Total vencido]],0) -> 5796300 | S198: =IF(Cartera[[#This Row],[Mas de 9]]>0,Cartera[[#This Row],[Dias]],0) -> 10 | T198: =IF(Cartera[[#This Row],[Dias]]>99,Cartera[[#This Row],[Total vencido]],0) -> 0 | U198: =IF(Cartera[[#This Row],[Mas de 100]]>0,Cartera[[#This Row],[Dias]],0) -> 0 | V198: =Cartera[[#This Row],[Vencimiento]]-Cartera[[#This Row],[Emision]] -> 29.999745 | W198: =+IF(Cartera[[#This Row],[Tipo]]=151,"Lom",IF(Cartera[[#This Row],[Tipo]]=153,"Lom",IF(Cartera[[#This Row],[Tipo]]=155,"Lom",IF(Cartera[[#This Row],[Tipo]]=200,"Lom",IF(Cartera[[#This Row],[Tipo]]=224,"Lom",IF(Cartera[[#This Row],[Tipo]]=251,"Lom",IF(Cartera[[#This Row],[Tipo]]=651,"Magra",IF(Cartera[[#This Row],[Tipo]]=655,"Magra",IF(Cartera[[#This Row],[Tipo]]=601,"Magra",IF(Cartera[[#This Row],[Tipo]]=751,"Galan",IF(Cartera[[#This Row],[Tipo]]=757,"Galan",IF(Cartera[[#This Row],[Tipo]]=701,"Galan",IF(Cartera[[#This Row],[Tipo]]=755,"Galan",IF(Cartera[[#This Row],[Tipo]]="CO","Conciliacion Cartera","")))))))))))))) | X198: =_xlfn.XLOOKUP(Cartera[[#This Row],[Nombre tercero]],Vendedor[Nombre],Vendedor[Vendedor],"",0,-1) -> JORGE PARDO
A199: =+A198 -> ALIMENTOS BENAL SAS | B199: 751 | C199: 18260 | D199: 4 | E199: 45997.589 | F199: 46027.589 | G199: 9 | H199: 7081600 | I199: 7081600 | J199: 0 | K199: 0 | L199: 7081600 | M199: 0 | N199: 0 | O199: 0 | P199: =SUM(Cartera[[#This Row],[1_a_8]:[>30]]) -> 7081600 | Q199: =+Cartera[[#This Row],[9_a_15]]+Cartera[[#This Row],[16_a_22]]+Cartera[[#This Row],[23_a_30]] -> 7081600 | R199: =IF(Cartera[[#This Row],[Dias]]>8,Cartera[[#This Row],[Total vencido]],0) -> 7081600 | S199: =IF(Cartera[[#This Row],[Mas de 9]]>0,Cartera[[#This Row],[Dias]],0) -> 9 | T199: =IF(Cartera[[#This Row],[Dias]]>99,Cartera[[#This Row],[Total vencido]],0) -> 0 | U199: =IF(Cartera[[#This Row],[Mas de 100]]>0,Cartera[[#This Row],[Dias]],0) -> 0 | V199: =Cartera[[#This Row],[Vencimiento]]-Cartera[[#This Row],[Emision]] -> 29.999745 | W199: =+IF(Cartera[[#This Row],[Tipo]]=151,"Lom",IF(Cartera[[#This Row],[Tipo]]=153,"Lom",IF(Cartera[[#This Row],[Tipo]]=155,"Lom",IF(Cartera[[#This Row],[Tipo]]=200,"Lom",IF(Cartera[[#This Row],[Tipo]]=224,"Lom",IF(Cartera[[#This Row],[Tipo]]=251,"Lom",IF(Cartera[[#This Row],[Tipo]]=651,"Magra",IF(Cartera[[#This Row],[Tipo]]=655,"Magra",IF(Cartera[[#This Row],[Tipo]]=601,"Magra",IF(Cartera[[#This Row],[Tipo]]=751,"Galan",IF(Cartera[[#This Row],[Tipo]]=757,"Galan",IF(Cartera[[#This Row],[Tipo]]=701,"Galan",IF(Cartera[[#This Row],[Tipo]]=755,"Galan",IF(Cartera[[#This Row],[Tipo]]="CO","Conciliacion Cartera","")))))))))))))) | X199: =_xlfn.XLOOKUP(Cartera[[#This Row],[Nombre tercero]],Vendedor[Nombre],Vendedor[Vendedor],"",0,-1) -> JORGE PARDO
A200: =+A199 -> ALIMENTOS BENAL SAS | B200: 751 | C200: 18307 | D200: 4 | E200: 46000.561 | F200: 46030.561 | G200: 6 | H200: 97300 | I200: 97300 | J200: 0 | K200: 97300 | L200: 0 | M200: 0 | N200: 0 | O200: 0 | P200: =SUM(Cartera[[#This Row],[1_a_8]:[>30]]) -> 97300 | Q200: =+Cartera[[#This Row],[9_a_15]]+Cartera[[#This Row],[16_a_22]]+Cartera[[#This Row],[23_a_30]] -> 0 | R200: =IF(Cartera[[#This Row],[Dias]]>8,Cartera[[#This Row],[Total vencido]],0) -> 0 | S200: =IF(Cartera[[#This Row],[Mas de 9]]>0,Cartera[[#This Row],[Dias]],0) -> 0 | T200: =IF(Cartera[[#This Row],[Dias]]>99,Cartera[[#This Row],[Total vencido]],0) -> 0 | U200: =IF(Cartera[[#This Row],[Mas de 100]]>0,Cartera[[#This Row],[Dias]],0) -> 0 | V200: =Cartera[[#This Row],[Vencimiento]]-Cartera[[#This Row],[Emision]] -> 30 | W200: =+IF(Cartera[[#This Row],[Tipo]]=151,"Lom",IF(Cartera[[#This Row],[Tipo]]=153,"Lom",IF(Cartera[[#This Row],[Tipo]]=155,"Lom",IF(Cartera[[#This Row],[Tipo]]=200,"Lom",IF(Cartera[[#This Row],[Tipo]]=224,"Lom",IF(Cartera[[#This Row],[Tipo]]=251,"Lom",IF(Cartera[[#This Row],[Tipo]]=651,"Magra",IF(Cartera[[#This Row],[Tipo]]=655,"Magra",IF(Cartera[[#This Row],[Tipo]]=601,"Magra",IF(Cartera[[#This Row],[Tipo]]=751,"Galan",IF(Cartera[[#This Row],[Tipo]]=757,"Galan",IF(Cartera[[#This Row],[Tipo]]=701,"Galan",IF(Cartera[[#This Row],[Tipo]]=755,"Galan",IF(Cartera[[#This Row],[Tipo]]="CO","Conciliacion Cartera","")))))))))))))) | X200: =_xlfn.XLOOKUP(Cartera[[#This Row],[Nombre tercero]],Vendedor[Nombre],Vendedor[Vendedor],"",0,-1) -> JORGE PARDO
A201: =+A200 -> ALIMENTOS BENAL SAS | B201: 751 | C201: 18332 | D201: 4 | E201: 46001.365 | F201: 46031.364 | G201: 5 | H201: 3973500 | I201: 3973500 | J201: 0 | K201: 3973500 | L201: 0 | M201: 0 | N201: 0 | O201: 0 | P201: =SUM(Cartera[[#This Row],[1_a_8]:[>30]]) -> 3973500 | Q201: =+Cartera[[#This Row],[9_a_15]]+Cartera[[#This Row],[16_a_22]]+Cartera[[#This Row],[23_a_30]] -> 0 | R201: =IF(Cartera[[#This Row],[Dias]]>8,Cartera[[#This Row],[Total vencido]],0) -> 0 | S201: =IF(Cartera[[#This Row],[Mas de 9]]>0,Cartera[[#This Row],[Dias]],0) -> 0 | T201: =IF(Cartera[[#This Row],[Dias]]>99,Cartera[[#This Row],[Total vencido]],0) -> 0 | U201: =IF(Cartera[[#This Row],[Mas de 100]]>0,Cartera[[#This Row],[Dias]],0) -> 0 | V201: =Cartera[[#This Row],[Vencimiento]]-Cartera[[#This Row],[Emision]] -> 29.999201 | W201: =+IF(Cartera[[#This Row],[Tipo]]=151,"Lom",IF(Cartera[[#This Row],[Tipo]]=153,"Lom",IF(Cartera[[#This Row],[Tipo]]=155,"Lom",IF(Cartera[[#This Row],[Tipo]]=200,"Lom",IF(Cartera[[#This Row],[Tipo]]=224,"Lom",IF(Cartera[[#This Row],[Tipo]]=251,"Lom",IF(Cartera[[#This Row],[Tipo]]=651,"Magra",IF(Cartera[[#This Row],[Tipo]]=655,"Magra",IF(Cartera[[#This Row],[Tipo]]=601,"Magra",IF(Cartera[[#This Row],[Tipo]]=751,"Galan",IF(Cartera[[#This Row],[Tipo]]=757,"Galan",IF(Cartera[[#This Row],[Tipo]]=701,"Galan",IF(Cartera[[#This Row],[Tipo]]=755,"Galan",IF(Cartera[[#This Row],[Tipo]]="CO","Conciliacion Cartera","")))))))))))))) | X201: =_xlfn.XLOOKUP(Cartera[[#This Row],[Nombre tercero]],Vendedor[Nombre],Vendedor[Vendedor],"",0,-1) -> JORGE PARDO
A202: =+A201 -> ALIMENTOS BENAL SAS | B202: 751 | C202: 18371 | D202: 4 | E202: 46002.3 | F202: 46032.299 | G202: 4 | H202: 4460700 | I202: 4460700 | J202: 0 | K202: 4460700 | L202: 0 | M202: 0 | N202: 0 | O202: 0 | P202: =SUM(Cartera[[#This Row],[1_a_8]:[>30]]) -> 4460700 | Q202: =+Cartera[[#This Row],[9_a_15]]+Cartera[[#This Row],[16_a_22]]+Cartera[[#This Row],[23_a_30]] -> 0 | R202: =IF(Cartera[[#This Row],[Dias]]>8,Cartera[[#This Row],[Total vencido]],0) -> 0 | S202: =IF(Cartera[[#This Row],[Mas de 9]]>0,Cartera[[#This Row],[Dias]],0) -> 0 | T202: =IF(Cartera[[#This Row],[Dias]]>99,Cartera[[#This Row],[Total vencido]],0) -> 0 | U202: =IF(Cartera[[#This Row],[Mas de 100]]>0,Cartera[[#This Row],[Dias]],0) -> 0 | V202: =Cartera[[#This Row],[Vencimiento]]-Cartera[[#This Row],[Emision]] -> 29.999769 | W202: =+IF(Cartera[[#This Row],[Tipo]]=151,"Lom",IF(Cartera[[#This Row],[Tipo]]=153,"Lom",IF(Cartera[[#This Row],[Tipo]]=155,"Lom",IF(Cartera[[#This Row],[Tipo]]=200,"Lom",IF(Cartera[[#This Row],[Tipo]]=224,"Lom",IF(Cartera[[#This Row],[Tipo]]=251,"Lom",IF(Cartera[[#This Row],[Tipo]]=651,"Magra",IF(Cartera[[#This Row],[Tipo]]=655,"Magra",IF(Cartera[[#This Row],[Tipo]]=601,"Magra",IF(Cartera[[#This Row],[Tipo]]=751,"Galan",IF(Cartera[[#This Row],[Tipo]]=757,"Galan",IF(Cartera[[#This Row],[Tipo]]=701,"Galan",IF(Cartera[[#This Row],[Tipo]]=755,"Galan",IF(Cartera[[#This Row],[Tipo]]="CO","Conciliacion Cartera","")))))))))))))) | X202: =_xlfn.XLOOKUP(Cartera[[#This Row],[Nombre tercero]],Vendedor[Nombre],Vendedor[Vendedor],"",0,-1) -> JORGE PARDO
A203: =+A202 -> ALIMENTOS BENAL SAS | B203: 751 | C203: 18396 | D203: 4 | E203: 46002.552 | F203: 46032.552 | G203: 4 | H203: 33600 | I203: 33600 | J203: 0 | K203: 33600 | L203: 0 | M203: 0 | N203: 0 | O203: 0 | P203: =SUM(Cartera[[#This Row],[1_a_8]:[>30]]) -> 33600 | Q203: =+Cartera[[#This Row],[9_a_15]]+Cartera[[#This Row],[16_a_22]]+Cartera[[#This Row],[23_a_30]] -> 0 | R203: =IF(Cartera[[#This Row],[Dias]]>8,Cartera[[#This Row],[Total vencido]],0) -> 0 | S203: =IF(Cartera[[#This Row],[Mas de 9]]>0,Cartera[[#This Row],[Dias]],0) -> 0 | T203: =IF(Cartera[[#This Row],[Dias]]>99,Cartera[[#This Row],[Total vencido]],0) -> 0 | U203: =IF(Cartera[[#This Row],[Mas de 100]]>0,Cartera[[#This Row],[Dias]],0) -> 0 | V203: =Cartera[[#This Row],[Vencimiento]]-Cartera[[#This Row],[Emision]] -> 30 | W203: =+IF(Cartera[[#This Row],[Tipo]]=151,"Lom",IF(Cartera[[#This Row],[Tipo]]=153,"Lom",IF(Cartera[[#This Row],[Tipo]]=155,"Lom",IF(Cartera[[#This Row],[Tipo]]=200,"Lom",IF(Cartera[[#This Row],[Tipo]]=224,"Lom",IF(Cartera[[#This Row],[Tipo]]=251,"Lom",IF(Cartera[[#This Row],[Tipo]]=651,"Magra",IF(Cartera[[#This Row],[Tipo]]=655,"Magra",IF(Cartera[[#This Row],[Tipo]]=601,"Magra",IF(Cartera[[#This Row],[Tipo]]=751,"Galan",IF(Cartera[[#This Row],[Tipo]]=757,"Galan",IF(Cartera[[#This Row],[Tipo]]=701,"Galan",IF(Cartera[[#This Row],[Tipo]]=755,"Galan",IF(Cartera[[#This Row],[Tipo]]="CO","Conciliacion Cartera","")))))))))))))) | X203: =_xlfn.XLOOKUP(Cartera[[#This Row],[Nombre tercero]],Vendedor[Nombre],Vendedor[Vendedor],"",0,-1) -> JORGE PARDO
A204: =+A203 -> ALIMENTOS BENAL SAS | B204: 751 | C204: 18513 | D204: 4 | E204: 46006.312 | F204: 46036.312 | G204: 0 | H204: 6153000 | I204: 6153000 | J204: 6153000 | K204: 0 | L204: 0 | M204: 0 | N204: 0 | O204: 0 | P204: =SUM(Cartera[[#This Row],[1_a_8]:[>30]]) -> 0 | Q204: =+Cartera[[#This Row],[9_a_15]]+Cartera[[#This Row],[16_a_22]]+Cartera[[#This Row],[23_a_30]] -> 0 | R204: =IF(Cartera[[#This Row],[Dias]]>8,Cartera[[#This Row],[Total vencido]],0) -> 0 | S204: =IF(Cartera[[#This Row],[Mas de 9]]>0,Cartera[[#This Row],[Dias]],0) -> 0 | T204: =IF(Cartera[[#This Row],[Dias]]>99,Cartera[[#This Row],[Total vencido]],0) -> 0 | U204: =IF(Cartera[[#This Row],[Mas de 100]]>0,Cartera[[#This Row],[Dias]],0) -> 0 | V204: =Cartera[[#This Row],[Vencimiento]]-Cartera[[#This Row],[Emision]] -> 29.999907 | W204: =+IF(Cartera[[#This Row],[Tipo]]=151,"Lom",IF(Cartera[[#This Row],[Tipo]]=153,"Lom",IF(Cartera[[#This Row],[Tipo]]=155,"Lom",IF(Cartera[[#This Row],[Tipo]]=200,"Lom",IF(Cartera[[#This Row],[Tipo]]=224,"Lom",IF(Cartera[[#This Row],[Tipo]]=251,"Lom",IF(Cartera[[#This Row],[Tipo]]=651,"Magra",IF(Cartera[[#This Row],[Tipo]]=655,"Magra",IF(Cartera[[#This Row],[Tipo]]=601,"Magra",IF(Cartera[[#This Row],[Tipo]]=751,"Galan",IF(Cartera[[#This Row],[Tipo]]=757,"Galan",IF(Cartera[[#This Row],[Tipo]]=701,"Galan",IF(Cartera[[#This Row],[Tipo]]=755,"Galan",IF(Cartera[[#This Row],[Tipo]]="CO","Conciliacion Cartera","")))))))))))))) | X204: =_xlfn.XLOOKUP(Cartera[[#This Row],[Nombre tercero]],Vendedor[Nombre],Vendedor[Vendedor],"",0,-1) -> JORGE PARDO
A205: =+A204 -> ALIMENTOS BENAL SAS | B205: 751 | C205: 18558 | D205: 4 | E205: 46007.542 | F205: 46037.536 | G205: -1 | H205: 7100800 | I205: 7100800 | J205: 7100800 | K205: 0 | L205: 0 | M205: 0 | N205: 0 | O205: 0 | P205: =SUM(Cartera[[#This Row],[1_a_8]:[>30]]) -> 0 | Q205: =+Cartera[[#This Row],[9_a_15]]+Cartera[[#This Row],[16_a_22]]+Cartera[[#This Row],[23_a_30]] -> 0 | R205: =IF(Cartera[[#This Row],[Dias]]>8,Cartera[[#This Row],[Total vencido]],0) -> 0 | S205: =IF(Cartera[[#This Row],[Mas de 9]]>0,Cartera[[#This Row],[Dias]],0) -> 0 | T205: =IF(Cartera[[#This Row],[Dias]]>99,Cartera[[#This Row],[Total vencido]],0) -> 0 | U205: =IF(Cartera[[#This Row],[Mas de 100]]>0,Cartera[[#This Row],[Dias]],0) -> 0 | V205: =Cartera[[#This Row],[Vencimiento]]-Cartera[[#This Row],[Emision]] -> 29.994421 | W205: =+IF(Cartera[[#This Row],[Tipo]]=151,"Lom",IF(Cartera[[#This Row],[Tipo]]=153,"Lom",IF(Cartera[[#This Row],[Tipo]]=155,"Lom",IF(Cartera[[#This Row],[Tipo]]=200,"Lom",IF(Cartera[[#This Row],[Tipo]]=224,"Lom",IF(Cartera[[#This Row],[Tipo]]=251,"Lom",IF(Cartera[[#This Row],[Tipo]]=651,"Magra",IF(Cartera[[#This Row],[Tipo]]=655,"Magra",IF(Cartera[[#This Row],[Tipo]]=601,"Magra",IF(Cartera[[#This Row],[Tipo]]=751,"Galan",IF(Cartera[[#This Row],[Tipo]]=757,"Galan",IF(Cartera[[#This Row],[Tipo]]=701,"Galan",IF(Cartera[[#This Row],[Tipo]]=755,"Galan",IF(Cartera[[#This Row],[Tipo]]="CO","Conciliacion Cartera","")))))))))))))) | X205: =_xlfn.XLOOKUP(Cartera[[#This Row],[Nombre tercero]],Vendedor[Nombre],Vendedor[Vendedor],"",0,-1) -> JORGE PARDO
A206: =+A205 -> ALIMENTOS BENAL SAS | B206: 751 | C206: 18590 | D206: 4 | E206: 46008.36 | F206: 46038.36 | G206: -2 | H206: 882000 | I206: 882000 | J206: 882000 | K206: 0 | L206: 0 | M206: 0 | N206: 0 | O206: 0 | P206: =SUM(Cartera[[#This Row],[1_a_8]:[>30]]) -> 0 | Q206: =+Cartera[[#This Row],[9_a_15]]+Cartera[[#This Row],[16_a_22]]+Cartera[[#This Row],[23_a_30]] -> 0 | R206: =IF(Cartera[[#This Row],[Dias]]>8,Cartera[[#This Row],[Total vencido]],0) -> 0 | S206: =IF(Cartera[[#This Row],[Mas de 9]]>0,Cartera[[#This Row],[Dias]],0) -> 0 | T206: =IF(Cartera[[#This Row],[Dias]]>99,Cartera[[#This Row],[Total vencido]],0) -> 0 | U206: =IF(Cartera[[#This Row],[Mas de 100]]>0,Cartera[[#This Row],[Dias]],0) -> 0 | V206: =Cartera[[#This Row],[Vencimiento]]-Cartera[[#This Row],[Emision]] -> 29.999919 | W206: =+IF(Cartera[[#This Row],[Tipo]]=151,"Lom",IF(Cartera[[#This Row],[Tipo]]=153,"Lom",IF(Cartera[[#This Row],[Tipo]]=155,"Lom",IF(Cartera[[#This Row],[Tipo]]=200,"Lom",IF(Cartera[[#This Row],[Tipo]]=224,"Lom",IF(Cartera[[#This Row],[Tipo]]=251,"Lom",IF(Cartera[[#This Row],[Tipo]]=651,"Magra",IF(Cartera[[#This Row],[Tipo]]=655,"Magra",IF(Cartera[[#This Row],[Tipo]]=601,"Magra",IF(Cartera[[#This Row],[Tipo]]=751,"Galan",IF(Cartera[[#This Row],[Tipo]]=757,"Galan",IF(Cartera[[#This Row],[Tipo]]=701,"Galan",IF(Cartera[[#This Row],[Tipo]]=755,"Galan",IF(Cartera[[#This Row],[Tipo]]="CO","Conciliacion Cartera","")))))))))))))) | X206: =_xlfn.XLOOKUP(Cartera[[#This Row],[Nombre tercero]],Vendedor[Nombre],Vendedor[Vendedor],"",0,-1) -> JORGE PARDO
A207: =+A206 -> ALIMENTOS BENAL SAS | B207: 751 | C207: 18629 | D207: 4 | E207: 46008.624 | F207: 46038.624 | G207: -2 | H207: 318000 | I207: 318000 | J207: 318000 | K207: 0 | L207: 0 | M207: 0 | N207: 0 | O207: 0 | P207: =SUM(Cartera[[#This Row],[1_a_8]:[>30]]) -> 0 | Q207: =+Cartera[[#This Row],[9_a_15]]+Cartera[[#This Row],[16_a_22]]+Cartera[[#This Row],[23_a_30]] -> 0 | R207: =IF(Cartera[[#This Row],[Dias]]>8,Cartera[[#This Row],[Total vencido]],0) -> 0 | S207: =IF(Cartera[[#This Row],[Mas de 9]]>0,Cartera[[#This Row],[Dias]],0) -> 0 | T207: =IF(Cartera[[#This Row],[Dias]]>99,Cartera[[#This Row],[Total vencido]],0) -> 0 | U207: =IF(Cartera[[#This Row],[Mas de 100]]>0,Cartera[[#This Row],[Dias]],0) -> 0 | V207: =Cartera[[#This Row],[Vencimiento]]-Cartera[[#This Row],[Emision]] -> 29.999769 | W207: =+IF(Cartera[[#This Row],[Tipo]]=151,"Lom",IF(Cartera[[#This Row],[Tipo]]=153,"Lom",IF(Cartera[[#This Row],[Tipo]]=155,"Lom",IF(Cartera[[#This Row],[Tipo]]=200,"Lom",IF(Cartera[[#This Row],[Tipo]]=224,"Lom",IF(Cartera[[#This Row],[Tipo]]=251,"Lom",IF(Cartera[[#This Row],[Tipo]]=651,"Magra",IF(Cartera[[#This Row],[Tipo]]=655,"Magra",IF(Cartera[[#This Row],[Tipo]]=601,"Magra",IF(Cartera[[#This Row],[Tipo]]=751,"Galan",IF(Cartera[[#This Row],[Tipo]]=757,"Galan",IF(Cartera[[#This Row],[Tipo]]=701,"Galan",IF(Cartera[[#This Row],[Tipo]]=755,"Galan",IF(Cartera[[#This Row],[Tipo]]="CO","Conciliacion Cartera","")))))))))))))) | X207: =_xlfn.XLOOKUP(Cartera[[#This Row],[Nombre tercero]],Vendedor[Nombre],Vendedor[Vendedor],"",0,-1) -> JORGE PARDO
A208: =+A207 -> ALIMENTOS BENAL SAS | B208: 751 | C208: 18898 | D208: 4 | E208: 46017.213 | F208: 46047.213 | G208: -11 | H208: 11167200 | I208: 11167200 | J208: 11167200 | K208: 0 | L208: 0 | M208: 0 | N208: 0 | O208: 0 | P208: =SUM(Cartera[[#This Row],[1_a_8]:[>30]]) -> 0 | Q208: =+Cartera[[#This Row],[9_a_15]]+Cartera[[#This Row],[16_a_22]]+Cartera[[#This Row],[23_a_30]] -> 0 | R208: =IF(Cartera[[#This Row],[Dias]]>8,Cartera[[#This Row],[Total vencido]],0) -> 0 | S208: =IF(Cartera[[#This Row],[Mas de 9]]>0,Cartera[[#This Row],[Dias]],0) -> 0 | T208: =IF(Cartera[[#This Row],[Dias]]>99,Cartera[[#This Row],[Total vencido]],0) -> 0 | U208: =IF(Cartera[[#This Row],[Mas de 100]]>0,Cartera[[#This Row],[Dias]],0) -> 0 | V208: =Cartera[[#This Row],[Vencimiento]]-Cartera[[#This Row],[Emision]] -> 29.999757 | W208: =+IF(Cartera[[#This Row],[Tipo]]=151,"Lom",IF(Cartera[[#This Row],[Tipo]]=153,"Lom",IF(Cartera[[#This Row],[Tipo]]=155,"Lom",IF(Cartera[[#This Row],[Tipo]]=200,"Lom",IF(Cartera[[#This Row],[Tipo]]=224,"Lom",IF(Cartera[[#This Row],[Tipo]]=251,"Lom",IF(Cartera[[#This Row],[Tipo]]=651,"Magra",IF(Cartera[[#This Row],[Tipo]]=655,"Magra",IF(Cartera[[#This Row],[Tipo]]=601,"Magra",IF(Cartera[[#This Row],[Tipo]]=751,"Galan",IF(Cartera[[#This Row],[Tipo]]=757,"Galan",IF(Cartera[[#This Row],[Tipo]]=701,"Galan",IF(Cartera[[#This Row],[Tipo]]=755,"Galan",IF(Cartera[[#This Row],[Tipo]]="CO","Conciliacion Cartera","")))))))))))))) | X208: =_xlfn.XLOOKUP(Cartera[[#This Row],[Nombre tercero]],Vendedor[Nombre],Vendedor[Vendedor],"",0,-1) -> JORGE PARDO
A209: =+A208 -> ALIMENTOS BENAL SAS | B209: 751 | C209: 18941 | D209: 4 | E209: 46018.508 | F209: 46048.508 | G209: -12 | H209: 4173600 | I209: 4173600 | J209: 4173600 | K209: 0 | L209: 0 | M209: 0 | N209: 0 | O209: 0 | P209: =SUM(Cartera[[#This Row],[1_a_8]:[>30]]) -> 0 | Q209: =+Cartera[[#This Row],[9_a_15]]+Cartera[[#This Row],[16_a_22]]+Cartera[[#This Row],[23_a_30]] -> 0 | R209: =IF(Cartera[[#This Row],[Dias]]>8,Cartera[[#This Row],[Total vencido]],0) -> 0 | S209: =IF(Cartera[[#This Row],[Mas de 9]]>0,Cartera[[#This Row],[Dias]],0) -> 0 | T209: =IF(Cartera[[#This Row],[Dias]]>99,Cartera[[#This Row],[Total vencido]],0) -> 0 | U209: =IF(Cartera[[#This Row],[Mas de 100]]>0,Cartera[[#This Row],[Dias]],0) -> 0 | V209: =Cartera[[#This Row],[Vencimiento]]-Cartera[[#This Row],[Emision]] -> 29.999873 | W209: =+IF(Cartera[[#This Row],[Tipo]]=151,"Lom",IF(Cartera[[#This Row],[Tipo]]=153,"Lom",IF(Cartera[[#This Row],[Tipo]]=155,"Lom",IF(Cartera[[#This Row],[Tipo]]=200,"Lom",IF(Cartera[[#This Row],[Tipo]]=224,"Lom",IF(Cartera[[#This Row],[Tipo]]=251,"Lom",IF(Cartera[[#This Row],[Tipo]]=651,"Magra",IF(Cartera[[#This Row],[Tipo]]=655,"Magra",IF(Cartera[[#This Row],[Tipo]]=601,"Magra",IF(Cartera[[#This Row],[Tipo]]=751,"Galan",IF(Cartera[[#This Row],[Tipo]]=757,"Galan",IF(Cartera[[#This Row],[Tipo]]=701,"Galan",IF(Cartera[[#This Row],[Tipo]]=755,"Galan",IF(Cartera[[#This Row],[Tipo]]="CO","Conciliacion Cartera","")))))))))))))) | X209: =_xlfn.XLOOKUP(Cartera[[#This Row],[Nombre tercero]],Vendedor[Nombre],Vendedor[Vendedor],"",0,-1) -> JORGE PARDO
A210: =+A209 -> ALIMENTOS BENAL SAS | B210: 751 | C210: 18963 | D210: 4 | E210: 46020.279 | F210: 46050.275 | G210: -14 | H210: 207000 | I210: 207000 | J210: 207000 | K210: 0 | L210: 0 | M210: 0 | N210: 0 | O210: 0 | P210: =SUM(Cartera[[#This Row],[1_a_8]:[>30]]) -> 0 | Q210: =+Cartera[[#This Row],[9_a_15]]+Cartera[[#This Row],[16_a_22]]+Cartera[[#This Row],[23_a_30]] -> 0 | R210: =IF(Cartera[[#This Row],[Dias]]>8,Cartera[[#This Row],[Total vencido]],0) -> 0 | S210: =IF(Cartera[[#This Row],[Mas de 9]]>0,Cartera[[#This Row],[Dias]],0) -> 0 | T210: =IF(Cartera[[#This Row],[Dias]]>99,Cartera[[#This Row],[Total vencido]],0) -> 0 | U210: =IF(Cartera[[#This Row],[Mas de 100]]>0,Cartera[[#This Row],[Dias]],0) -> 0 | V210: =Cartera[[#This Row],[Vencimiento]]-Cartera[[#This Row],[Emision]] -> 29.995093 | W210: =+IF(Cartera[[#This Row],[Tipo]]=151,"Lom",IF(Cartera[[#This Row],[Tipo]]=153,"Lom",IF(Cartera[[#This Row],[Tipo]]=155,"Lom",IF(Cartera[[#This Row],[Tipo]]=200,"Lom",IF(Cartera[[#This Row],[Tipo]]=224,"Lom",IF(Cartera[[#This Row],[Tipo]]=251,"Lom",IF(Cartera[[#This Row],[Tipo]]=651,"Magra",IF(Cartera[[#This Row],[Tipo]]=655,"Magra",IF(Cartera[[#This Row],[Tipo]]=601,"Magra",IF(Cartera[[#This Row],[Tipo]]=751,"Galan",IF(Cartera[[#This Row],[Tipo]]=757,"Galan",IF(Cartera[[#This Row],[Tipo]]=701,"Galan",IF(Cartera[[#This Row],[Tipo]]=755,"Galan",IF(Cartera[[#This Row],[Tipo]]="CO","Conciliacion Cartera","")))))))))))))) | X210: =_xlfn.XLOOKUP(Cartera[[#This Row],[Nombre tercero]],Vendedor[Nombre],Vendedor[Vendedor],"",0,-1) -> JORGE PARDO
... A212: =+A211 -> ALIMENTOS BENAL SAS | B212: 751 | C212: 19039 | D212: 4 | E212: 46022.686 | F212: 46052.686 | G212: -16 | H212: 40950 | I212: 40950 | J212: 40950 | K212: 0 | L212: 0 | M212: 0 | N212: 0 | O212: 0 | P212: =SUM(Cartera[[#This Row],[1_a_8]:[>30]]) -> 0 | Q212: =+Cartera[[#This Row],[9_a_15]]+Cartera[[#This Row],[16_a_22]]+Cartera[[#This Row],[23_a_30]] -> 0 | R212: =IF(Cartera[[#This Row],[Dias]]>8,Cartera[[#This Row],[Total vencido]],0) -> 0 | S212: =IF(Cartera[[#This Row],[Mas de 9]]>0,Cartera[[#This Row],[Dias]],0) -> 0 | T212: =IF(Cartera[[#This Row],[Dias]]>99,Cartera[[#This Row],[Total vencido]],0) -> 0 | U212: =IF(Cartera[[#This Row],[Mas de 100]]>0,Cartera[[#This Row],[Dias]],0) -> 0 | V212: =Cartera[[#This Row],[Vencimiento]]-Cartera[[#This Row],[Emision]] -> 30 | W212: =+IF(Cartera[[#This Row],[Tipo]]=151,"Lom",IF(Cartera[[#This Row],[Tipo]]=153,"Lom",IF(Cartera[[#This Row],[Tipo]]=155,"Lom",IF(Cartera[[#This Row],[Tipo]]=200,"Lom",IF(Cartera[[#This Row],[Tipo]]=224,"Lom",IF(Cartera[[#This Row],[Tipo]]=251,"Lom",IF(Cartera[[#This Row],[Tipo]]=651,"Magra",IF(Cartera[[#This Row],[Tipo]]=655,"Magra",IF(Cartera[[#This Row],[Tipo]]=601,"Magra",IF(Cartera[[#This Row],[Tipo]]=751,"Galan",IF(Cartera[[#This Row],[Tipo]]=757,"Galan",IF(Cartera[[#This Row],[Tipo]]=701,"Galan",IF(Cartera[[#This Row],[Tipo]]=755,"Galan",IF(Cartera[[#This Row],[Tipo]]="CO","Conciliacion Cartera","")))))))))))))) | X212: =_xlfn.XLOOKUP(Cartera[[#This Row],[Nombre tercero]],Vendedor[Nombre],Vendedor[Vendedor],"",0,-1) -> JORGE PARDO
A213: ALTO BISTRO SAS | B213: 151 | C213: 22984 | D213: 4 | E213: 45996.352 | F213: 45997.346 | G213: 39 | H213: 357200 | I213: 339150 | J213: 0 | K213: 0 | L213: 0 | M213: 0 | N213: 0 | O213: 339150 | P213: =SUM(Cartera[[#This Row],[1_a_8]:[>30]]) -> 339150 | Q213: =+Cartera[[#This Row],[9_a_15]]+Cartera[[#This Row],[16_a_22]]+Cartera[[#This Row],[23_a_30]] -> 0 | R213: =IF(Cartera[[#This Row],[Dias]]>8,Cartera[[#This Row],[Total vencido]],0) -> 339150 | S213: =IF(Cartera[[#This Row],[Mas de 9]]>0,Cartera[[#This Row],[Dias]],0) -> 39 | T213: =IF(Cartera[[#This Row],[Dias]]>99,Cartera[[#This Row],[Total vencido]],0) -> 0 | U213: =IF(Cartera[[#This Row],[Mas de 100]]>0,Cartera[[#This Row],[Dias]],0) -> 0 | V213: =Cartera[[#This Row],[Vencimiento]]-Cartera[[#This Row],[Emision]] -> 0.99400463 | W213: =+IF(Cartera[[#This Row],[Tipo]]=151,"Lom",IF(Cartera[[#This Row],[Tipo]]=153,"Lom",IF(Cartera[[#This Row],[Tipo]]=155,"Lom",IF(Cartera[[#This Row],[Tipo]]=200,"Lom",IF(Cartera[[#This Row],[Tipo]]=224,"Lom",IF(Cartera[[#This Row],[Tipo]]=251,"Lom",IF(Cartera[[#This Row],[Tipo]]=651,"Magra",IF(Cartera[[#This Row],[Tipo]]=655,"Magra",IF(Cartera[[#This Row],[Tipo]]=601,"Magra",IF(Cartera[[#This Row],[Tipo]]=751,"Galan",IF(Cartera[[#This Row],[Tipo]]=757,"Galan",IF(Cartera[[#This Row],[Tipo]]=701,"Galan",IF(Cartera[[#This Row],[Tipo]]=755,"Galan",IF(Cartera[[#This Row],[Tipo]]="CO","Conciliacion Cartera","")))))))))))))) | X213: =_xlfn.XLOOKUP(Cartera[[#This Row],[Nombre tercero]],Vendedor[Nombre],Vendedor[Vendedor],"",0,-1) -> ANGELA SILVESTRE
A214: =+A213 -> ALTO BISTRO SAS | B214: 151 | C214: 23324 | D214: 4 | E214: 46008.38 | F214: 46009.379 | G214: 27 | H214: 552900 | I214: 547200 | J214: 0 | K214: 0 | L214: 0 | M214: 0 | N214: 547200 | O214: 0 | P214: =SUM(Cartera[[#This Row],[1_a_8]:[>30]]) -> 547200 | Q214: =+Cartera[[#This Row],[9_a_15]]+Cartera[[#This Row],[16_a_22]]+Cartera[[#This Row],[23_a_30]] -> 547200 | R214: =IF(Cartera[[#This Row],[Dias]]>8,Cartera[[#This Row],[Total vencido]],0) -> 547200 | S214: =IF(Cartera[[#This Row],[Mas de 9]]>0,Cartera[[#This Row],[Dias]],0) -> 27 | T214: =IF(Cartera[[#This Row],[Dias]]>99,Cartera[[#This Row],[Total vencido]],0) -> 0 | U214: =IF(Cartera[[#This Row],[Mas de 100]]>0,Cartera[[#This Row],[Dias]],0) -> 0 | V214: =Cartera[[#This Row],[Vencimiento]]-Cartera[[#This Row],[Emision]] -> 0.9994213 | W214: =+IF(Cartera[[#This Row],[Tipo]]=151,"Lom",IF(Cartera[[#This Row],[Tipo]]=153,"Lom",IF(Cartera[[#This Row],[Tipo]]=155,"Lom",IF(Cartera[[#This Row],[Tipo]]=200,"Lom",IF(Cartera[[#This Row],[Tipo]]=224,"Lom",IF(Cartera[[#This Row],[Tipo]]=251,"Lom",IF(Cartera[[#This Row],[Tipo]]=651,"Magra",IF(Cartera[[#This Row],[Tipo]]=655,"Magra",IF(Cartera[[#This Row],[Tipo]]=601,"Magra",IF(Cartera[[#This Row],[Tipo]]=751,"Galan",IF(Cartera[[#This Row],[Tipo]]=757,"Galan",IF(Cartera[[#This Row],[Tipo]]=701,"Galan",IF(Cartera[[#This Row],[Tipo]]=755,"Galan",IF(Cartera[[#This Row],[Tipo]]="CO","Conciliacion Cartera","")))))))))))))) | X214: =_xlfn.XLOOKUP(Cartera[[#This Row],[Nombre tercero]],Vendedor[Nombre],Vendedor[Vendedor],"",0,-1) -> ANGELA SILVESTRE
A215: ANA MARIA DANGOND | B215: 751 | C215: 18401 | D215: 1 | E215: 46002.579 | F215: 46003.577 | G215: 33 | H215: 444600 | I215: 444600 | J215: 0 | K215: 0 | L215: 0 | M215: 0 | N215: 0 | O215: 444600 | P215: =SUM(Cartera[[#This Row],[1_a_8]:[>30]]) -> 444600 | Q215: =+Cartera[[#This Row],[9_a_15]]+Cartera[[#This Row],[16_a_22]]+Cartera[[#This Row],[23_a_30]] -> 0 | R215: =IF(Cartera[[#This Row],[Dias]]>8,Cartera[[#This Row],[Total vencido]],0) -> 444600 | S215: =IF(Cartera[[#This Row],[Mas de 9]]>0,Cartera[[#This Row],[Dias]],0) -> 33 | T215: =IF(Cartera[[#This Row],[Dias]]>99,Cartera[[#This Row],[Total vencido]],0) -> 0 | U215: =IF(Cartera[[#This Row],[Mas de 100]]>0,Cartera[[#This Row],[Dias]],0) -> 0 | V215: =Cartera[[#This Row],[Vencimiento]]-Cartera[[#This Row],[Emision]] -> 0.99881944 | W215: =+IF(Cartera[[#This Row],[Tipo]]=151,"Lom",IF(Cartera[[#This Row],[Tipo]]=153,"Lom",IF(Cartera[[#This Row],[Tipo]]=155,"Lom",IF(Cartera[[#This Row],[Tipo]]=200,"Lom",IF(Cartera[[#This Row],[Tipo]]=224,"Lom",IF(Cartera[[#This Row],[Tipo]]=251,"Lom",IF(Cartera[[#This Row],[Tipo]]=651,"Magra",IF(Cartera[[#This Row],[Tipo]]=655,"Magra",IF(Cartera[[#This Row],[Tipo]]=601,"Magra",IF(Cartera[[#This Row],[Tipo]]=751,"Galan",IF(Cartera[[#This Row],[Tipo]]=757,"Galan",IF(Cartera[[#This Row],[Tipo]]=701,"Galan",IF(Cartera[[#This Row],[Tipo]]=755,"Galan",IF(Cartera[[#This Row],[Tipo]]="CO","Conciliacion Cartera","")))))))))))))) | X215: =_xlfn.XLOOKUP(Cartera[[#This Row],[Nombre tercero]],Vendedor[Nombre],Vendedor[Vendedor],"",0,-1) -> ANGELA SILVESTRE
A216: AVICOLA RENACER MC SAS | B216: 151 | C216: 23750 | D216: 13 | E216: 46022.246 | F216: 46023.246 | G216: 13 | H216: 299360 | I216: 299360 | J216: 0 | K216: 0 | L216: 299360 | M216: 0 | N216: 0 | O216: 0 | P216: =SUM(Cartera[[#This Row],[1_a_8]:[>30]]) -> 299360 | Q216: =+Cartera[[#This Row],[9_a_15]]+Cartera[[#This Row],[16_a_22]]+Cartera[[#This Row],[23_a_30]] -> 299360 | R216: =IF(Cartera[[#This Row],[Dias]]>8,Cartera[[#This Row],[Total vencido]],0) -> 299360 | S216: =IF(Cartera[[#This Row],[Mas de 9]]>0,Cartera[[#This Row],[Dias]],0) -> 13 | T216: =IF(Cartera[[#This Row],[Dias]]>99,Cartera[[#This Row],[Total vencido]],0) -> 0 | U216: =IF(Cartera[[#This Row],[Mas de 100]]>0,Cartera[[#This Row],[Dias]],0) -> 0 | V216: =Cartera[[#This Row],[Vencimiento]]-Cartera[[#This Row],[Emision]] -> 0.99975694 | W216: =+IF(Cartera[[#This Row],[Tipo]]=151,"Lom",IF(Cartera[[#This Row],[Tipo]]=153,"Lom",IF(Cartera[[#This Row],[Tipo]]=155,"Lom",IF(Cartera[[#This Row],[Tipo]]=200,"Lom",IF(Cartera[[#This Row],[Tipo]]=224,"Lom",IF(Cartera[[#This Row],[Tipo]]=251,"Lom",IF(Cartera[[#This Row],[Tipo]]=651,"Magra",IF(Cartera[[#This Row],[Tipo]]=655,"Magra",IF(Cartera[[#This Row],[Tipo]]=601,"Magra",IF(Cartera[[#This Row],[Tipo]]=751,"Galan",IF(Cartera[[#This Row],[Tipo]]=757,"Galan",IF(Cartera[[#This Row],[Tipo]]=701,"Galan",IF(Cartera[[#This Row],[Tipo]]=755,"Galan",IF(Cartera[[#This Row],[Tipo]]="CO","Conciliacion Cartera","")))))))))))))) | X216: =_xlfn.XLOOKUP(Cartera[[#This Row],[Nombre tercero]],Vendedor[Nombre],Vendedor[Vendedor],"",0,-1) -> JORGE PORRAS
A217: AZOTEA BARBECUE S.A.S. | B217: 151 | C217: 23549 | D217: 11 | E217: 46014.35 | F217: 46022.35 | G217: 14 | H217: 98200 | I217: 98200 | J217: 0 | K217: 0 | L217: 98200 | M217: 0 | N217: 0 | O217: 0 | P217: =SUM(Cartera[[#This Row],[1_a_8]:[>30]]) -> 98200 | Q217: =+Cartera[[#This Row],[9_a_15]]+Cartera[[#This Row],[16_a_22]]+Cartera[[#This Row],[23_a_30]] -> 98200 | R217: =IF(Cartera[[#This Row],[Dias]]>8,Cartera[[#This Row],[Total vencido]],0) -> 98200 | S217: =IF(Cartera[[#This Row],[Mas de 9]]>0,Cartera[[#This Row],[Dias]],0) -> 14 | T217: =IF(Cartera[[#This Row],[Dias]]>99,Cartera[[#This Row],[Total vencido]],0) -> 0 | U217: =IF(Cartera[[#This Row],[Mas de 100]]>0,Cartera[[#This Row],[Dias]],0) -> 0 | V217: =Cartera[[#This Row],[Vencimiento]]-Cartera[[#This Row],[Emision]] -> 7.9998264 | W217: =+IF(Cartera[[#This Row],[Tipo]]=151,"Lom",IF(Cartera[[#This Row],[Tipo]]=153,"Lom",IF(Cartera[[#This Row],[Tipo]]=155,"Lom",IF(Cartera[[#This Row],[Tipo]]=200,"Lom",IF(Cartera[[#This Row],[Tipo]]=224,"Lom",IF(Cartera[[#This Row],[Tipo]]=251,"Lom",IF(Cartera[[#This Row],[Tipo]]=651,"Magra",IF(Cartera[[#This Row],[Tipo]]=655,"Magra",IF(Cartera[[#This Row],[Tipo]]=601,"Magra",IF(Cartera[[#This Row],[Tipo]]=751,"Galan",IF(Cartera[[#This Row],[Tipo]]=757,"Galan",IF(Cartera[[#This Row],[Tipo]]=701,"Galan",IF(Cartera[[#This Row],[Tipo]]=755,"Galan",IF(Cartera[[#This Row],[Tipo]]="CO","Conciliacion Cartera","")))))))))))))) | X217: =_xlfn.XLOOKUP(Cartera[[#This Row],[Nombre tercero]],Vendedor[Nombre],Vendedor[Vendedor],"",0,-1) -> JENNY ANDREA DIAZ
A218: BACO FOODS COLOMBIA S.A.S | B218: 751 | C218: 18000 | D218: 8 | E218: 45992.21 | F218: 46022.209 | G218: 14 | H218: 1156000 | I218: 1156000 | J218: 0 | K218: 0 | L218: 1156000 | M218: 0 | N218: 0 | O218: 0 | P218: =SUM(Cartera[[#This Row],[1_a_8]:[>30]]) -> 1156000 | Q218: =+Cartera[[#This Row],[9_a_15]]+Cartera[[#This Row],[16_a_22]]+Cartera[[#This Row],[23_a_30]] -> 1156000 | R218: =IF(Cartera[[#This Row],[Dias]]>8,Cartera[[#This Row],[Total vencido]],0) -> 1156000 | S218: =IF(Cartera[[#This Row],[Mas de 9]]>0,Cartera[[#This Row],[Dias]],0) -> 14 | T218: =IF(Cartera[[#This Row],[Dias]]>99,Cartera[[#This Row],[Total vencido]],0) -> 0 | U218: =IF(Cartera[[#This Row],[Mas de 100]]>0,Cartera[[#This Row],[Dias]],0) -> 0 | V218: =Cartera[[#This Row],[Vencimiento]]-Cartera[[#This Row],[Emision]] -> 29.999699 | W218: =+IF(Cartera[[#This Row],[Tipo]]=151,"Lom",IF(Cartera[[#This Row],[Tipo]]=153,"Lom",IF(Cartera[[#This Row],[Tipo]]=155,"Lom",IF(Cartera[[#This Row],[Tipo]]=200,"Lom",IF(Cartera[[#This Row],[Tipo]]=224,"Lom",IF(Cartera[[#This Row],[Tipo]]=251,"Lom",IF(Cartera[[#This Row],[Tipo]]=651,"Magra",IF(Cartera[[#This Row],[Tipo]]=655,"Magra",IF(Cartera[[#This Row],[Tipo]]=601,"Magra",IF(Cartera[[#This Row],[Tipo]]=751,"Galan",IF(Cartera[[#This Row],[Tipo]]=757,"Galan",IF(Cartera[[#This Row],[Tipo]]=701,"Galan",IF(Cartera[[#This Row],[Tipo]]=755,"Galan",IF(Cartera[[#This Row],[Tipo]]="CO","Conciliacion Cartera","")))))))))))))) | X218: =_xlfn.XLOOKUP(Cartera[[#This Row],[Nombre tercero]],Vendedor[Nombre],Vendedor[Vendedor],"",0,-1) -> WILLIAM DARIO PADILLA
A219: =+A218 -> BACO FOODS COLOMBIA S.A.S | B219: 751 | C219: 18047 | D219: 8 | E219: 45992.603 | F219: 46022.603 | G219: 14 | H219: 723600 | I219: 723600 | J219: 0 | K219: 0 | L219: 723600 | M219: 0 | N219: 0 | O219: 0 | P219: =SUM(Cartera[[#This Row],[1_a_8]:[>30]]) -> 723600 | Q219: =+Cartera[[#This Row],[9_a_15]]+Cartera[[#This Row],[16_a_22]]+Cartera[[#This Row],[23_a_30]] -> 723600 | R219: =IF(Cartera[[#This Row],[Dias]]>8,Cartera[[#This Row],[Total vencido]],0) -> 723600 | S219: =IF(Cartera[[#This Row],[Mas de 9]]>0,Cartera[[#This Row],[Dias]],0) -> 14 | T219: =IF(Cartera[[#This Row],[Dias]]>99,Cartera[[#This Row],[Total vencido]],0) -> 0 | U219: =IF(Cartera[[#This Row],[Mas de 100]]>0,Cartera[[#This Row],[Dias]],0) -> 0 | V219: =Cartera[[#This Row],[Vencimiento]]-Cartera[[#This Row],[Emision]] -> 29.999861 | W219: =+IF(Cartera[[#This Row],[Tipo]]=151,"Lom",IF(Cartera[[#This Row],[Tipo]]=153,"Lom",IF(Cartera[[#This Row],[Tipo]]=155,"Lom",IF(Cartera[[#This Row],[Tipo]]=200,"Lom",IF(Cartera[[#This Row],[Tipo]]=224,"Lom",IF(Cartera[[#This Row],[Tipo]]=251,"Lom",IF(Cartera[[#This Row],[Tipo]]=651,"Magra",IF(Cartera[[#This Row],[Tipo]]=655,"Magra",IF(Cartera[[#This Row],[Tipo]]=601,"Magra",IF(Cartera[[#This Row],[Tipo]]=751,"Galan",IF(Cartera[[#This Row],[Tipo]]=757,"Galan",IF(Cartera[[#This Row],[Tipo]]=701,"Galan",IF(Cartera[[#This Row],[Tipo]]=755,"Galan",IF(Cartera[[#This Row],[Tipo]]="CO","Conciliacion Cartera","")))))))))))))) | X219: =_xlfn.XLOOKUP(Cartera[[#This Row],[Nombre tercero]],Vendedor[Nombre],Vendedor[Vendedor],"",0,-1) -> WILLIAM DARIO PADILLA
A220: =+A219 -> BACO FOODS COLOMBIA S.A.S | B220: 751 | C220: 18075 | D220: 8 | E220: 45993.455 | F220: 46023.455 | G220: 13 | H220: 1128000 | I220: 1128000 | J220: 0 | K220: 0 | L220: 1128000 | M220: 0 | N220: 0 | O220: 0 | P220: =SUM(Cartera[[#This Row],[1_a_8]:[>30]]) -> 1128000 | Q220: =+Cartera[[#This Row],[9_a_15]]+Cartera[[#This Row],[16_a_22]]+Cartera[[#This Row],[23_a_30]] -> 1128000 | R220: =IF(Cartera[[#This Row],[Dias]]>8,Cartera[[#This Row],[Total vencido]],0) -> 1128000 | S220: =IF(Cartera[[#This Row],[Mas de 9]]>0,Cartera[[#This Row],[Dias]],0) -> 13 | T220: =IF(Cartera[[#This Row],[Dias]]>99,Cartera[[#This Row],[Total vencido]],0) -> 0 | U220: =IF(Cartera[[#This Row],[Mas de 100]]>0,Cartera[[#This Row],[Dias]],0) -> 0 | V220: =Cartera[[#This Row],[Vencimiento]]-Cartera[[#This Row],[Emision]] -> 29.999699 | W220: =+IF(Cartera[[#This Row],[Tipo]]=151,"Lom",IF(Cartera[[#This Row],[Tipo]]=153,"Lom",IF(Cartera[[#This Row],[Tipo]]=155,"Lom",IF(Cartera[[#This Row],[Tipo]]=200,"Lom",IF(Cartera[[#This Row],[Tipo]]=224,"Lom",IF(Cartera[[#This Row],[Tipo]]=251,"Lom",IF(Cartera[[#This Row],[Tipo]]=651,"Magra",IF(Cartera[[#This Row],[Tipo]]=655,"Magra",IF(Cartera[[#This Row],[Tipo]]=601,"Magra",IF(Cartera[[#This Row],[Tipo]]=751,"Galan",IF(Cartera[[#This Row],[Tipo]]=757,"Galan",IF(Cartera[[#This Row],[Tipo]]=701,"Galan",IF(Cartera[[#This Row],[Tipo]]=755,"Galan",IF(Cartera[[#This Row],[Tipo]]="CO","Conciliacion Cartera","")))))))))))))) | X220: =_xlfn.XLOOKUP(Cartera[[#This Row],[Nombre tercero]],Vendedor[Nombre],Vendedor[Vendedor],"",0,-1) -> WILLIAM DARIO PADILLA
A221: =+A220 -> BACO FOODS COLOMBIA S.A.S | B221: 751 | C221: 18251 | D221: 8 | E221: 45997.538 | F221: 46027.538 | G221: 9 | H221: 867600 | I221: 867600 | J221: 0 | K221: 0 | L221: 867600 | M221: 0 | N221: 0 | O221: 0 | P221: =SUM(Cartera[[#This Row],[1_a_8]:[>30]]) -> 867600 | Q221: =+Cartera[[#This Row],[9_a_15]]+Cartera[[#This Row],[16_a_22]]+Cartera[[#This Row],[23_a_30]] -> 867600 | R221: =IF(Cartera[[#This Row],[Dias]]>8,Cartera[[#This Row],[Total vencido]],0) -> 867600 | S221: =IF(Cartera[[#This Row],[Mas de 9]]>0,Cartera[[#This Row],[Dias]],0) -> 9 | T221: =IF(Cartera[[#This Row],[Dias]]>99,Cartera[[#This Row],[Total vencido]],0) -> 0 | U221: =IF(Cartera[[#This Row],[Mas de 100]]>0,Cartera[[#This Row],[Dias]],0) -> 0 | V221: =Cartera[[#This Row],[Vencimiento]]-Cartera[[#This Row],[Emision]] -> 29.999861 | W221: =+IF(Cartera[[#This Row],[Tipo]]=151,"Lom",IF(Cartera[[#This Row],[Tipo]]=153,"Lom",IF(Cartera[[#This Row],[Tipo]]=155,"Lom",IF(Cartera[[#This Row],[Tipo]]=200,"Lom",IF(Cartera[[#This Row],[Tipo]]=224,"Lom",IF(Cartera[[#This Row],[Tipo]]=251,"Lom",IF(Cartera[[#This Row],[Tipo]]=651,"Magra",IF(Cartera[[#This Row],[Tipo]]=655,"Magra",IF(Cartera[[#This Row],[Tipo]]=601,"Magra",IF(Cartera[[#This Row],[Tipo]]=751,"Galan",IF(Cartera[[#This Row],[Tipo]]=757,"Galan",IF(Cartera[[#This Row],[Tipo]]=701,"Galan",IF(Cartera[[#This Row],[Tipo]]=755,"Galan",IF(Cartera[[#This Row],[Tipo]]="CO","Conciliacion Cartera","")))))))))))))) | X221: =_xlfn.XLOOKUP(Cartera[[#This Row],[Nombre tercero]],Vendedor[Nombre],Vendedor[Vendedor],"",0,-1) -> WILLIAM DARIO PADILLA
A222: =+A221 -> BACO FOODS COLOMBIA S.A.S | B222: 751 | C222: 18296 | D222: 8 | E222: 46000.523 | F222: 46030.523 | G222: 6 | H222: 1130000 | I222: 1130000 | J222: 0 | K222: 1130000 | L222: 0 | M222: 0 | N222: 0 | O222: 0 | P222: =SUM(Cartera[[#This Row],[1_a_8]:[>30]]) -> 1130000 | Q222: =+Cartera[[#This Row],[9_a_15]]+Cartera[[#This Row],[16_a_22]]+Cartera[[#This Row],[23_a_30]] -> 0 | R222: =IF(Cartera[[#This Row],[Dias]]>8,Cartera[[#This Row],[Total vencido]],0) -> 0 | S222: =IF(Cartera[[#This Row],[Mas de 9]]>0,Cartera[[#This Row],[Dias]],0) -> 0 | T222: =IF(Cartera[[#This Row],[Dias]]>99,Cartera[[#This Row],[Total vencido]],0) -> 0 | U222: =IF(Cartera[[#This Row],[Mas de 100]]>0,Cartera[[#This Row],[Dias]],0) -> 0 | V222: =Cartera[[#This Row],[Vencimiento]]-Cartera[[#This Row],[Emision]] -> 29.99985 | W222: =+IF(Cartera[[#This Row],[Tipo]]=151,"Lom",IF(Cartera[[#This Row],[Tipo]]=153,"Lom",IF(Cartera[[#This Row],[Tipo]]=155,"Lom",IF(Cartera[[#This Row],[Tipo]]=200,"Lom",IF(Cartera[[#This Row],[Tipo]]=224,"Lom",IF(Cartera[[#This Row],[Tipo]]=251,"Lom",IF(Cartera[[#This Row],[Tipo]]=651,"Magra",IF(Cartera[[#This Row],[Tipo]]=655,"Magra",IF(Cartera[[#This Row],[Tipo]]=601,"Magra",IF(Cartera[[#This Row],[Tipo]]=751,"Galan",IF(Cartera[[#This Row],[Tipo]]=757,"Galan",IF(Cartera[[#This Row],[Tipo]]=701,"Galan",IF(Cartera[[#This Row],[Tipo]]=755,"Galan",IF(Cartera[[#This Row],[Tipo]]="CO","Conciliacion Cartera","")))))))))))))) | X222: =_xlfn.XLOOKUP(Cartera[[#This Row],[Nombre tercero]],Vendedor[Nombre],Vendedor[Vendedor],"",0,-1) -> WILLIAM DARIO PADILLA
A223: =+A222 -> BACO FOODS COLOMBIA S.A.S | B223: 751 | C223: 18484 | D223: 8 | E223: 46004.402 | F223: 46034.402 | G223: 2 | H223: 1803600 | I223: 1803600 | J223: 0 | K223: 1803600 | L223: 0 | M223: 0 | N223: 0 | O223: 0 | P223: =SUM(Cartera[[#This Row],[1_a_8]:[>30]]) -> 1803600 | Q223: =+Cartera[[#This Row],[9_a_15]]+Cartera[[#This Row],[16_a_22]]+Cartera[[#This Row],[23_a_30]] -> 0 | R223: =IF(Cartera[[#This Row],[Dias]]>8,Cartera[[#This Row],[Total vencido]],0) -> 0 | S223: =IF(Cartera[[#This Row],[Mas de 9]]>0,Cartera[[#This Row],[Dias]],0) -> 0 | T223: =IF(Cartera[[#This Row],[Dias]]>99,Cartera[[#This Row],[Total vencido]],0) -> 0 | U223: =IF(Cartera[[#This Row],[Mas de 100]]>0,Cartera[[#This Row],[Dias]],0) -> 0 | V223: =Cartera[[#This Row],[Vencimiento]]-Cartera[[#This Row],[Emision]] -> 29.999884 | W223: =+IF(Cartera[[#This Row],[Tipo]]=151,"Lom",IF(Cartera[[#This Row],[Tipo]]=153,"Lom",IF(Cartera[[#This Row],[Tipo]]=155,"Lom",IF(Cartera[[#This Row],[Tipo]]=200,"Lom",IF(Cartera[[#This Row],[Tipo]]=224,"Lom",IF(Cartera[[#This Row],[Tipo]]=251,"Lom",IF(Cartera[[#This Row],[Tipo]]=651,"Magra",IF(Cartera[[#This Row],[Tipo]]=655,"Magra",IF(Cartera[[#This Row],[Tipo]]=601,"Magra",IF(Cartera[[#This Row],[Tipo]]=751,"Galan",IF(Cartera[[#This Row],[Tipo]]=757,"Galan",IF(Cartera[[#This Row],[Tipo]]=701,"Galan",IF(Cartera[[#This Row],[Tipo]]=755,"Galan",IF(Cartera[[#This Row],[Tipo]]="CO","Conciliacion Cartera","")))))))))))))) | X223: =_xlfn.XLOOKUP(Cartera[[#This Row],[Nombre tercero]],Vendedor[Nombre],Vendedor[Vendedor],"",0,-1) -> WILLIAM DARIO PADILLA
A224: =+A223 -> BACO FOODS COLOMBIA S.A.S | B224: 751 | C224: 18564 | D224: 8 | E224: 46007.555 | F224: 46037.554 | G224: -1 | H224: 1136000 | I224: 1136000 | J224: 1136000 | K224: 0 | L224: 0 | M224: 0 | N224: 0 | O224: 0 | P224: =SUM(Cartera[[#This Row],[1_a_8]:[>30]]) -> 0 | Q224: =+Cartera[[#This Row],[9_a_15]]+Cartera[[#This Row],[16_a_22]]+Cartera[[#This Row],[23_a_30]] -> 0 | R224: =IF(Cartera[[#This Row],[Dias]]>8,Cartera[[#This Row],[Total vencido]],0) -> 0 | S224: =IF(Cartera[[#This Row],[Mas de 9]]>0,Cartera[[#This Row],[Dias]],0) -> 0 | T224: =IF(Cartera[[#This Row],[Dias]]>99,Cartera[[#This Row],[Total vencido]],0) -> 0 | U224: =IF(Cartera[[#This Row],[Mas de 100]]>0,Cartera[[#This Row],[Dias]],0) -> 0 | V224: =Cartera[[#This Row],[Vencimiento]]-Cartera[[#This Row],[Emision]] -> 29.999375 | W224: =+IF(Cartera[[#This Row],[Tipo]]=151,"Lom",IF(Cartera[[#This Row],[Tipo]]=153,"Lom",IF(Cartera[[#This Row],[Tipo]]=155,"Lom",IF(Cartera[[#This Row],[Tipo]]=200,"Lom",IF(Cartera[[#This Row],[Tipo]]=224,"Lom",IF(Cartera[[#This Row],[Tipo]]=251,"Lom",IF(Cartera[[#This Row],[Tipo]]=651,"Magra",IF(Cartera[[#This Row],[Tipo]]=655,"Magra",IF(Cartera[[#This Row],[Tipo]]=601,"Magra",IF(Cartera[[#This Row],[Tipo]]=751,"Galan",IF(Cartera[[#This Row],[Tipo]]=757,"Galan",IF(Cartera[[#This Row],[Tipo]]=701,"Galan",IF(Cartera[[#This Row],[Tipo]]=755,"Galan",IF(Cartera[[#This Row],[Tipo]]="CO","Conciliacion Cartera","")))))))))))))) | X224: =_xlfn.XLOOKUP(Cartera[[#This Row],[Nombre tercero]],Vendedor[Nombre],Vendedor[Vendedor],"",0,-1) -> WILLIAM DARIO PADILLA
A225: =+A224 -> BACO FOODS COLOMBIA S.A.S | B225: 751 | C225: 18791 | D225: 8 | E225: 46013.504 | F225: 46043.504 | G225: -7 | H225: 579600 | I225: 579600 | J225: 579600 | K225: 0 | L225: 0 | M225: 0 | N225: 0 | O225: 0 | P225: =SUM(Cartera[[#This Row],[1_a_8]:[>30]]) -> 0 | Q225: =+Cartera[[#This Row],[9_a_15]]+Cartera[[#This Row],[16_a_22]]+Cartera[[#This Row],[23_a_30]] -> 0 | R225: =IF(Cartera[[#This Row],[Dias]]>8,Cartera[[#This Row],[Total vencido]],0) -> 0 | S225: =IF(Cartera[[#This Row],[Mas de 9]]>0,Cartera[[#This Row],[Dias]],0) -> 0 | T225: =IF(Cartera[[#This Row],[Dias]]>99,Cartera[[#This Row],[Total vencido]],0) -> 0 | U225: =IF(Cartera[[#This Row],[Mas de 100]]>0,Cartera[[#This Row],[Dias]],0) -> 0 | V225: =Cartera[[#This Row],[Vencimiento]]-Cartera[[#This Row],[Emision]] -> 29.999745 | W225: =+IF(Cartera[[#This Row],[Tipo]]=151,"Lom",IF(Cartera[[#This Row],[Tipo]]=153,"Lom",IF(Cartera[[#This Row],[Tipo]]=155,"Lom",IF(Cartera[[#This Row],[Tipo]]=200,"Lom",IF(Cartera[[#This Row],[Tipo]]=224,"Lom",IF(Cartera[[#This Row],[Tipo]]=251,"Lom",IF(Cartera[[#This Row],[Tipo]]=651,"Magra",IF(Cartera[[#This Row],[Tipo]]=655,"Magra",IF(Cartera[[#This Row],[Tipo]]=601,"Magra",IF(Cartera[[#This Row],[Tipo]]=751,"Galan",IF(Cartera[[#This Row],[Tipo]]=757,"Galan",IF(Cartera[[#This Row],[Tipo]]=701,"Galan",IF(Cartera[[#This Row],[Tipo]]=755,"Galan",IF(Cartera[[#This Row],[Tipo]]="CO","Conciliacion Cartera","")))))))))))))) | X225: =_xlfn.XLOOKUP(Cartera[[#This Row],[Nombre tercero]],Vendedor[Nombre],Vendedor[Vendedor],"",0,-1) -> WILLIAM DARIO PADILLA
A226: =+A225 -> BACO FOODS COLOMBIA S.A.S | B226: 751 | C226: 18940 | D226: 8 | E226: 46018.5 | F226: 46048.5 | G226: -12 | H226: 2058600 | I226: 2058600 | J226: 2058600 | K226: 0 | L226: 0 | M226: 0 | N226: 0 | O226: 0 | P226: =SUM(Cartera[[#This Row],[1_a_8]:[>30]]) -> 0 | Q226: =+Cartera[[#This Row],[9_a_15]]+Cartera[[#This Row],[16_a_22]]+Cartera[[#This Row],[23_a_30]] -> 0 | R226: =IF(Cartera[[#This Row],[Dias]]>8,Cartera[[#This Row],[Total vencido]],0) -> 0 | S226: =IF(Cartera[[#This Row],[Mas de 9]]>0,Cartera[[#This Row],[Dias]],0) -> 0 | T226: =IF(Cartera[[#This Row],[Dias]]>99,Cartera[[#This Row],[Total vencido]],0) -> 0 | U226: =IF(Cartera[[#This Row],[Mas de 100]]>0,Cartera[[#This Row],[Dias]],0) -> 0 | V226: =Cartera[[#This Row],[Vencimiento]]-Cartera[[#This Row],[Emision]] -> 29.999687 | W226: =+IF(Cartera[[#This Row],[Tipo]]=151,"Lom",IF(Cartera[[#This Row],[Tipo]]=153,"Lom",IF(Cartera[[#This Row],[Tipo]]=155,"Lom",IF(Cartera[[#This Row],[Tipo]]=200,"Lom",IF(Cartera[[#This Row],[Tipo]]=224,"Lom",IF(Cartera[[#This Row],[Tipo]]=251,"Lom",IF(Cartera[[#This Row],[Tipo]]=651,"Magra",IF(Cartera[[#This Row],[Tipo]]=655,"Magra",IF(Cartera[[#This Row],[Tipo]]=601,"Magra",IF(Cartera[[#This Row],[Tipo]]=751,"Galan",IF(Cartera[[#This Row],[Tipo]]=757,"Galan",IF(Cartera[[#This Row],[Tipo]]=701,"Galan",IF(Cartera[[#This Row],[Tipo]]=755,"Galan",IF(Cartera[[#This Row],[Tipo]]="CO","Conciliacion Cartera","")))))))))))))) | X226: =_xlfn.XLOOKUP(Cartera[[#This Row],[Nombre tercero]],Vendedor[Nombre],Vendedor[Vendedor],"",0,-1) -> WILLIAM DARIO PADILLA
A227: BASTIDAS MEDINA MARCELA | B227: 151 | C227: 23601 | D227: 11 | E227: 46015.37 | F227: 46023.368 | G227: 13 | H227: 333700 | I227: 333700 | J227: 0 | K227: 0 | L227: 333700 | M227: 0 | N227: 0 | O227: 0 | P227: =SUM(Cartera[[#This Row],[1_a_8]:[>30]]) -> 333700 | Q227: =+Cartera[[#This Row],[9_a_15]]+Cartera[[#This Row],[16_a_22]]+Cartera[[#This Row],[23_a_30]] -> 333700 | R227: =IF(Cartera[[#This Row],[Dias]]>8,Cartera[[#This Row],[Total vencido]],0) -> 333700 | S227: =IF(Cartera[[#This Row],[Mas de 9]]>0,Cartera[[#This Row],[Dias]],0) -> 13 | T227: =IF(Cartera[[#This Row],[Dias]]>99,Cartera[[#This Row],[Total vencido]],0) -> 0 | U227: =IF(Cartera[[#This Row],[Mas de 100]]>0,Cartera[[#This Row],[Dias]],0) -> 0 | V227: =Cartera[[#This Row],[Vencimiento]]-Cartera[[#This Row],[Emision]] -> 7.9982407 | W227: =+IF(Cartera[[#This Row],[Tipo]]=151,"Lom",IF(Cartera[[#This Row],[Tipo]]=153,"Lom",IF(Cartera[[#This Row],[Tipo]]=155,"Lom",IF(Cartera[[#This Row],[Tipo]]=200,"Lom",IF(Cartera[[#This Row],[Tipo]]=224,"Lom",IF(Cartera[[#This Row],[Tipo]]=251,"Lom",IF(Cartera[[#This Row],[Tipo]]=651,"Magra",IF(Cartera[[#This Row],[Tipo]]=655,"Magra",IF(Cartera[[#This Row],[Tipo]]=601,"Magra",IF(Cartera[[#This Row],[Tipo]]=751,"Galan",IF(Cartera[[#This Row],[Tipo]]=757,"Galan",IF(Cartera[[#This Row],[Tipo]]=701,"Galan",IF(Cartera[[#This Row],[Tipo]]=755,"Galan",IF(Cartera[[#This Row],[Tipo]]="CO","Conciliacion Cartera","")))))))))))))) | X227: =_xlfn.XLOOKUP(Cartera[[#This Row],[Nombre tercero]],Vendedor[Nombre],Vendedor[Vendedor],"",0,-1) -> ANGELA SILVESTRE
A228: =+A227 -> BASTIDAS MEDINA MARCELA | B228: 151 | C228: 23630 | D228: 11 | E228: 46017.318 | F228: 46025.318 | G228: 11 | H228: 145000 | I228: 145000 | J228: 0 | K228: 0 | L228: 145000 | M228: 0 | N228: 0 | O228: 0 | P228: =SUM(Cartera[[#This Row],[1_a_8]:[>30]]) -> 145000 | Q228: =+Cartera[[#This Row],[9_a_15]]+Cartera[[#This Row],[16_a_22]]+Cartera[[#This Row],[23_a_30]] -> 145000 | R228: =IF(Cartera[[#This Row],[Dias]]>8,Cartera[[#This Row],[Total vencido]],0) -> 145000 | S228: =IF(Cartera[[#This Row],[Mas de 9]]>0,Cartera[[#This Row],[Dias]],0) -> 11 | T228: =IF(Cartera[[#This Row],[Dias]]>99,Cartera[[#This Row],[Total vencido]],0) -> 0 | U228: =IF(Cartera[[#This Row],[Mas de 100]]>0,Cartera[[#This Row],[Dias]],0) -> 0 | V228: =Cartera[[#This Row],[Vencimiento]]-Cartera[[#This Row],[Emision]] -> 7.9998611 | W228: =+IF(Cartera[[#This Row],[Tipo]]=151,"Lom",IF(Cartera[[#This Row],[Tipo]]=153,"Lom",IF(Cartera[[#This Row],[Tipo]]=155,"Lom",IF(Cartera[[#This Row],[Tipo]]=200,"Lom",IF(Cartera[[#This Row],[Tipo]]=224,"Lom",IF(Cartera[[#This Row],[Tipo]]=251,"Lom",IF(Cartera[[#This Row],[Tipo]]=651,"Magra",IF(Cartera[[#This Row],[Tipo]]=655,"Magra",IF(Cartera[[#This Row],[Tipo]]=601,"Magra",IF(Cartera[[#This Row],[Tipo]]=751,"Galan",IF(Cartera[[#This Row],[Tipo]]=757,"Galan",IF(Cartera[[#This Row],[Tipo]]=701,"Galan",IF(Cartera[[#This Row],[Tipo]]=755,"Galan",IF(Cartera[[#This Row],[Tipo]]="CO","Conciliacion Cartera","")))))))))))))) | X228: =_xlfn.XLOOKUP(Cartera[[#This Row],[Nombre tercero]],Vendedor[Nombre],Vendedor[Vendedor],"",0,-1) -> ANGELA SILVESTRE
A229: =+A228 -> BASTIDAS MEDINA MARCELA | B229: 151 | C229: 23740 | D229: 11 | E229: 46021.455 | F229: 46029.455 | G229: 7 | H229: 169400 | I229: 169400 | J229: 0 | K229: 169400 | L229: 0 | M229: 0 | N229: 0 | O229: 0 | P229: =SUM(Cartera[[#This Row],[1_a_8]:[>30]]) -> 169400 | Q229: =+Cartera[[#This Row],[9_a_15]]+Cartera[[#This Row],[16_a_22]]+Cartera[[#This Row],[23_a_30]] -> 0 | R229: =IF(Cartera[[#This Row],[Dias]]>8,Cartera[[#This Row],[Total vencido]],0) -> 0 | S229: =IF(Cartera[[#This Row],[Mas de 9]]>0,Cartera[[#This Row],[Dias]],0) -> 0 | T229: =IF(Cartera[[#This Row],[Dias]]>99,Cartera[[#This Row],[Total vencido]],0) -> 0 | U229: =IF(Cartera[[#This Row],[Mas de 100]]>0,Cartera[[#This Row],[Dias]],0) -> 0 | V229: =Cartera[[#This Row],[Vencimiento]]-Cartera[[#This Row],[Emision]] -> 7.999838 | W229: =+IF(Cartera[[#This Row],[Tipo]]=151,"Lom",IF(Cartera[[#This Row],[Tipo]]=153,"Lom",IF(Cartera[[#This Row],[Tipo]]=155,"Lom",IF(Cartera[[#This Row],[Tipo]]=200,"Lom",IF(Cartera[[#This Row],[Tipo]]=224,"Lom",IF(Cartera[[#This Row],[Tipo]]=251,"Lom",IF(Cartera[[#This Row],[Tipo]]=651,"Magra",IF(Cartera[[#This Row],[Tipo]]=655,"Magra",IF(Cartera[[#This Row],[Tipo]]=601,"Magra",IF(Cartera[[#This Row],[Tipo]]=751,"Galan",IF(Cartera[[#This Row],[Tipo]]=757,"Galan",IF(Cartera[[#This Row],[Tipo]]=701,"Galan",IF(Cartera[[#This Row],[Tipo]]=755,"Galan",IF(Cartera[[#This Row],[Tipo]]="CO","Conciliacion Cartera","")))))))))))))) | X229: =_xlfn.XLOOKUP(Cartera[[#This Row],[Nombre tercero]],Vendedor[Nombre],Vendedor[Vendedor],"",0,-1) -> ANGELA SILVESTRE
A230: =+A229 -> BASTIDAS MEDINA MARCELA | B230: 151 | C230: 23748 | D230: 11 | E230: 46022.242 | F230: 46030.242 | G230: 6 | H230: 323100 | I230: 323100 | J230: 0 | K230: 323100 | L230: 0 | M230: 0 | N230: 0 | O230: 0 | P230: =SUM(Cartera[[#This Row],[1_a_8]:[>30]]) -> 323100 | Q230: =+Cartera[[#This Row],[9_a_15]]+Cartera[[#This Row],[16_a_22]]+Cartera[[#This Row],[23_a_30]] -> 0 | R230: =IF(Cartera[[#This Row],[Dias]]>8,Cartera[[#This Row],[Total vencido]],0) -> 0 | S230: =IF(Cartera[[#This Row],[Mas de 9]]>0,Cartera[[#This Row],[Dias]],0) -> 0 | T230: =IF(Cartera[[#This Row],[Dias]]>99,Cartera[[#This Row],[Total vencido]],0) -> 0 | U230: =IF(Cartera[[#This Row],[Mas de 100]]>0,Cartera[[#This Row],[Dias]],0) -> 0 | V230: =Cartera[[#This Row],[Vencimiento]]-Cartera[[#This Row],[Emision]] -> 7.9997222 | W230: =+IF(Cartera[[#This Row],[Tipo]]=151,"Lom",IF(Cartera[[#This Row],[Tipo]]=153,"Lom",IF(Cartera[[#This Row],[Tipo]]=155,"Lom",IF(Cartera[[#This Row],[Tipo]]=200,"Lom",IF(Cartera[[#This Row],[Tipo]]=224,"Lom",IF(Cartera[[#This Row],[Tipo]]=251,"Lom",IF(Cartera[[#This Row],[Tipo]]=651,"Magra",IF(Cartera[[#This Row],[Tipo]]=655,"Magra",IF(Cartera[[#This Row],[Tipo]]=601,"Magra",IF(Cartera[[#This Row],[Tipo]]=751,"Galan",IF(Cartera[[#This Row],[Tipo]]=757,"Galan",IF(Cartera[[#This Row],[Tipo]]=701,"Galan",IF(Cartera[[#This Row],[Tipo]]=755,"Galan",IF(Cartera[[#This Row],[Tipo]]="CO","Conciliacion Cartera","")))))))))))))) | X230: =_xlfn.XLOOKUP(Cartera[[#This Row],[Nombre tercero]],Vendedor[Nombre],Vendedor[Vendedor],"",0,-1) -> ANGELA SILVESTRE
A231: BISTROT S.A.S | B231: 151 | C231: 22170 | D231: 3 | E231: 45966.282 | F231: 45996.282 | G231: 40 | H231: 279500 | I231: 279500 | J231: 0 | K231: 0 | L231: 0 | M231: 0 | N231: 0 | O231: 279500 | P231: =SUM(Cartera[[#This Row],[1_a_8]:[>30]]) -> 279500 | Q231: =+Cartera[[#This Row],[9_a_15]]+Cartera[[#This Row],[16_a_22]]+Cartera[[#This Row],[23_a_30]] -> 0 | R231: =IF(Cartera[[#This Row],[Dias]]>8,Cartera[[#This Row],[Total vencido]],0) -> 279500 | S231: =IF(Cartera[[#This Row],[Mas de 9]]>0,Cartera[[#This Row],[Dias]],0) -> 40 | T231: =IF(Cartera[[#This Row],[Dias]]>99,Cartera[[#This Row],[Total vencido]],0) -> 0 | U231: =IF(Cartera[[#This Row],[Mas de 100]]>0,Cartera[[#This Row],[Dias]],0) -> 0 | V231: =Cartera[[#This Row],[Vencimiento]]-Cartera[[#This Row],[Emision]] -> 29.999873 | W231: =+IF(Cartera[[#This Row],[Tipo]]=151,"Lom",IF(Cartera[[#This Row],[Tipo]]=153,"Lom",IF(Cartera[[#This Row],[Tipo]]=155,"Lom",IF(Cartera[[#This Row],[Tipo]]=200,"Lom",IF(Cartera[[#This Row],[Tipo]]=224,"Lom",IF(Cartera[[#This Row],[Tipo]]=251,"Lom",IF(Cartera[[#This Row],[Tipo]]=651,"Magra",IF(Cartera[[#This Row],[Tipo]]=655,"Magra",IF(Cartera[[#This Row],[Tipo]]=601,"Magra",IF(Cartera[[#This Row],[Tipo]]=751,"Galan",IF(Cartera[[#This Row],[Tipo]]=757,"Galan",IF(Cartera[[#This Row],[Tipo]]=701,"Galan",IF(Cartera[[#This Row],[Tipo]]=755,"Galan",IF(Cartera[[#This Row],[Tipo]]="CO","Conciliacion Cartera","")))))))))))))) | X231: =_xlfn.XLOOKUP(Cartera[[#This Row],[Nombre tercero]],Vendedor[Nombre],Vendedor[Vendedor],"",0,-1) -> ANGELA SILVESTRE
A232: =+A231 -> BISTROT S.A.S | B232: 151 | C232: 22352 | D232: 3 | E232: 45974.301 | F232: 46004.3 | G232: 32 | H232: 541200 | I232: 541200 | J232: 0 | K232: 0 | L232: 0 | M232: 0 | N232: 0 | O232: 541200 | P232: =SUM(Cartera[[#This Row],[1_a_8]:[>30]]) -> 541200 | Q232: =+Cartera[[#This Row],[9_a_15]]+Cartera[[#This Row],[16_a_22]]+Cartera[[#This Row],[23_a_30]] -> 0 | R232: =IF(Cartera[[#This Row],[Dias]]>8,Cartera[[#This Row],[Total vencido]],0) -> 541200 | S232: =IF(Cartera[[#This Row],[Mas de 9]]>0,Cartera[[#This Row],[Dias]],0) -> 32 | T232: =IF(Cartera[[#This Row],[Dias]]>99,Cartera[[#This Row],[Total vencido]],0) -> 0 | U232: =IF(Cartera[[#This Row],[Mas de 100]]>0,Cartera[[#This Row],[Dias]],0) -> 0 | V232: =Cartera[[#This Row],[Vencimiento]]-Cartera[[#This Row],[Emision]] -> 29.999861 | W232: =+IF(Cartera[[#This Row],[Tipo]]=151,"Lom",IF(Cartera[[#This Row],[Tipo]]=153,"Lom",IF(Cartera[[#This Row],[Tipo]]=155,"Lom",IF(Cartera[[#This Row],[Tipo]]=200,"Lom",IF(Cartera[[#This Row],[Tipo]]=224,"Lom",IF(Cartera[[#This Row],[Tipo]]=251,"Lom",IF(Cartera[[#This Row],[Tipo]]=651,"Magra",IF(Cartera[[#This Row],[Tipo]]=655,"Magra",IF(Cartera[[#This Row],[Tipo]]=601,"Magra",IF(Cartera[[#This Row],[Tipo]]=751,"Galan",IF(Cartera[[#This Row],[Tipo]]=757,"Galan",IF(Cartera[[#This Row],[Tipo]]=701,"Galan",IF(Cartera[[#This Row],[Tipo]]=755,"Galan",IF(Cartera[[#This Row],[Tipo]]="CO","Conciliacion Cartera","")))))))))))))) | X232: =_xlfn.XLOOKUP(Cartera[[#This Row],[Nombre tercero]],Vendedor[Nombre],Vendedor[Vendedor],"",0,-1) -> ANGELA SILVESTRE
A233: =+A232 -> BISTROT S.A.S | B233: 151 | C233: 22531 | D233: 3 | E233: 45981.344 | F233: 46011.337 | G233: 25 | H233: 362900 | I233: 362900 | J233: 0 | K233: 0 | L233: 0 | M233: 0 | N233: 362900 | O233: 0 | P233: =SUM(Cartera[[#This Row],[1_a_8]:[>30]]) -> 362900 | Q233: =+Cartera[[#This Row],[9_a_15]]+Cartera[[#This Row],[16_a_22]]+Cartera[[#This Row],[23_a_30]] -> 362900 | R233: =IF(Cartera[[#This Row],[Dias]]>8,Cartera[[#This Row],[Total vencido]],0) -> 362900 | S233: =IF(Cartera[[#This Row],[Mas de 9]]>0,Cartera[[#This Row],[Dias]],0) -> 25 | T233: =IF(Cartera[[#This Row],[Dias]]>99,Cartera[[#This Row],[Total vencido]],0) -> 0 | U233: =IF(Cartera[[#This Row],[Mas de 100]]>0,Cartera[[#This Row],[Dias]],0) -> 0 | V233: =Cartera[[#This Row],[Vencimiento]]-Cartera[[#This Row],[Emision]] -> 29.992917 | W233: =+IF(Cartera[[#This Row],[Tipo]]=151,"Lom",IF(Cartera[[#This Row],[Tipo]]=153,"Lom",IF(Cartera[[#This Row],[Tipo]]=155,"Lom",IF(Cartera[[#This Row],[Tipo]]=200,"Lom",IF(Cartera[[#This Row],[Tipo]]=224,"Lom",IF(Cartera[[#This Row],[Tipo]]=251,"Lom",IF(Cartera[[#This Row],[Tipo]]=651,"Magra",IF(Cartera[[#This Row],[Tipo]]=655,"Magra",IF(Cartera[[#This Row],[Tipo]]=601,"Magra",IF(Cartera[[#This Row],[Tipo]]=751,"Galan",IF(Cartera[[#This Row],[Tipo]]=757,"Galan",IF(Cartera[[#This Row],[Tipo]]=701,"Galan",IF(Cartera[[#This Row],[Tipo]]=755,"Galan",IF(Cartera[[#This Row],[Tipo]]="CO","Conciliacion Cartera","")))))))))))))) | X233: =_xlfn.XLOOKUP(Cartera[[#This Row],[Nombre tercero]],Vendedor[Nombre],Vendedor[Vendedor],"",0,-1) -> ANGELA SILVESTRE
A234: =+A233 -> BISTROT S.A.S | B234: 151 | C234: 22896 | D234: 3 | E234: 45993.374 | F234: 46023.373 | G234: 13 | H234: 512000 | I234: 512000 | J234: 0 | K234: 0 | L234: 512000 | M234: 0 | N234: 0 | O234: 0 | P234: =SUM(Cartera[[#This Row],[1_a_8]:[>30]]) -> 512000 | Q234: =+Cartera[[#This Row],[9_a_15]]+Cartera[[#This Row],[16_a_22]]+Cartera[[#This Row],[23_a_30]] -> 512000 | R234: =IF(Cartera[[#This Row],[Dias]]>8,Cartera[[#This Row],[Total vencido]],0) -> 512000 | S234: =IF(Cartera[[#This Row],[Mas de 9]]>0,Cartera[[#This Row],[Dias]],0) -> 13 | T234: =IF(Cartera[[#This Row],[Dias]]>99,Cartera[[#This Row],[Total vencido]],0) -> 0 | U234: =IF(Cartera[[#This Row],[Mas de 100]]>0,Cartera[[#This Row],[Dias]],0) -> 0 | V234: =Cartera[[#This Row],[Vencimiento]]-Cartera[[#This Row],[Emision]] -> 29.999734 | W234: =+IF(Cartera[[#This Row],[Tipo]]=151,"Lom",IF(Cartera[[#This Row],[Tipo]]=153,"Lom",IF(Cartera[[#This Row],[Tipo]]=155,"Lom",IF(Cartera[[#This Row],[Tipo]]=200,"Lom",IF(Cartera[[#This Row],[Tipo]]=224,"Lom",IF(Cartera[[#This Row],[Tipo]]=251,"Lom",IF(Cartera[[#This Row],[Tipo]]=651,"Magra",IF(Cartera[[#This Row],[Tipo]]=655,"Magra",IF(Cartera[[#This Row],[Tipo]]=601,"Magra",IF(Cartera[[#This Row],[Tipo]]=751,"Galan",IF(Cartera[[#This Row],[Tipo]]=757,"Galan",IF(Cartera[[#This Row],[Tipo]]=701,"Galan",IF(Cartera[[#This Row],[Tipo]]=755,"Galan",IF(Cartera[[#This Row],[Tipo]]="CO","Conciliacion Cartera","")))))))))))))) | X234: =_xlfn.XLOOKUP(Cartera[[#This Row],[Nombre tercero]],Vendedor[Nombre],Vendedor[Vendedor],"",0,-1) -> ANGELA SILVESTRE
A235: =+A234 -> BISTROT S.A.S | B235: 151 | C235: 23040 | D235: 3 | E235: 45997.459 | F235: 46027.459 | G235: 9 | H235: 136300 | I235: 136300 | J235: 0 | K235: 0 | L235: 136300 | M235: 0 | N235: 0 | O235: 0 | P235: =SUM(Cartera[[#This Row],[1_a_8]:[>30]]) -> 136300 | Q235: =+Cartera[[#This Row],[9_a_15]]+Cartera[[#This Row],[16_a_22]]+Cartera[[#This Row],[23_a_30]] -> 136300 | R235: =IF(Cartera[[#This Row],[Dias]]>8,Cartera[[#This Row],[Total vencido]],0) -> 136300 | S235: =IF(Cartera[[#This Row],[Mas de 9]]>0,Cartera[[#This Row],[Dias]],0) -> 9 | T235: =IF(Cartera[[#This Row],[Dias]]>99,Cartera[[#This Row],[Total vencido]],0) -> 0 | U235: =IF(Cartera[[#This Row],[Mas de 100]]>0,Cartera[[#This Row],[Dias]],0) -> 0 | V235: =Cartera[[#This Row],[Vencimiento]]-Cartera[[#This Row],[Emision]] -> 29.999803 | W235: =+IF(Cartera[[#This Row],[Tipo]]=151,"Lom",IF(Cartera[[#This Row],[Tipo]]=153,"Lom",IF(Cartera[[#This Row],[Tipo]]=155,"Lom",IF(Cartera[[#This Row],[Tipo]]=200,"Lom",IF(Cartera[[#This Row],[Tipo]]=224,"Lom",IF(Cartera[[#This Row],[Tipo]]=251,"Lom",IF(Cartera[[#This Row],[Tipo]]=651,"Magra",IF(Cartera[[#This Row],[Tipo]]=655,"Magra",IF(Cartera[[#This Row],[Tipo]]=601,"Magra",IF(Cartera[[#This Row],[Tipo]]=751,"Galan",IF(Cartera[[#This Row],[Tipo]]=757,"Galan",IF(Cartera[[#This Row],[Tipo]]=701,"Galan",IF(Cartera[[#This Row],[Tipo]]=755,"Galan",IF(Cartera[[#This Row],[Tipo]]="CO","Conciliacion Cartera","")))))))))))))) | X235: =_xlfn.XLOOKUP(Cartera[[#This Row],[Nombre tercero]],Vendedor[Nombre],Vendedor[Vendedor],"",0,-1) -> ANGELA SILVESTRE
A236: =+A235 -> BISTROT S.A.S | B236: 151 | C236: 23091 | D236: 3 | E236: 46001.276 | F236: 46031.276 | G236: 5 | H236: 295900 | I236: 295900 | J236: 0 | K236: 295900 | L236: 0 | M236: 0 | N236: 0 | O236: 0 | P236: =SUM(Cartera[[#This Row],[1_a_8]:[>30]]) -> 295900 | Q236: =+Cartera[[#This Row],[9_a_15]]+Cartera[[#This Row],[16_a_22]]+Cartera[[#This Row],[23_a_30]] -> 0 | R236: =IF(Cartera[[#This Row],[Dias]]>8,Cartera[[#This Row],[Total vencido]],0) -> 0 | S236: =IF(Cartera[[#This Row],[Mas de 9]]>0,Cartera[[#This Row],[Dias]],0) -> 0 | T236: =IF(Cartera[[#This Row],[Dias]]>99,Cartera[[#This Row],[Total vencido]],0) -> 0 | U236: =IF(Cartera[[#This Row],[Mas de 100]]>0,Cartera[[#This Row],[Dias]],0) -> 0 | V236: =Cartera[[#This Row],[Vencimiento]]-Cartera[[#This Row],[Emision]] -> 29.999861 | W236: =+IF(Cartera[[#This Row],[Tipo]]=151,"Lom",IF(Cartera[[#This Row],[Tipo]]=153,"Lom",IF(Cartera[[#This Row],[Tipo]]=155,"Lom",IF(Cartera[[#This Row],[Tipo]]=200,"Lom",IF(Cartera[[#This Row],[Tipo]]=224,"Lom",IF(Cartera[[#This Row],[Tipo]]=251,"Lom",IF(Cartera[[#This Row],[Tipo]]=651,"Magra",IF(Cartera[[#This Row],[Tipo]]=655,"Magra",IF(Cartera[[#This Row],[Tipo]]=601,"Magra",IF(Cartera[[#This Row],[Tipo]]=751,"Galan",IF(Cartera[[#This Row],[Tipo]]=757,"Galan",IF(Cartera[[#This Row],[Tipo]]=701,"Galan",IF(Cartera[[#This Row],[Tipo]]=755,"Galan",IF(Cartera[[#This Row],[Tipo]]="CO","Conciliacion Cartera","")))))))))))))) | X236: =_xlfn.XLOOKUP(Cartera[[#This Row],[Nombre tercero]],Vendedor[Nombre],Vendedor[Vendedor],"",0,-1) -> ANGELA SILVESTRE
A237: =+A236 -> BISTROT S.A.S | B237: 151 | C237: 23400 | D237: 3 | E237: 46010.363 | F237: 46040.363 | G237: -4 | H237: 449700 | I237: 449700 | J237: 449700 | K237: 0 | L237: 0 | M237: 0 | N237: 0 | O237: 0 | P237: =SUM(Cartera[[#This Row],[1_a_8]:[>30]]) -> 0 | Q237: =+Cartera[[#This Row],[9_a_15]]+Cartera[[#This Row],[16_a_22]]+Cartera[[#This Row],[23_a_30]] -> 0 | R237: =IF(Cartera[[#This Row],[Dias]]>8,Cartera[[#This Row],[Total vencido]],0) -> 0 | S237: =IF(Cartera[[#This Row],[Mas de 9]]>0,Cartera[[#This Row],[Dias]],0) -> 0 | T237: =IF(Cartera[[#This Row],[Dias]]>99,Cartera[[#This Row],[Total vencido]],0) -> 0 | U237: =IF(Cartera[[#This Row],[Mas de 100]]>0,Cartera[[#This Row],[Dias]],0) -> 0 | V237: =Cartera[[#This Row],[Vencimiento]]-Cartera[[#This Row],[Emision]] -> 29.999722 | W237: =+IF(Cartera[[#This Row],[Tipo]]=151,"Lom",IF(Cartera[[#This Row],[Tipo]]=153,"Lom",IF(Cartera[[#This Row],[Tipo]]=155,"Lom",IF(Cartera[[#This Row],[Tipo]]=200,"Lom",IF(Cartera[[#This Row],[Tipo]]=224,"Lom",IF(Cartera[[#This Row],[Tipo]]=251,"Lom",IF(Cartera[[#This Row],[Tipo]]=651,"Magra",IF(Cartera[[#This Row],[Tipo]]=655,"Magra",IF(Cartera[[#This Row],[Tipo]]=601,"Magra",IF(Cartera[[#This Row],[Tipo]]=751,"Galan",IF(Cartera[[#This Row],[Tipo]]=757,"Galan",IF(Cartera[[#This Row],[Tipo]]=701,"Galan",IF(Cartera[[#This Row],[Tipo]]=755,"Galan",IF(Cartera[[#This Row],[Tipo]]="CO","Conciliacion Cartera","")))))))))))))) | X237: =_xlfn.XLOOKUP(Cartera[[#This Row],[Nombre tercero]],Vendedor[Nombre],Vendedor[Vendedor],"",0,-1) -> ANGELA SILVESTRE
A238: =+A237 -> BISTROT S.A.S | B238: 151 | C238: 23633 | D238: 3 | E238: 46017.321 | F238: 46047.32 | G238: -11 | H238: 633600 | I238: 633600 | J238: 633600 | K238: 0 | L238: 0 | M238: 0 | N238: 0 | O238: 0 | P238: =SUM(Cartera[[#This Row],[1_a_8]:[>30]]) -> 0 | Q238: =+Cartera[[#This Row],[9_a_15]]+Cartera[[#This Row],[16_a_22]]+Cartera[[#This Row],[23_a_30]] -> 0 | R238: =IF(Cartera[[#This Row],[Dias]]>8,Cartera[[#This Row],[Total vencido]],0) -> 0 | S238: =IF(Cartera[[#This Row],[Mas de 9]]>0,Cartera[[#This Row],[Dias]],0) -> 0 | T238: =IF(Cartera[[#This Row],[Dias]]>99,Cartera[[#This Row],[Total vencido]],0) -> 0 | U238: =IF(Cartera[[#This Row],[Mas de 100]]>0,Cartera[[#This Row],[Dias]],0) -> 0 | V238: =Cartera[[#This Row],[Vencimiento]]-Cartera[[#This Row],[Emision]] -> 29.99978 | W238: =+IF(Cartera[[#This Row],[Tipo]]=151,"Lom",IF(Cartera[[#This Row],[Tipo]]=153,"Lom",IF(Cartera[[#This Row],[Tipo]]=155,"Lom",IF(Cartera[[#This Row],[Tipo]]=200,"Lom",IF(Cartera[[#This Row],[Tipo]]=224,"Lom",IF(Cartera[[#This Row],[Tipo]]=251,"Lom",IF(Cartera[[#This Row],[Tipo]]=651,"Magra",IF(Cartera[[#This Row],[Tipo]]=655,"Magra",IF(Cartera[[#This Row],[Tipo]]=601,"Magra",IF(Cartera[[#This Row],[Tipo]]=751,"Galan",IF(Cartera[[#This Row],[Tipo]]=757,"Galan",IF(Cartera[[#This Row],[Tipo]]=701,"Galan",IF(Cartera[[#This Row],[Tipo]]=755,"Galan",IF(Cartera[[#This Row],[Tipo]]="CO","Conciliacion Cartera","")))))))))))))) | X238: =_xlfn.XLOOKUP(Cartera[[#This Row],[Nombre tercero]],Vendedor[Nombre],Vendedor[Vendedor],"",0,-1) -> ANGELA SILVESTRE
A239: CAJA COLOMBIANA DE SUBSIDIO FAMILIAR COLSUBSIDIO | B239: 151 | C239: 22792 | D239: 3 | E239: 45990.517 | F239: 46020.517 | G239: 16 | H239: 191000 | I239: 191000 | J239: 0 | K239: 0 | L239: 0 | M239: 191000 | N239: 0 | O239: 0 | P239: =SUM(Cartera[[#This Row],[1_a_8]:[>30]]) -> 191000 | Q239: =+Cartera[[#This Row],[9_a_15]]+Cartera[[#This Row],[16_a_22]]+Cartera[[#This Row],[23_a_30]] -> 191000 | R239: =IF(Cartera[[#This Row],[Dias]]>8,Cartera[[#This Row],[Total vencido]],0) -> 191000 | S239: =IF(Cartera[[#This Row],[Mas de 9]]>0,Cartera[[#This Row],[Dias]],0) -> 16 | T239: =IF(Cartera[[#This Row],[Dias]]>99,Cartera[[#This Row],[Total vencido]],0) -> 0 | U239: =IF(Cartera[[#This Row],[Mas de 100]]>0,Cartera[[#This Row],[Dias]],0) -> 0 | V239: =Cartera[[#This Row],[Vencimiento]]-Cartera[[#This Row],[Emision]] -> 30 | W239: =+IF(Cartera[[#This Row],[Tipo]]=151,"Lom",IF(Cartera[[#This Row],[Tipo]]=153,"Lom",IF(Cartera[[#This Row],[Tipo]]=155,"Lom",IF(Cartera[[#This Row],[Tipo]]=200,"Lom",IF(Cartera[[#This Row],[Tipo]]=224,"Lom",IF(Cartera[[#This Row],[Tipo]]=251,"Lom",IF(Cartera[[#This Row],[Tipo]]=651,"Magra",IF(Cartera[[#This Row],[Tipo]]=655,"Magra",IF(Cartera[[#This Row],[Tipo]]=601,"Magra",IF(Cartera[[#This Row],[Tipo]]=751,"Galan",IF(Cartera[[#This Row],[Tipo]]=757,"Galan",IF(Cartera[[#This Row],[Tipo]]=701,"Galan",IF(Cartera[[#This Row],[Tipo]]=755,"Galan",IF(Cartera[[#This Row],[Tipo]]="CO","Conciliacion Cartera","")))))))))))))) | X239: =_xlfn.XLOOKUP(Cartera[[#This Row],[Nombre tercero]],Vendedor[Nombre],Vendedor[Vendedor],"",0,-1) -> ANGELA SILVESTRE
A240: =+A239 -> CAJA COLOMBIANA DE SUBSIDIO FAMILIAR COLSUBSIDIO | B240: 151 | C240: 22793 | D240: 3 | E240: 45990.528 | F240: 46020.528 | G240: 16 | H240: 357840 | I240: 357840 | J240: 0 | K240: 0 | L240: 0 | M240: 357840 | N240: 0 | O240: 0 | P240: =SUM(Cartera[[#This Row],[1_a_8]:[>30]]) -> 357840 | Q240: =+Cartera[[#This Row],[9_a_15]]+Cartera[[#This Row],[16_a_22]]+Cartera[[#This Row],[23_a_30]] -> 357840 | R240: =IF(Cartera[[#This Row],[Dias]]>8,Cartera[[#This Row],[Total vencido]],0) -> 357840 | S240: =IF(Cartera[[#This Row],[Mas de 9]]>0,Cartera[[#This Row],[Dias]],0) -> 16 | T240: =IF(Cartera[[#This Row],[Dias]]>99,Cartera[[#This Row],[Total vencido]],0) -> 0 | U240: =IF(Cartera[[#This Row],[Mas de 100]]>0,Cartera[[#This Row],[Dias]],0) -> 0 | V240: =Cartera[[#This Row],[Vencimiento]]-Cartera[[#This Row],[Emision]] -> 30 | W240: =+IF(Cartera[[#This Row],[Tipo]]=151,"Lom",IF(Cartera[[#This Row],[Tipo]]=153,"Lom",IF(Cartera[[#This Row],[Tipo]]=155,"Lom",IF(Cartera[[#This Row],[Tipo]]=200,"Lom",IF(Cartera[[#This Row],[Tipo]]=224,"Lom",IF(Cartera[[#This Row],[Tipo]]=251,"Lom",IF(Cartera[[#This Row],[Tipo]]=651,"Magra",IF(Cartera[[#This Row],[Tipo]]=655,"Magra",IF(Cartera[[#This Row],[Tipo]]=601,"Magra",IF(Cartera[[#This Row],[Tipo]]=751,"Galan",IF(Cartera[[#This Row],[Tipo]]=757,"Galan",IF(Cartera[[#This Row],[Tipo]]=701,"Galan",IF(Cartera[[#This Row],[Tipo]]=755,"Galan",IF(Cartera[[#This Row],[Tipo]]="CO","Conciliacion Cartera","")))))))))))))) | X240: =_xlfn.XLOOKUP(Cartera[[#This Row],[Nombre tercero]],Vendedor[Nombre],Vendedor[Vendedor],"",0,-1) -> ANGELA SILVESTRE
A241: =+A240 -> CAJA COLOMBIANA DE SUBSIDIO FAMILIAR COLSUBSIDIO | B241: 151 | C241: 22794 | D241: 3 | E241: 45990.529 | F241: 46020.529 | G241: 16 | H241: 2108850 | I241: 2108850 | J241: 0 | K241: 0 | L241: 0 | M241: 2108850 | N241: 0 | O241: 0 | P241: =SUM(Cartera[[#This Row],[1_a_8]:[>30]]) -> 2108850 | Q241: =+Cartera[[#This Row],[9_a_15]]+Cartera[[#This Row],[16_a_22]]+Cartera[[#This Row],[23_a_30]] -> 2108850 | R241: =IF(Cartera[[#This Row],[Dias]]>8,Cartera[[#This Row],[Total vencido]],0) -> 2108850 | S241: =IF(Cartera[[#This Row],[Mas de 9]]>0,Cartera[[#This Row],[Dias]],0) -> 16 | T241: =IF(Cartera[[#This Row],[Dias]]>99,Cartera[[#This Row],[Total vencido]],0) -> 0 | U241: =IF(Cartera[[#This Row],[Mas de 100]]>0,Cartera[[#This Row],[Dias]],0) -> 0 | V241: =Cartera[[#This Row],[Vencimiento]]-Cartera[[#This Row],[Emision]] -> 29.999884 | W241: =+IF(Cartera[[#This Row],[Tipo]]=151,"Lom",IF(Cartera[[#This Row],[Tipo]]=153,"Lom",IF(Cartera[[#This Row],[Tipo]]=155,"Lom",IF(Cartera[[#This Row],[Tipo]]=200,"Lom",IF(Cartera[[#This Row],[Tipo]]=224,"Lom",IF(Cartera[[#This Row],[Tipo]]=251,"Lom",IF(Cartera[[#This Row],[Tipo]]=651,"Magra",IF(Cartera[[#This Row],[Tipo]]=655,"Magra",IF(Cartera[[#This Row],[Tipo]]=601,"Magra",IF(Cartera[[#This Row],[Tipo]]=751,"Galan",IF(Cartera[[#This Row],[Tipo]]=757,"Galan",IF(Cartera[[#This Row],[Tipo]]=701,"Galan",IF(Cartera[[#This Row],[Tipo]]=755,"Galan",IF(Cartera[[#This Row],[Tipo]]="CO","Conciliacion Cartera","")))))))))))))) | X241: =_xlfn.XLOOKUP(Cartera[[#This Row],[Nombre tercero]],Vendedor[Nombre],Vendedor[Vendedor],"",0,-1) -> ANGELA SILVESTRE
A242: =+A241 -> CAJA COLOMBIANA DE SUBSIDIO FAMILIAR COLSUBSIDIO | B242: 151 | C242: 22796 | D242: 3 | E242: 45990.532 | F242: 46020.532 | G242: 16 | H242: 2402400 | I242: 2402400 | J242: 0 | K242: 0 | L242: 0 | M242: 2402400 | N242: 0 | O242: 0 | P242: =SUM(Cartera[[#This Row],[1_a_8]:[>30]]) -> 2402400 | Q242: =+Cartera[[#This Row],[9_a_15]]+Cartera[[#This Row],[16_a_22]]+Cartera[[#This Row],[23_a_30]] -> 2402400 | R242: =IF(Cartera[[#This Row],[Dias]]>8,Cartera[[#This Row],[Total vencido]],0) -> 2402400 | S242: =IF(Cartera[[#This Row],[Mas de 9]]>0,Cartera[[#This Row],[Dias]],0) -> 16 | T242: =IF(Cartera[[#This Row],[Dias]]>99,Cartera[[#This Row],[Total vencido]],0) -> 0 | U242: =IF(Cartera[[#This Row],[Mas de 100]]>0,Cartera[[#This Row],[Dias]],0) -> 0 | V242: =Cartera[[#This Row],[Vencimiento]]-Cartera[[#This Row],[Emision]] -> 29.999525 | W242: =+IF(Cartera[[#This Row],[Tipo]]=151,"Lom",IF(Cartera[[#This Row],[Tipo]]=153,"Lom",IF(Cartera[[#This Row],[Tipo]]=155,"Lom",IF(Cartera[[#This Row],[Tipo]]=200,"Lom",IF(Cartera[[#This Row],[Tipo]]=224,"Lom",IF(Cartera[[#This Row],[Tipo]]=251,"Lom",IF(Cartera[[#This Row],[Tipo]]=651,"Magra",IF(Cartera[[#This Row],[Tipo]]=655,"Magra",IF(Cartera[[#This Row],[Tipo]]=601,"Magra",IF(Cartera[[#This Row],[Tipo]]=751,"Galan",IF(Cartera[[#This Row],[Tipo]]=757,"Galan",IF(Cartera[[#This Row],[Tipo]]=701,"Galan",IF(Cartera[[#This Row],[Tipo]]=755,"Galan",IF(Cartera[[#This Row],[Tipo]]="CO","Conciliacion Cartera","")))))))))))))) | X242: =_xlfn.XLOOKUP(Cartera[[#This Row],[Nombre tercero]],Vendedor[Nombre],Vendedor[Vendedor],"",0,-1) -> ANGELA SILVESTRE
A243: =+A242 -> CAJA COLOMBIANA DE SUBSIDIO FAMILIAR COLSUBSIDIO | B243: 151 | C243: 22797 | D243: 3 | E243: 45990.533 | F243: 46020.533 | G243: 16 | H243: 303600 | I243: 303600 | J243: 0 | K243: 0 | L243: 0 | M243: 303600 | N243: 0 | O243: 0 | P243: =SUM(Cartera[[#This Row],[1_a_8]:[>30]]) -> 303600 | Q243: =+Cartera[[#This Row],[9_a_15]]+Cartera[[#This Row],[16_a_22]]+Cartera[[#This Row],[23_a_30]] -> 303600 | R243: =IF(Cartera[[#This Row],[Dias]]>8,Cartera[[#This Row],[Total vencido]],0) -> 303600 | S243: =IF(Cartera[[#This Row],[Mas de 9]]>0,Cartera[[#This Row],[Dias]],0) -> 16 | T243: =IF(Cartera[[#This Row],[Dias]]>99,Cartera[[#This Row],[Total vencido]],0) -> 0 | U243: =IF(Cartera[[#This Row],[Mas de 100]]>0,Cartera[[#This Row],[Dias]],0) -> 0 | V243: =Cartera[[#This Row],[Vencimiento]]-Cartera[[#This Row],[Emision]] -> 29.99978 | W243: =+IF(Cartera[[#This Row],[Tipo]]=151,"Lom",IF(Cartera[[#This Row],[Tipo]]=153,"Lom",IF(Cartera[[#This Row],[Tipo]]=155,"Lom",IF(Cartera[[#This Row],[Tipo]]=200,"Lom",IF(Cartera[[#This Row],[Tipo]]=224,"Lom",IF(Cartera[[#This Row],[Tipo]]=251,"Lom",IF(Cartera[[#This Row],[Tipo]]=651,"Magra",IF(Cartera[[#This Row],[Tipo]]=655,"Magra",IF(Cartera[[#This Row],[Tipo]]=601,"Magra",IF(Cartera[[#This Row],[Tipo]]=751,"Galan",IF(Cartera[[#This Row],[Tipo]]=757,"Galan",IF(Cartera[[#This Row],[Tipo]]=701,"Galan",IF(Cartera[[#This Row],[Tipo]]=755,"Galan",IF(Cartera[[#This Row],[Tipo]]="CO","Conciliacion Cartera","")))))))))))))) | X243: =_xlfn.XLOOKUP(Cartera[[#This Row],[Nombre tercero]],Vendedor[Nombre],Vendedor[Vendedor],"",0,-1) -> ANGELA SILVESTRE
A244: =+A243 -> CAJA COLOMBIANA DE SUBSIDIO FAMILIAR COLSUBSIDIO | B244: 151 | C244: 22798 | D244: 3 | E244: 45990.534 | F244: 46020.533 | G244: 16 | H244: 231000 | I244: 231000 | J244: 0 | K244: 0 | L244: 0 | M244: 231000 | N244: 0 | O244: 0 | P244: =SUM(Cartera[[#This Row],[1_a_8]:[>30]]) -> 231000 | Q244: =+Cartera[[#This Row],[9_a_15]]+Cartera[[#This Row],[16_a_22]]+Cartera[[#This Row],[23_a_30]] -> 231000 | R244: =IF(Cartera[[#This Row],[Dias]]>8,Cartera[[#This Row],[Total vencido]],0) -> 231000 | S244: =IF(Cartera[[#This Row],[Mas de 9]]>0,Cartera[[#This Row],[Dias]],0) -> 16 | T244: =IF(Cartera[[#This Row],[Dias]]>99,Cartera[[#This Row],[Total vencido]],0) -> 0 | U244: =IF(Cartera[[#This Row],[Mas de 100]]>0,Cartera[[#This Row],[Dias]],0) -> 0 | V244: =Cartera[[#This Row],[Vencimiento]]-Cartera[[#This Row],[Emision]] -> 29.999711 | W244: =+IF(Cartera[[#This Row],[Tipo]]=151,"Lom",IF(Cartera[[#This Row],[Tipo]]=153,"Lom",IF(Cartera[[#This Row],[Tipo]]=155,"Lom",IF(Cartera[[#This Row],[Tipo]]=200,"Lom",IF(Cartera[[#This Row],[Tipo]]=224,"Lom",IF(Cartera[[#This Row],[Tipo]]=251,"Lom",IF(Cartera[[#This Row],[Tipo]]=651,"Magra",IF(Cartera[[#This Row],[Tipo]]=655,"Magra",IF(Cartera[[#This Row],[Tipo]]=601,"Magra",IF(Cartera[[#This Row],[Tipo]]=751,"Galan",IF(Cartera[[#This Row],[Tipo]]=757,"Galan",IF(Cartera[[#This Row],[Tipo]]=701,"Galan",IF(Cartera[[#This Row],[Tipo]]=755,"Galan",IF(Cartera[[#This Row],[Tipo]]="CO","Conciliacion Cartera","")))))))))))))) | X244: =_xlfn.XLOOKUP(Cartera[[#This Row],[Nombre tercero]],Vendedor[Nombre],Vendedor[Vendedor],"",0,-1) -> ANGELA SILVESTRE
A245: =+A244 -> CAJA COLOMBIANA DE SUBSIDIO FAMILIAR COLSUBSIDIO | B245: 151 | C245: 22799 | D245: 3 | E245: 45990.534 | F245: 46020.534 | G245: 16 | H245: 987550 | I245: 987550 | J245: 0 | K245: 0 | L245: 0 | M245: 987550 | N245: 0 | O245: 0 | P245: =SUM(Cartera[[#This Row],[1_a_8]:[>30]]) -> 987550 | Q245: =+Cartera[[#This Row],[9_a_15]]+Cartera[[#This Row],[16_a_22]]+Cartera[[#This Row],[23_a_30]] -> 987550 | R245: =IF(Cartera[[#This Row],[Dias]]>8,Cartera[[#This Row],[Total vencido]],0) -> 987550 | S245: =IF(Cartera[[#This Row],[Mas de 9]]>0,Cartera[[#This Row],[Dias]],0) -> 16 | T245: =IF(Cartera[[#This Row],[Dias]]>99,Cartera[[#This Row],[Total vencido]],0) -> 0 | U245: =IF(Cartera[[#This Row],[Mas de 100]]>0,Cartera[[#This Row],[Dias]],0) -> 0 | V245: =Cartera[[#This Row],[Vencimiento]]-Cartera[[#This Row],[Emision]] -> 29.999745 | W245: =+IF(Cartera[[#This Row],[Tipo]]=151,"Lom",IF(Cartera[[#This Row],[Tipo]]=153,"Lom",IF(Cartera[[#This Row],[Tipo]]=155,"Lom",IF(Cartera[[#This Row],[Tipo]]=200,"Lom",IF(Cartera[[#This Row],[Tipo]]=224,"Lom",IF(Cartera[[#This Row],[Tipo]]=251,"Lom",IF(Cartera[[#This Row],[Tipo]]=651,"Magra",IF(Cartera[[#This Row],[Tipo]]=655,"Magra",IF(Cartera[[#This Row],[Tipo]]=601,"Magra",IF(Cartera[[#This Row],[Tipo]]=751,"Galan",IF(Cartera[[#This Row],[Tipo]]=757,"Galan",IF(Cartera[[#This Row],[Tipo]]=701,"Galan",IF(Cartera[[#This Row],[Tipo]]=755,"Galan",IF(Cartera[[#This Row],[Tipo]]="CO","Conciliacion Cartera","")))))))))))))) | X245: =_xlfn.XLOOKUP(Cartera[[#This Row],[Nombre tercero]],Vendedor[Nombre],Vendedor[Vendedor],"",0,-1) -> ANGELA SILVESTRE
A246: =+A245 -> CAJA COLOMBIANA DE SUBSIDIO FAMILIAR COLSUBSIDIO | B246: 151 | C246: 22800 | D246: 3 | E246: 45990.535 | F246: 46020.535 | G246: 16 | H246: 1417700 | I246: 1417700 | J246: 0 | K246: 0 | L246: 0 | M246: 1417700 | N246: 0 | O246: 0 | P246: =SUM(Cartera[[#This Row],[1_a_8]:[>30]]) -> 1417700 | Q246: =+Cartera[[#This Row],[9_a_15]]+Cartera[[#This Row],[16_a_22]]+Cartera[[#This Row],[23_a_30]] -> 1417700 | R246: =IF(Cartera[[#This Row],[Dias]]>8,Cartera[[#This Row],[Total vencido]],0) -> 1417700 | S246: =IF(Cartera[[#This Row],[Mas de 9]]>0,Cartera[[#This Row],[Dias]],0) -> 16 | T246: =IF(Cartera[[#This Row],[Dias]]>99,Cartera[[#This Row],[Total vencido]],0) -> 0 | U246: =IF(Cartera[[#This Row],[Mas de 100]]>0,Cartera[[#This Row],[Dias]],0) -> 0 | V246: =Cartera[[#This Row],[Vencimiento]]-Cartera[[#This Row],[Emision]] -> 29.999664 | W246: =+IF(Cartera[[#This Row],[Tipo]]=151,"Lom",IF(Cartera[[#This Row],[Tipo]]=153,"Lom",IF(Cartera[[#This Row],[Tipo]]=155,"Lom",IF(Cartera[[#This Row],[Tipo]]=200,"Lom",IF(Cartera[[#This Row],[Tipo]]=224,"Lom",IF(Cartera[[#This Row],[Tipo]]=251,"Lom",IF(Cartera[[#This Row],[Tipo]]=651,"Magra",IF(Cartera[[#This Row],[Tipo]]=655,"Magra",IF(Cartera[[#This Row],[Tipo]]=601,"Magra",IF(Cartera[[#This Row],[Tipo]]=751,"Galan",IF(Cartera[[#This Row],[Tipo]]=757,"Galan",IF(Cartera[[#This Row],[Tipo]]=701,"Galan",IF(Cartera[[#This Row],[Tipo]]=755,"Galan",IF(Cartera[[#This Row],[Tipo]]="CO","Conciliacion Cartera","")))))))))))))) | X246: =_xlfn.XLOOKUP(Cartera[[#This Row],[Nombre tercero]],Vendedor[Nombre],Vendedor[Vendedor],"",0,-1) -> ANGELA SILVESTRE
A247: =+A246 -> CAJA COLOMBIANA DE SUBSIDIO FAMILIAR COLSUBSIDIO | B247: 151 | C247: 22801 | D247: 3 | E247: 45990.536 | F247: 46020.536 | G247: 16 | H247: 447000 | I247: 447000 | J247: 0 | K247: 0 | L247: 0 | M247: 447000 | N247: 0 | O247: 0 | P247: =SUM(Cartera[[#This Row],[1_a_8]:[>30]]) -> 447000 | Q247: =+Cartera[[#This Row],[9_a_15]]+Cartera[[#This Row],[16_a_22]]+Cartera[[#This Row],[23_a_30]] -> 447000 | R247: =IF(Cartera[[#This Row],[Dias]]>8,Cartera[[#This Row],[Total vencido]],0) -> 447000 | S247: =IF(Cartera[[#This Row],[Mas de 9]]>0,Cartera[[#This Row],[Dias]],0) -> 16 | T247: =IF(Cartera[[#This Row],[Dias]]>99,Cartera[[#This Row],[Total vencido]],0) -> 0 | U247: =IF(Cartera[[#This Row],[Mas de 100]]>0,Cartera[[#This Row],[Dias]],0) -> 0 | V247: =Cartera[[#This Row],[Vencimiento]]-Cartera[[#This Row],[Emision]] -> 29.999699 | W247: =+IF(Cartera[[#This Row],[Tipo]]=151,"Lom",IF(Cartera[[#This Row],[Tipo]]=153,"Lom",IF(Cartera[[#This Row],[Tipo]]=155,"Lom",IF(Cartera[[#This Row],[Tipo]]=200,"Lom",IF(Cartera[[#This Row],[Tipo]]=224,"Lom",IF(Cartera[[#This Row],[Tipo]]=251,"Lom",IF(Cartera[[#This Row],[Tipo]]=651,"Magra",IF(Cartera[[#This Row],[Tipo]]=655,"Magra",IF(Cartera[[#This Row],[Tipo]]=601,"Magra",IF(Cartera[[#This Row],[Tipo]]=751,"Galan",IF(Cartera[[#This Row],[Tipo]]=757,"Galan",IF(Cartera[[#This Row],[Tipo]]=701,"Galan",IF(Cartera[[#This Row],[Tipo]]=755,"Galan",IF(Cartera[[#This Row],[Tipo]]="CO","Conciliacion Cartera","")))))))))))))) | X247: =_xlfn.XLOOKUP(Cartera[[#This Row],[Nombre tercero]],Vendedor[Nombre],Vendedor[Vendedor],"",0,-1) -> ANGELA SILVESTRE
A248: =+A247 -> CAJA COLOMBIANA DE SUBSIDIO FAMILIAR COLSUBSIDIO | B248: 151 | C248: 22802 | D248: 3 | E248: 45990.537 | F248: 46020.537 | G248: 16 | H248: 1113600 | I248: 1113600 | J248: 0 | K248: 0 | L248: 0 | M248: 1113600 | N248: 0 | O248: 0 | P248: =SUM(Cartera[[#This Row],[1_a_8]:[>30]]) -> 1113600 | Q248: =+Cartera[[#This Row],[9_a_15]]+Cartera[[#This Row],[16_a_22]]+Cartera[[#This Row],[23_a_30]] -> 1113600 | R248: =IF(Cartera[[#This Row],[Dias]]>8,Cartera[[#This Row],[Total vencido]],0) -> 1113600 | S248: =IF(Cartera[[#This Row],[Mas de 9]]>0,Cartera[[#This Row],[Dias]],0) -> 16 | T248: =IF(Cartera[[#This Row],[Dias]]>99,Cartera[[#This Row],[Total vencido]],0) -> 0 | U248: =IF(Cartera[[#This Row],[Mas de 100]]>0,Cartera[[#This Row],[Dias]],0) -> 0 | V248: =Cartera[[#This Row],[Vencimiento]]-Cartera[[#This Row],[Emision]] -> 29.999491 | W248: =+IF(Cartera[[#This Row],[Tipo]]=151,"Lom",IF(Cartera[[#This Row],[Tipo]]=153,"Lom",IF(Cartera[[#This Row],[Tipo]]=155,"Lom",IF(Cartera[[#This Row],[Tipo]]=200,"Lom",IF(Cartera[[#This Row],[Tipo]]=224,"Lom",IF(Cartera[[#This Row],[Tipo]]=251,"Lom",IF(Cartera[[#This Row],[Tipo]]=651,"Magra",IF(Cartera[[#This Row],[Tipo]]=655,"Magra",IF(Cartera[[#This Row],[Tipo]]=601,"Magra",IF(Cartera[[#This Row],[Tipo]]=751,"Galan",IF(Cartera[[#This Row],[Tipo]]=757,"Galan",IF(Cartera[[#This Row],[Tipo]]=701,"Galan",IF(Cartera[[#This Row],[Tipo]]=755,"Galan",IF(Cartera[[#This Row],[Tipo]]="CO","Conciliacion Cartera","")))))))))))))) | X248: =_xlfn.XLOOKUP(Cartera[[#This Row],[Nombre tercero]],Vendedor[Nombre],Vendedor[Vendedor],"",0,-1) -> ANGELA SILVESTRE
A249: =+A248 -> CAJA COLOMBIANA DE SUBSIDIO FAMILIAR COLSUBSIDIO | B249: 151 | C249: 22803 | D249: 3 | E249: 45990.538 | F249: 46020.538 | G249: 16 | H249: 462000 | I249: 462000 | J249: 0 | K249: 0 | L249: 0 | M249: 462000 | N249: 0 | O249: 0 | P249: =SUM(Cartera[[#This Row],[1_a_8]:[>30]]) -> 462000 | Q249: =+Cartera[[#This Row],[9_a_15]]+Cartera[[#This Row],[16_a_22]]+Cartera[[#This Row],[23_a_30]] -> 462000 | R249: =IF(Cartera[[#This Row],[Dias]]>8,Cartera[[#This Row],[Total vencido]],0) -> 462000 | S249: =IF(Cartera[[#This Row],[Mas de 9]]>0,Cartera[[#This Row],[Dias]],0) -> 16 | T249: =IF(Cartera[[#This Row],[Dias]]>99,Cartera[[#This Row],[Total vencido]],0) -> 0 | U249: =IF(Cartera[[#This Row],[Mas de 100]]>0,Cartera[[#This Row],[Dias]],0) -> 0 | V249: =Cartera[[#This Row],[Vencimiento]]-Cartera[[#This Row],[Emision]] -> 29.999826 | W249: =+IF(Cartera[[#This Row],[Tipo]]=151,"Lom",IF(Cartera[[#This Row],[Tipo]]=153,"Lom",IF(Cartera[[#This Row],[Tipo]]=155,"Lom",IF(Cartera[[#This Row],[Tipo]]=200,"Lom",IF(Cartera[[#This Row],[Tipo]]=224,"Lom",IF(Cartera[[#This Row],[Tipo]]=251,"Lom",IF(Cartera[[#This Row],[Tipo]]=651,"Magra",IF(Cartera[[#This Row],[Tipo]]=655,"Magra",IF(Cartera[[#This Row],[Tipo]]=601,"Magra",IF(Cartera[[#This Row],[Tipo]]=751,"Galan",IF(Cartera[[#This Row],[Tipo]]=757,"Galan",IF(Cartera[[#This Row],[Tipo]]=701,"Galan",IF(Cartera[[#This Row],[Tipo]]=755,"Galan",IF(Cartera[[#This Row],[Tipo]]="CO","Conciliacion Cartera","")))))))))))))) | X249: =_xlfn.XLOOKUP(Cartera[[#This Row],[Nombre tercero]],Vendedor[Nombre],Vendedor[Vendedor],"",0,-1) -> ANGELA SILVESTRE
A250: =+A249 -> CAJA COLOMBIANA DE SUBSIDIO FAMILIAR COLSUBSIDIO | B250: 151 | C250: 22806 | D250: 3 | E250: 45990.54 | F250: 46020.539 | G250: 16 | H250: 1755400 | I250: 1755400 | J250: 0 | K250: 0 | L250: 0 | M250: 1755400 | N250: 0 | O250: 0 | P250: =SUM(Cartera[[#This Row],[1_a_8]:[>30]]) -> 1755400 | Q250: =+Cartera[[#This Row],[9_a_15]]+Cartera[[#This Row],[16_a_22]]+Cartera[[#This Row],[23_a_30]] -> 1755400 | R250: =IF(Cartera[[#This Row],[Dias]]>8,Cartera[[#This Row],[Total vencido]],0) -> 1755400 | S250: =IF(Cartera[[#This Row],[Mas de 9]]>0,Cartera[[#This Row],[Dias]],0) -> 16 | T250: =IF(Cartera[[#This Row],[Dias]]>99,Cartera[[#This Row],[Total vencido]],0) -> 0 | U250: =IF(Cartera[[#This Row],[Mas de 100]]>0,Cartera[[#This Row],[Dias]],0) -> 0 | V250: =Cartera[[#This Row],[Vencimiento]]-Cartera[[#This Row],[Emision]] -> 29.998461 | W250: =+IF(Cartera[[#This Row],[Tipo]]=151,"Lom",IF(Cartera[[#This Row],[Tipo]]=153,"Lom",IF(Cartera[[#This Row],[Tipo]]=155,"Lom",IF(Cartera[[#This Row],[Tipo]]=200,"Lom",IF(Cartera[[#This Row],[Tipo]]=224,"Lom",IF(Cartera[[#This Row],[Tipo]]=251,"Lom",IF(Cartera[[#This Row],[Tipo]]=651,"Magra",IF(Cartera[[#This Row],[Tipo]]=655,"Magra",IF(Cartera[[#This Row],[Tipo]]=601,"Magra",IF(Cartera[[#This Row],[Tipo]]=751,"Galan",IF(Cartera[[#This Row],[Tipo]]=757,"Galan",IF(Cartera[[#This Row],[Tipo]]=701,"Galan",IF(Cartera[[#This Row],[Tipo]]=755,"Galan",IF(Cartera[[#This Row],[Tipo]]="CO","Conciliacion Cartera","")))))))))))))) | X250: =_xlfn.XLOOKUP(Cartera[[#This Row],[Nombre tercero]],Vendedor[Nombre],Vendedor[Vendedor],"",0,-1) -> ANGELA SILVESTRE
A251: =+A250 -> CAJA COLOMBIANA DE SUBSIDIO FAMILIAR COLSUBSIDIO | B251: 151 | C251: 22807 | D251: 3 | E251: 45990.541 | F251: 46020.541 | G251: 16 | H251: 21505750 | I251: 21505750 | J251: 0 | K251: 0 | L251: 0 | M251: 21505750 | N251: 0 | O251: 0 | P251: =SUM(Cartera[[#This Row],[1_a_8]:[>30]]) -> 21505750 | Q251: =+Cartera[[#This Row],[9_a_15]]+Cartera[[#This Row],[16_a_22]]+Cartera[[#This Row],[23_a_30]] -> 21505750 | R251: =IF(Cartera[[#This Row],[Dias]]>8,Cartera[[#This Row],[Total vencido]],0) -> 21505750 | S251: =IF(Cartera[[#This Row],[Mas de 9]]>0,Cartera[[#This Row],[Dias]],0) -> 16 | T251: =IF(Cartera[[#This Row],[Dias]]>99,Cartera[[#This Row],[Total vencido]],0) -> 0 | U251: =IF(Cartera[[#This Row],[Mas de 100]]>0,Cartera[[#This Row],[Dias]],0) -> 0 | V251: =Cartera[[#This Row],[Vencimiento]]-Cartera[[#This Row],[Emision]] -> 29.999803 | W251: =+IF(Cartera[[#This Row],[Tipo]]=151,"Lom",IF(Cartera[[#This Row],[Tipo]]=153,"Lom",IF(Cartera[[#This Row],[Tipo]]=155,"Lom",IF(Cartera[[#This Row],[Tipo]]=200,"Lom",IF(Cartera[[#This Row],[Tipo]]=224,"Lom",IF(Cartera[[#This Row],[Tipo]]=251,"Lom",IF(Cartera[[#This Row],[Tipo]]=651,"Magra",IF(Cartera[[#This Row],[Tipo]]=655,"Magra",IF(Cartera[[#This Row],[Tipo]]=601,"Magra",IF(Cartera[[#This Row],[Tipo]]=751,"Galan",IF(Cartera[[#This Row],[Tipo]]=757,"Galan",IF(Cartera[[#This Row],[Tipo]]=701,"Galan",IF(Cartera[[#This Row],[Tipo]]=755,"Galan",IF(Cartera[[#This Row],[Tipo]]="CO","Conciliacion Cartera","")))))))))))))) | X251: =_xlfn.XLOOKUP(Cartera[[#This Row],[Nombre tercero]],Vendedor[Nombre],Vendedor[Vendedor],"",0,-1) -> ANGELA SILVESTRE
... A378: =+A377 -> CAJA COLOMBIANA DE SUBSIDIO FAMILIAR COLSUBSIDIO | B378: 151 | C378: 23790 | D378: 3 | E378: 46022.512 | F378: 46052.512 | G378: -16 | H378: 448500 | I378: 448500 | J378: 448500 | K378: 0 | L378: 0 | M378: 0 | N378: 0 | O378: 0 | P378: =SUM(Cartera[[#This Row],[1_a_8]:[>30]]) -> 0 | Q378: =+Cartera[[#This Row],[9_a_15]]+Cartera[[#This Row],[16_a_22]]+Cartera[[#This Row],[23_a_30]] -> 0 | R378: =IF(Cartera[[#This Row],[Dias]]>8,Cartera[[#This Row],[Total vencido]],0) -> 0 | S378: =IF(Cartera[[#This Row],[Mas de 9]]>0,Cartera[[#This Row],[Dias]],0) -> 0 | T378: =IF(Cartera[[#This Row],[Dias]]>99,Cartera[[#This Row],[Total vencido]],0) -> 0 | U378: =IF(Cartera[[#This Row],[Mas de 100]]>0,Cartera[[#This Row],[Dias]],0) -> 0 | V378: =Cartera[[#This Row],[Vencimiento]]-Cartera[[#This Row],[Emision]] -> 30 | W378: =+IF(Cartera[[#This Row],[Tipo]]=151,"Lom",IF(Cartera[[#This Row],[Tipo]]=153,"Lom",IF(Cartera[[#This Row],[Tipo]]=155,"Lom",IF(Cartera[[#This Row],[Tipo]]=200,"Lom",IF(Cartera[[#This Row],[Tipo]]=224,"Lom",IF(Cartera[[#This Row],[Tipo]]=251,"Lom",IF(Cartera[[#This Row],[Tipo]]=651,"Magra",IF(Cartera[[#This Row],[Tipo]]=655,"Magra",IF(Cartera[[#This Row],[Tipo]]=601,"Magra",IF(Cartera[[#This Row],[Tipo]]=751,"Galan",IF(Cartera[[#This Row],[Tipo]]=757,"Galan",IF(Cartera[[#This Row],[Tipo]]=701,"Galan",IF(Cartera[[#This Row],[Tipo]]=755,"Galan",IF(Cartera[[#This Row],[Tipo]]="CO","Conciliacion Cartera","")))))))))))))) | X378: =_xlfn.XLOOKUP(Cartera[[#This Row],[Nombre tercero]],Vendedor[Nombre],Vendedor[Vendedor],"",0,-1) -> ANGELA SILVESTRE
A379: CANAL DIGITAL | B379: 155 | C379: 49507 | D379: 1 | E379: 45909.485 | F379: 45910.485 | G379: 126 | H379: 170690 | I379: 55615 | J379: 0 | K379: 0 | L379: 0 | M379: 0 | N379: 0 | O379: 55615 | P379: =SUM(Cartera[[#This Row],[1_a_8]:[>30]]) -> 55615 | Q379: =+Cartera[[#This Row],[9_a_15]]+Cartera[[#This Row],[16_a_22]]+Cartera[[#This Row],[23_a_30]] -> 0 | R379: =IF(Cartera[[#This Row],[Dias]]>8,Cartera[[#This Row],[Total vencido]],0) -> 55615 | S379: =IF(Cartera[[#This Row],[Mas de 9]]>0,Cartera[[#This Row],[Dias]],0) -> 126 | T379: =IF(Cartera[[#This Row],[Dias]]>99,Cartera[[#This Row],[Total vencido]],0) -> 55615 | U379: =IF(Cartera[[#This Row],[Mas de 100]]>0,Cartera[[#This Row],[Dias]],0) -> 126 | V379: =Cartera[[#This Row],[Vencimiento]]-Cartera[[#This Row],[Emision]] -> 1 | W379: =+IF(Cartera[[#This Row],[Tipo]]=151,"Lom",IF(Cartera[[#This Row],[Tipo]]=153,"Lom",IF(Cartera[[#This Row],[Tipo]]=155,"Lom",IF(Cartera[[#This Row],[Tipo]]=200,"Lom",IF(Cartera[[#This Row],[Tipo]]=224,"Lom",IF(Cartera[[#This Row],[Tipo]]=251,"Lom",IF(Cartera[[#This Row],[Tipo]]=651,"Magra",IF(Cartera[[#This Row],[Tipo]]=655,"Magra",IF(Cartera[[#This Row],[Tipo]]=601,"Magra",IF(Cartera[[#This Row],[Tipo]]=751,"Galan",IF(Cartera[[#This Row],[Tipo]]=757,"Galan",IF(Cartera[[#This Row],[Tipo]]=701,"Galan",IF(Cartera[[#This Row],[Tipo]]=755,"Galan",IF(Cartera[[#This Row],[Tipo]]="CO","Conciliacion Cartera","")))))))))))))) | X379: =_xlfn.XLOOKUP(Cartera[[#This Row],[Nombre tercero]],Vendedor[Nombre],Vendedor[Vendedor],"",0,-1) -> ANGELA SILVESTRE
A380: =+A379 -> CANAL DIGITAL | B380: 155 | C380: 52156 | D380: 1 | E380: 45939.47 | F380: 45940.47 | G380: 96 | H380: 169890 | I380: 169890 | J380: 0 | K380: 0 | L380: 0 | M380: 0 | N380: 0 | O380: 169890 | P380: =SUM(Cartera[[#This Row],[1_a_8]:[>30]]) -> 169890 | Q380: =+Cartera[[#This Row],[9_a_15]]+Cartera[[#This Row],[16_a_22]]+Cartera[[#This Row],[23_a_30]] -> 0 | R380: =IF(Cartera[[#This Row],[Dias]]>8,Cartera[[#This Row],[Total vencido]],0) -> 169890 | S380: =IF(Cartera[[#This Row],[Mas de 9]]>0,Cartera[[#This Row],[Dias]],0) -> 96 | T380: =IF(Cartera[[#This Row],[Dias]]>99,Cartera[[#This Row],[Total vencido]],0) -> 0 | U380: =IF(Cartera[[#This Row],[Mas de 100]]>0,Cartera[[#This Row],[Dias]],0) -> 0 | V380: =Cartera[[#This Row],[Vencimiento]]-Cartera[[#This Row],[Emision]] -> 1 | W380: =+IF(Cartera[[#This Row],[Tipo]]=151,"Lom",IF(Cartera[[#This Row],[Tipo]]=153,"Lom",IF(Cartera[[#This Row],[Tipo]]=155,"Lom",IF(Cartera[[#This Row],[Tipo]]=200,"Lom",IF(Cartera[[#This Row],[Tipo]]=224,"Lom",IF(Cartera[[#This Row],[Tipo]]=251,"Lom",IF(Cartera[[#This Row],[Tipo]]=651,"Magra",IF(Cartera[[#This Row],[Tipo]]=655,"Magra",IF(Cartera[[#This Row],[Tipo]]=601,"Magra",IF(Cartera[[#This Row],[Tipo]]=751,"Galan",IF(Cartera[[#This Row],[Tipo]]=757,"Galan",IF(Cartera[[#This Row],[Tipo]]=701,"Galan",IF(Cartera[[#This Row],[Tipo]]=755,"Galan",IF(Cartera[[#This Row],[Tipo]]="CO","Conciliacion Cartera","")))))))))))))) | X380: =_xlfn.XLOOKUP(Cartera[[#This Row],[Nombre tercero]],Vendedor[Nombre],Vendedor[Vendedor],"",0,-1) -> ANGELA SILVESTRE
A381: CANTINA LA 15 SAS | B381: 751 | C381: 18031 | D381: 4 | E381: 45992.371 | F381: 46022.371 | G381: 14 | H381: 1429500 | I381: 1429500 | J381: 0 | K381: 0 | L381: 1429500 | M381: 0 | N381: 0 | O381: 0 | P381: =SUM(Cartera[[#This Row],[1_a_8]:[>30]]) -> 1429500 | Q381: =+Cartera[[#This Row],[9_a_15]]+Cartera[[#This Row],[16_a_22]]+Cartera[[#This Row],[23_a_30]] -> 1429500 | R381: =IF(Cartera[[#This Row],[Dias]]>8,Cartera[[#This Row],[Total vencido]],0) -> 1429500 | S381: =IF(Cartera[[#This Row],[Mas de 9]]>0,Cartera[[#This Row],[Dias]],0) -> 14 | T381: =IF(Cartera[[#This Row],[Dias]]>99,Cartera[[#This Row],[Total vencido]],0) -> 0 | U381: =IF(Cartera[[#This Row],[Mas de 100]]>0,Cartera[[#This Row],[Dias]],0) -> 0 | V381: =Cartera[[#This Row],[Vencimiento]]-Cartera[[#This Row],[Emision]] -> 30 | W381: =+IF(Cartera[[#This Row],[Tipo]]=151,"Lom",IF(Cartera[[#This Row],[Tipo]]=153,"Lom",IF(Cartera[[#This Row],[Tipo]]=155,"Lom",IF(Cartera[[#This Row],[Tipo]]=200,"Lom",IF(Cartera[[#This Row],[Tipo]]=224,"Lom",IF(Cartera[[#This Row],[Tipo]]=251,"Lom",IF(Cartera[[#This Row],[Tipo]]=651,"Magra",IF(Cartera[[#This Row],[Tipo]]=655,"Magra",IF(Cartera[[#This Row],[Tipo]]=601,"Magra",IF(Cartera[[#This Row],[Tipo]]=751,"Galan",IF(Cartera[[#This Row],[Tipo]]=757,"Galan",IF(Cartera[[#This Row],[Tipo]]=701,"Galan",IF(Cartera[[#This Row],[Tipo]]=755,"Galan",IF(Cartera[[#This Row],[Tipo]]="CO","Conciliacion Cartera","")))))))))))))) | X381: =_xlfn.XLOOKUP(Cartera[[#This Row],[Nombre tercero]],Vendedor[Nombre],Vendedor[Vendedor],"",0,-1) -> JORGE PARDO
A382: =+A381 -> CANTINA LA 15 SAS | B382: 751 | C382: 18136 | D382: 4 | E382: 45994.595 | F382: 46024.594 | G382: 12 | H382: 1980000 | I382: 1980000 | J382: 0 | K382: 0 | L382: 1980000 | M382: 0 | N382: 0 | O382: 0 | P382: =SUM(Cartera[[#This Row],[1_a_8]:[>30]]) -> 1980000 | Q382: =+Cartera[[#This Row],[9_a_15]]+Cartera[[#This Row],[16_a_22]]+Cartera[[#This Row],[23_a_30]] -> 1980000 | R382: =IF(Cartera[[#This Row],[Dias]]>8,Cartera[[#This Row],[Total vencido]],0) -> 1980000 | S382: =IF(Cartera[[#This Row],[Mas de 9]]>0,Cartera[[#This Row],[Dias]],0) -> 12 | T382: =IF(Cartera[[#This Row],[Dias]]>99,Cartera[[#This Row],[Total vencido]],0) -> 0 | U382: =IF(Cartera[[#This Row],[Mas de 100]]>0,Cartera[[#This Row],[Dias]],0) -> 0 | V382: =Cartera[[#This Row],[Vencimiento]]-Cartera[[#This Row],[Emision]] -> 29.999884 | W382: =+IF(Cartera[[#This Row],[Tipo]]=151,"Lom",IF(Cartera[[#This Row],[Tipo]]=153,"Lom",IF(Cartera[[#This Row],[Tipo]]=155,"Lom",IF(Cartera[[#This Row],[Tipo]]=200,"Lom",IF(Cartera[[#This Row],[Tipo]]=224,"Lom",IF(Cartera[[#This Row],[Tipo]]=251,"Lom",IF(Cartera[[#This Row],[Tipo]]=651,"Magra",IF(Cartera[[#This Row],[Tipo]]=655,"Magra",IF(Cartera[[#This Row],[Tipo]]=601,"Magra",IF(Cartera[[#This Row],[Tipo]]=751,"Galan",IF(Cartera[[#This Row],[Tipo]]=757,"Galan",IF(Cartera[[#This Row],[Tipo]]=701,"Galan",IF(Cartera[[#This Row],[Tipo]]=755,"Galan",IF(Cartera[[#This Row],[Tipo]]="CO","Conciliacion Cartera","")))))))))))))) | X382: =_xlfn.XLOOKUP(Cartera[[#This Row],[Nombre tercero]],Vendedor[Nombre],Vendedor[Vendedor],"",0,-1) -> JORGE PARDO
A383: =+A382 -> CANTINA LA 15 SAS | B383: 751 | C383: 18275 | D383: 4 | E383: 45999.413 | F383: 46029.413 | G383: 7 | H383: 6751700 | I383: 6751700 | J383: 0 | K383: 6751700 | L383: 0 | M383: 0 | N383: 0 | O383: 0 | P383: =SUM(Cartera[[#This Row],[1_a_8]:[>30]]) -> 6751700 | Q383: =+Cartera[[#This Row],[9_a_15]]+Cartera[[#This Row],[16_a_22]]+Cartera[[#This Row],[23_a_30]] -> 0 | R383: =IF(Cartera[[#This Row],[Dias]]>8,Cartera[[#This Row],[Total vencido]],0) -> 0 | S383: =IF(Cartera[[#This Row],[Mas de 9]]>0,Cartera[[#This Row],[Dias]],0) -> 0 | T383: =IF(Cartera[[#This Row],[Dias]]>99,Cartera[[#This Row],[Total vencido]],0) -> 0 | U383: =IF(Cartera[[#This Row],[Mas de 100]]>0,Cartera[[#This Row],[Dias]],0) -> 0 | V383: =Cartera[[#This Row],[Vencimiento]]-Cartera[[#This Row],[Emision]] -> 29.999687 | W383: =+IF(Cartera[[#This Row],[Tipo]]=151,"Lom",IF(Cartera[[#This Row],[Tipo]]=153,"Lom",IF(Cartera[[#This Row],[Tipo]]=155,"Lom",IF(Cartera[[#This Row],[Tipo]]=200,"Lom",IF(Cartera[[#This Row],[Tipo]]=224,"Lom",IF(Cartera[[#This Row],[Tipo]]=251,"Lom",IF(Cartera[[#This Row],[Tipo]]=651,"Magra",IF(Cartera[[#This Row],[Tipo]]=655,"Magra",IF(Cartera[[#This Row],[Tipo]]=601,"Magra",IF(Cartera[[#This Row],[Tipo]]=751,"Galan",IF(Cartera[[#This Row],[Tipo]]=757,"Galan",IF(Cartera[[#This Row],[Tipo]]=701,"Galan",IF(Cartera[[#This Row],[Tipo]]=755,"Galan",IF(Cartera[[#This Row],[Tipo]]="CO","Conciliacion Cartera","")))))))))))))) | X383: =_xlfn.XLOOKUP(Cartera[[#This Row],[Nombre tercero]],Vendedor[Nombre],Vendedor[Vendedor],"",0,-1) -> JORGE PARDO
A384: =+A383 -> CANTINA LA 15 SAS | B384: 751 | C384: 18286 | D384: 4 | E384: 46000.309 | F384: 46030.309 | G384: 6 | H384: 1817200 | I384: 1817200 | J384: 0 | K384: 1817200 | L384: 0 | M384: 0 | N384: 0 | O384: 0 | P384: =SUM(Cartera[[#This Row],[1_a_8]:[>30]]) -> 1817200 | Q384: =+Cartera[[#This Row],[9_a_15]]+Cartera[[#This Row],[16_a_22]]+Cartera[[#This Row],[23_a_30]] -> 0 | R384: =IF(Cartera[[#This Row],[Dias]]>8,Cartera[[#This Row],[Total vencido]],0) -> 0 | S384: =IF(Cartera[[#This Row],[Mas de 9]]>0,Cartera[[#This Row],[Dias]],0) -> 0 | T384: =IF(Cartera[[#This Row],[Dias]]>99,Cartera[[#This Row],[Total vencido]],0) -> 0 | U384: =IF(Cartera[[#This Row],[Mas de 100]]>0,Cartera[[#This Row],[Dias]],0) -> 0 | V384: =Cartera[[#This Row],[Vencimiento]]-Cartera[[#This Row],[Emision]] -> 30 | W384: =+IF(Cartera[[#This Row],[Tipo]]=151,"Lom",IF(Cartera[[#This Row],[Tipo]]=153,"Lom",IF(Cartera[[#This Row],[Tipo]]=155,"Lom",IF(Cartera[[#This Row],[Tipo]]=200,"Lom",IF(Cartera[[#This Row],[Tipo]]=224,"Lom",IF(Cartera[[#This Row],[Tipo]]=251,"Lom",IF(Cartera[[#This Row],[Tipo]]=651,"Magra",IF(Cartera[[#This Row],[Tipo]]=655,"Magra",IF(Cartera[[#This Row],[Tipo]]=601,"Magra",IF(Cartera[[#This Row],[Tipo]]=751,"Galan",IF(Cartera[[#This Row],[Tipo]]=757,"Galan",IF(Cartera[[#This Row],[Tipo]]=701,"Galan",IF(Cartera[[#This Row],[Tipo]]=755,"Galan",IF(Cartera[[#This Row],[Tipo]]="CO","Conciliacion Cartera","")))))))))))))) | X384: =_xlfn.XLOOKUP(Cartera[[#This Row],[Nombre tercero]],Vendedor[Nombre],Vendedor[Vendedor],"",0,-1) -> JORGE PARDO
A385: =+A384 -> CANTINA LA 15 SAS | B385: 751 | C385: 18326 | D385: 4 | E385: 46001.271 | F385: 46031.27 | G385: 5 | H385: 4583600 | I385: 4583600 | J385: 0 | K385: 4583600 | L385: 0 | M385: 0 | N385: 0 | O385: 0 | P385: =SUM(Cartera[[#This Row],[1_a_8]:[>30]]) -> 4583600 | Q385: =+Cartera[[#This Row],[9_a_15]]+Cartera[[#This Row],[16_a_22]]+Cartera[[#This Row],[23_a_30]] -> 0 | R385: =IF(Cartera[[#This Row],[Dias]]>8,Cartera[[#This Row],[Total vencido]],0) -> 0 | S385: =IF(Cartera[[#This Row],[Mas de 9]]>0,Cartera[[#This Row],[Dias]],0) -> 0 | T385: =IF(Cartera[[#This Row],[Dias]]>99,Cartera[[#This Row],[Total vencido]],0) -> 0 | U385: =IF(Cartera[[#This Row],[Mas de 100]]>0,Cartera[[#This Row],[Dias]],0) -> 0 | V385: =Cartera[[#This Row],[Vencimiento]]-Cartera[[#This Row],[Emision]] -> 29.999421 | W385: =+IF(Cartera[[#This Row],[Tipo]]=151,"Lom",IF(Cartera[[#This Row],[Tipo]]=153,"Lom",IF(Cartera[[#This Row],[Tipo]]=155,"Lom",IF(Cartera[[#This Row],[Tipo]]=200,"Lom",IF(Cartera[[#This Row],[Tipo]]=224,"Lom",IF(Cartera[[#This Row],[Tipo]]=251,"Lom",IF(Cartera[[#This Row],[Tipo]]=651,"Magra",IF(Cartera[[#This Row],[Tipo]]=655,"Magra",IF(Cartera[[#This Row],[Tipo]]=601,"Magra",IF(Cartera[[#This Row],[Tipo]]=751,"Galan",IF(Cartera[[#This Row],[Tipo]]=757,"Galan",IF(Cartera[[#This Row],[Tipo]]=701,"Galan",IF(Cartera[[#This Row],[Tipo]]=755,"Galan",IF(Cartera[[#This Row],[Tipo]]="CO","Conciliacion Cartera","")))))))))))))) | X385: =_xlfn.XLOOKUP(Cartera[[#This Row],[Nombre tercero]],Vendedor[Nombre],Vendedor[Vendedor],"",0,-1) -> JORGE PARDO
A386: =+A385 -> CANTINA LA 15 SAS | B386: 751 | C386: 18493 | D386: 4 | E386: 46006.185 | F386: 46036.184 | G386: 0 | H386: 12891400 | I386: 11819000 | J386: 11819000 | K386: 0 | L386: 0 | M386: 0 | N386: 0 | O386: 0 | P386: =SUM(Cartera[[#This Row],[1_a_8]:[>30]]) -> 0 | Q386: =+Cartera[[#This Row],[9_a_15]]+Cartera[[#This Row],[16_a_22]]+Cartera[[#This Row],[23_a_30]] -> 0 | R386: =IF(Cartera[[#This Row],[Dias]]>8,Cartera[[#This Row],[Total vencido]],0) -> 0 | S386: =IF(Cartera[[#This Row],[Mas de 9]]>0,Cartera[[#This Row],[Dias]],0) -> 0 | T386: =IF(Cartera[[#This Row],[Dias]]>99,Cartera[[#This Row],[Total vencido]],0) -> 0 | U386: =IF(Cartera[[#This Row],[Mas de 100]]>0,Cartera[[#This Row],[Dias]],0) -> 0 | V386: =Cartera[[#This Row],[Vencimiento]]-Cartera[[#This Row],[Emision]] -> 29.999525 | W386: =+IF(Cartera[[#This Row],[Tipo]]=151,"Lom",IF(Cartera[[#This Row],[Tipo]]=153,"Lom",IF(Cartera[[#This Row],[Tipo]]=155,"Lom",IF(Cartera[[#This Row],[Tipo]]=200,"Lom",IF(Cartera[[#This Row],[Tipo]]=224,"Lom",IF(Cartera[[#This Row],[Tipo]]=251,"Lom",IF(Cartera[[#This Row],[Tipo]]=651,"Magra",IF(Cartera[[#This Row],[Tipo]]=655,"Magra",IF(Cartera[[#This Row],[Tipo]]=601,"Magra",IF(Cartera[[#This Row],[Tipo]]=751,"Galan",IF(Cartera[[#This Row],[Tipo]]=757,"Galan",IF(Cartera[[#This Row],[Tipo]]=701,"Galan",IF(Cartera[[#This Row],[Tipo]]=755,"Galan",IF(Cartera[[#This Row],[Tipo]]="CO","Conciliacion Cartera","")))))))))))))) | X386: =_xlfn.XLOOKUP(Cartera[[#This Row],[Nombre tercero]],Vendedor[Nombre],Vendedor[Vendedor],"",0,-1) -> JORGE PARDO
A387: =+A386 -> CANTINA LA 15 SAS | B387: 751 | C387: 18738 | D387: 4 | E387: 46011.43 | F387: 46041.429 | G387: -5 | H387: 1013300 | I387: 1013300 | J387: 1013300 | K387: 0 | L387: 0 | M387: 0 | N387: 0 | O387: 0 | P387: =SUM(Cartera[[#This Row],[1_a_8]:[>30]]) -> 0 | Q387: =+Cartera[[#This Row],[9_a_15]]+Cartera[[#This Row],[16_a_22]]+Cartera[[#This Row],[23_a_30]] -> 0 | R387: =IF(Cartera[[#This Row],[Dias]]>8,Cartera[[#This Row],[Total vencido]],0) -> 0 | S387: =IF(Cartera[[#This Row],[Mas de 9]]>0,Cartera[[#This Row],[Dias]],0) -> 0 | T387: =IF(Cartera[[#This Row],[Dias]]>99,Cartera[[#This Row],[Total vencido]],0) -> 0 | U387: =IF(Cartera[[#This Row],[Mas de 100]]>0,Cartera[[#This Row],[Dias]],0) -> 0 | V387: =Cartera[[#This Row],[Vencimiento]]-Cartera[[#This Row],[Emision]] -> 29.999884 | W387: =+IF(Cartera[[#This Row],[Tipo]]=151,"Lom",IF(Cartera[[#This Row],[Tipo]]=153,"Lom",IF(Cartera[[#This Row],[Tipo]]=155,"Lom",IF(Cartera[[#This Row],[Tipo]]=200,"Lom",IF(Cartera[[#This Row],[Tipo]]=224,"Lom",IF(Cartera[[#This Row],[Tipo]]=251,"Lom",IF(Cartera[[#This Row],[Tipo]]=651,"Magra",IF(Cartera[[#This Row],[Tipo]]=655,"Magra",IF(Cartera[[#This Row],[Tipo]]=601,"Magra",IF(Cartera[[#This Row],[Tipo]]=751,"Galan",IF(Cartera[[#This Row],[Tipo]]=757,"Galan",IF(Cartera[[#This Row],[Tipo]]=701,"Galan",IF(Cartera[[#This Row],[Tipo]]=755,"Galan",IF(Cartera[[#This Row],[Tipo]]="CO","Conciliacion Cartera","")))))))))))))) | X387: =_xlfn.XLOOKUP(Cartera[[#This Row],[Nombre tercero]],Vendedor[Nombre],Vendedor[Vendedor],"",0,-1) -> JORGE PARDO
...

Sheet Vendedores
B2: Nit | C2: Nombre | D2: Columna1 | E2: Vendedor | F2: Columna2
B3: 900993503 | C3: A MANO SAS | E3: JORGE PARDO | F3: HORECA
B4: 900539052 | C4: ABEL Y SOFIA SAS | E4: ANGELA SILVESTRE | F4: HORECA
B5: 901017839 | C5: ACVL S.A.S | E5: JORGE PARDO | F5: Mayoristas
B6: 79643388 | C6: ADRIAN ALVAREZ | E6: ANGELA SILVESTRE | F6: Mayoristas
B7: 52074253 | C7: ADRIANA BERMUDEZ RAMIREZ | E7: JORGE PARDO | F7: HORECA
B8: 1018454730 | C8: ADRIANA RUBIO MARTINEZ | E8: ANGELA SILVESTRE | F8: Mostrador
B9: 830059718 | C9: AECSA SAS | E9: ANGELA SILVESTRE | F9: HORECA
B10: 83056853 | C10: AGROMAS LTDA | E10: ANGELA SILVESTRE | F10: Mayoristas
B11: 900527483 | C11: AGROPECUARIA EL INGENIO SAS MAGROS CARNES DE CERDO | E11: ANGELA SILVESTRE | F11: Mayoristas
B12: 890207037 | C12: AGROPUCUARIA ALIAR S.A.S | E12: ANGELA SILVESTRE | F12: Industria
B13: 901746296 | C13: AGROTODO MENEGUA SAS | E13: ANGELA SILVESTRE | F13: Industria
B14: 901734623 | C14: AGUA DE AFLUENTES SAS | E14: ANGELA SILVESTRE | F14: HORECA
... B96: 79382679 | C96: CANDIDO CORTES | E96: ANGELA SILVESTRE | F96: Mayoristas
B97: 900906554 | C97: CANTINA LA 15 SAS | D97: Cantina la 15 | E97: JORGE PARDO | F97: HORECA
B98: 901627338 | C98: CAÑAS PERVER SAS | E98: ANGELA SILVESTRE | F98: Mayoristas
B99: 143 | C99: CARLOS AYALA | E99: ANGELA SILVESTRE | F99: Mayoristas
B100: 79126370 | C100: CARLOS CUBIDES | E100: ANGELA SILVESTRE | F100: HORECA
B101: 93392103 | C101: CARLOS FLOREZ | E101: ANGELA SILVESTRE | F101: Canal digital
B102: 451 | C102: CARLOS GALEANO | E102: ANGELA SILVESTRE | F102: Mayoristas
B103: 148 | C103: CARLOS LINARES | E103: ANGELA SILVESTRE | F103: Mostrador
B104: 19226024 | C104: CARLOS NAVARRO | E104: ANGELA SILVESTRE | F104: Mayoristas
B105: 162 | C105: CARLOS ALBERTO GARAY PLAZAS | E105: ANGELA SILVESTRE | F105: Mostrador
B106: 80109859 | C106: CARLOS ANDRES BALLESTEROS | E106: ANGELA SILVESTRE | F106: Mayoristas
B107: 80854452 | C107: CARLOS ANDRES CORTES PACHON | E107: ANGELA SILVESTRE | F107: Mayoristas
B108: 1042454473 | C108: CARLOS ANDRES HERNANDEZ MARTINEZ | E108: ANGELA SILVESTRE | F108: HORECA
B109: 1057736403 | C109: CARLOS ANDRES SEPEDA RUBIO | E109: ANGELA SILVESTRE | F109: HORECA
... B382: 901494655 | C382: INVERSIONES DIMASOL S.A.S | E382: ANGELA SILVESTRE | F382: HORECA
B383: 830115239 | C383: INVERSIONES EL CARNAL SAS | D383: El Carnal | E383: JORGE PARDO | F383: HORECA
B384: 891856457 | C384: INVERSIONES EL DORADO SAS | E384: ANGELA SILVESTRE | F384: Industria
B385: 900675420 | C385: INVERSIONES GUATOQUE SAS | E385: ANGELA SILVESTRE | F385: Mostrador
B386: 901354603 | C386: INVERSIONES KHIMAIRA S.A.S | E386: ANGELA SILVESTRE | F386: Mayoristas
B387: 901494828 | C387: INVERSIONES LA ESPERANZA RBR SAS | E387: ANGELA SILVESTRE | F387: HORECA
B388: 900793046 | C388: INVERSIONES MARTINEZ FRUTIMAX S.A.S | E388: ANGELA SILVESTRE | F388: Industria
B389: 901240494 | C389: INVERSIONES MI TIERRITA SAS | E389: JORGE PARDO | F389: HORECA
B390: 901558589 | C390: INVERSIONES MSA SAS | E390: ANGELA SILVESTRE | F390: Mayoristas
B391: 901222813 | C391: INVERSIONES NGB & CO SAS | E391: ANGELA SILVESTRE | F391: HORECA
B392: 901261990 | C392: INVERSIONES ORANGE BLUE SAS | E392: ANGELA SILVESTRE | F392: HORECA
B393: 901498635 | C393: INVERSIONES PEDERNALES SAS | E393: ANGELA SILVESTRE | F393: HORECA
B394: 860039586 | C394: IPT INVERSIONES | E394: ANGELA SILVESTRE | F394: Mostrador
B395: 901322103 | C395: IRISH COMPANY COLOMBIA S A S | E395: ANGELA SILVESTRE | F395: HORECA
... B684: 379 | C684: SAN JOAQUIN | E684: ANGELA SILVESTRE | F684: Mayoristas
C685: SANDRA LILIANA GONGORA HERNANDEZ | E685: ANGELA SILVESTRE | F685: Mayoristas
B686: 901100074 | C686: SANSON SAS | E686: ANGELA SILVESTRE | F686: HORECA
B687: 900327148 | C687: SANTA COSTILLA S.A.S | E687: ANGELA SILVESTRE | F687: HORECA
B688: 900172069 | C688: SAPORE SAS | E688: WILLIAM DARIO PADILLA | F688: HORECA
B689: 419 | C689: SAUL NARANJO | E689: ANGELA SILVESTRE | F689: Mayoristas
B690: 1070325571 | C690: SAUL ROMERO BUITRAGO | E690: ANGELA SILVESTRE | F690: HORECA
B691: 53041717 | C691: SAYDY SIRLEY BOBADILLA HERNANDEZ | E691: ANGELA SILVESTRE | F691: Industria
B692: 901435824 | C692: SEBALI SAS | E692: ANGELA SILVESTRE | F692: HORECA
B693: 120801761 | C693: SEBASTIAN ESLAVA | E693: ANGELA SILVESTRE | F693: Mostrador
B694: 1020801761 | C694: SEBASTIAN ESLAVA DANGOND | E694: ANGELA SILVESTRE | F694: HORECA
B695: 1016090875 | C695: SEBASTIAN FELIPE VELASCO DIAZ | E695: ANGELA SILVESTRE | F695: Industria
B696: 830133449 | C696: SEGUROS CAPITAL LTDA ASESORES | E696: ANGELA SILVESTRE | F696: Mostrador
B697: 150 | C697: SERAFIN DIAZ | E697: ANGELA SILVESTRE | F697: Mayoristas
... B771: 830094751 | C771: ZX VENTURES COLOMBIA SAS | E771: WILLIAM DARIO PADILLA | F771: HORECA
C772: BALLEN LEON GOURMET SAS | E772: WILLIAM DARIO PADILLA | F772: HORECA
C773: CARNES & CIA SAS | E773: WILLIAM DARIO PADILLA | F773: HORECA
C774: JHON HENDERSON RODRIGUEZ MAHECHA | E774: WILLIAM DARIO PADILLA | F774: HORECA
C775: SEXTO RESTAURANTES SAS | E775: WILLIAM DARIO PADILLA | F775: HORECA
C776: TORRE E INVERSIONES SAS | E776: ANGELA SILVESTRE | F776: Mayoristas
C777: LUZ MARINA PELAYO ORTIZ | E777: WILLIAM DARIO PADILLA | F777: HORECA
C778: ANDRES FERNANDO CORTES HERNANDEZ | E778: WILLIAM DARIO PADILLA | F778: HORECA
C779: JHON HENDERSON RODRIGUEZ MAHECHA | E779: WILLIAM DARIO PADILLA | F779: HORECA
C780: INVERSIONES TRES MILAGROS SAS | E780: WILLIAM DARIO PADILLA | F780: HORECA
C781: CARNES Y HUEVOS K SAS | E781: WILLIAM DARIO PADILLA | F781: HORECA
C782: PEYBU SAS | E782: WILLIAM DARIO PADILLA | F782: HORECA
C783: OWS SPORT SAS | E783: ANGELA SILVESTRE | F783: Canales
... C785: ROBINFOOD COLOMBIA SAS | E785: WILLIAM DARIO PADILLA | F785: Mayoristas
B786: 901676975 | C786: SAGRADO BGTA SAS | E786: JORGE PARDO | F786: HORECA
C787: DUFLO SERVICIOS INTEGRALES S.A.S. | E787: WILLIAM DARIO PADILLA | F787: HORECA
C788: CATEDRAL SAS | E788: WILLIAM DARIO PADILLA | F788: HORECA
C789: PCC SA | E789: JORGE PARDO | F789: HORECA
C790: ARIAS GUERRA Y ASOCIADOS | E790: ANGELA SILVESTRE | F790: Mayoristas
C791: JUAN MANUEL PALLARES ARRIETA | E791: WILLIAM DARIO PADILLA | F791: HORECA
C792: PANTRY FOOD SAS | E792: WILLIAM DARIO PADILLA | F792: HORECA
C793: SOSTENIBILIDAD S.A.S. | E793: WILLIAM DARIO PADILLA | F793: Mayoristas
C794: GRUPO LA LA LA SAS | E794: JORGE PARDO | F794: HORECA
C795: COLEGIOS COLOMBIANOS SAS | E795: JORGE PARDO | F795: HORECA
C796: M&R GASTRONOMY SAS | E796: JORGE PARDO | F796: HORECA
C797: INVERSIONES Y SOLUCIONES DE TRADICION SAS | E797: JORGE PARDO | F797: HORECA
C798: GODDARD CATERING GROUP BOGOTA SAS | E798: WILLIAM DARIO PADILLA | F798: HORECA
... C818: ANDRES MAURICIO CUELLAR HERRERA | E818: WILLIAM DARIO PADILLA | F818: HORECA
B819: 79646110 | C819: JOHN DIEGO GUTIERREZ POLANCO | D819: MOKHA Pasteleria | E819: JENNIFER GONZALEZ TRIANA | F819: Mayoristas
B820: 1120560126 | C820: ELIZABETH MURILLO VALENCIA | D820: Surtiaves tradicion y sabor | E820: JENNIFER GONZALEZ TRIANA | F820: Mayoristas
B821: 79457023 | C821: IVAN RODRIGO LUQUE RESTREPO0 | D821: Las Vacas Gordas Parrilla | E821: JENNIFER GONZALEZ TRIANA | F821: HORECA
B822: 79457023 | C822: IVAN RODRIGO LUQUE RESTREPO | D822: Las Vacas Gordas Parrilla | E822: JENNIFER GONZALEZ TRIANA | F822: HORECA
B823: 80251957 | C823: DIEGO ARMANDO CESPEDES | D823: Restaurante caseros | E823: JENNIFER GONZALEZ TRIANA | F823: Mayoristas
B824: 901789519 | C824: ALIANZA DOC SAS | D824: Restaurante DOC SAS | E824: JENNIFER GONZALEZ TRIANA | F824: Mayoristas
B825: 1022365147 | C825: MIJAIR ANDRES CALDERON ARGOTY | D825: Rio Bistro Café Gastro Bar | E825: JENNIFER GONZALEZ TRIANA | F825: Mayoristas
B826: 1049018901 | C826: LILIANA DAZA RIAPIRA | D826: Sabor Santandereano de la82 | E826: JENNY DIAZ | F826: Mayoristas
B827: 20610698 | C827: NIEVES GUTIERREZ CORREAL | D827: Casa de la Sazón | E827: JENNIFER GONZALEZ TRIANA | F827: Mayoristas
B828: 52973625 | C828: SONIA CONTANZA CARDENAS MURCIA | D828: Restaurante Fason | E828: JENNY DIAZ | F828: Mayoristas
B829: 52899303 | C829: DOLLY EDITH SANABRIA CANTOR | D829: Tres caminos Café restaurante | E829: JENNIFER GONZALEZ TRIANA | F829: Mayoristas
B830: 35378811 | C830: YALINDI BONILLA GRANADOS | D830: Restaurante Angol | E830: JENNY DIAZ | F830: Mayoristas
B831: 1019145894 | C831: DIEGO ALEJANDRO ALZATE GONZALEZ | E831: JENNY DIAZ | F831: Mayoristas
B832: 52352150 | C832: SANDRA MILENA VARGAS QUIROGA | D832: El Grill de la abuela | E832: JENNIFER GONZALEZ TRIANA | F832: Mayoristas
B833: 79486810 | C833: HELBERT ANDRES RAMIREZ TOCARRUNCHO | D833: Parrilla fusion café restaurante bar | E833: JENNIFER GONZALEZ TRIANA | F833: Mayoristas
B834: 35331038 | C834: ANA LUCIA BAUTISTA MANCILLA | D834: Al fogón Carnes y sopas | E834: JENNIFER GONZALEZ TRIANA | F834: Mayoristas
B835: 79975592 | C835: DARWIN GEOVANNI OCHOA MERCHAN | D835: Los Saboros del sabor | E835: JENNY DIAZ | F835: Mayoristas
...

Sheet Clientes
B2: Por recaudar (facturas por vencer hoy y sig. 5 días) | D2: Total Vencido | E2: Vencido 1 a 8 | F2: > de 9 días | G2: > de 100 días
B3: =SUM(clientes[Por vencer]) -> 2.9695255e+08 | D3: =SUM(clientes[Total vencido]) -> 1.2132369e+09 | E3: =SUM(clientes[De 1 a 8]) -> 2.4253249e+08 | F3: =SUM(clientes[> de 9 días]) -> 8.0861625e+08 | G3: =SUM(clientes[> de 100 días]) -> 1.6208816e+08
B6: Clientes | C6: Plazo | D6: Total vencido | E6: De 1 a 8 | F6: > de 9 días | G6: > de 100 días | H6: Por vencer | I6: Hoy | J6: 1 día | K6: 2 días | L6: 3 días | M6: 4 días | N6: 5 días | O6: 6 días | P6: Total a recaudar | Q6: Por vencer que no se recaudará | R6: Motivo
B7: 4G FOOD SAS | C7: =IFERROR(AVERAGEIF(Cartera[Nombre tercero],clientes[[#This Row],[Clientes ]],Cartera[Plazo cliente]),0) -> 14.999541 | D7: =SUMIF(Cartera[Nombre tercero],clientes[[#This Row],[Clientes ]],Cartera[Total vencido]) -> 2469800 | E7: =SUMIF(Cartera[Nombre tercero],clientes[[#This Row],[Clientes ]],Cartera[1_a_8]) -> 816200 | F7: =SUMIF(Cartera[Nombre tercero],clientes[[#This Row],[Clientes ]],Cartera[Mas de 9])-G7 -> 1653600 | G7: =SUMIF(Cartera[Nombre tercero],clientes[[#This Row],[Clientes ]],Cartera[Mas de 100]) -> 0 | H7: =SUMIFS(Cartera[Sin_Vencer],Cartera[Nombre tercero],clientes[[#This Row],[Clientes ]],Cartera[Dias],0)+SUMIFS(Cartera[Sin_Vencer],Cartera[Nombre tercero],clientes[[#This Row],[Clientes ]],Cartera[Dias],-1)+SUMIFS(Cartera[Sin_Vencer],Cartera[Nombre tercero],clientes[[#This Row],[Clientes ]],Cartera[Dias],-2)+SUMIFS(Cartera[Sin_Vencer],Cartera[Nombre tercero],clientes[[#This Row],[Clientes ]],Cartera[Dias],-3)+SUMIFS(Cartera[Sin_Vencer],Cartera[Nombre tercero],clientes[[#This Row],[Clientes ]],Cartera[Dias],-4)+SUMIFS(Cartera[Sin_Vencer],Cartera[Nombre tercero],clientes[[#This Row],[Clientes ]],Cartera[Dias],-5) -> 0 | I7: =SUMIFS(Cartera[Saldo],Cartera[Nombre tercero],clientes[[#This Row],[Clientes ]],Cartera[Dias],0) -> 0 | J7: =SUMIFS(Cartera[Sin_Vencer],Cartera[Nombre tercero],clientes[[#This Row],[Clientes ]],Cartera[Dias],-1) -> 0 | K7: =SUMIFS(Cartera[Sin_Vencer],Cartera[Nombre tercero],clientes[[#This Row],[Clientes ]],Cartera[Dias],-2) -> 0 | L7: =SUMIFS(Cartera[Sin_Vencer],Cartera[Nombre tercero],clientes[[#This Row],[Clientes ]],Cartera[Dias],-3) -> 0 | M7: =SUMIFS(Cartera[Sin_Vencer],Cartera[Nombre tercero],clientes[[#This Row],[Clientes ]],Cartera[Dias],-4) -> 0 | N7: =SUMIFS(Cartera[Sin_Vencer],Cartera[Nombre tercero],clientes[[#This Row],[Clientes ]],Cartera[Dias],-5) -> 0 | O7: =SUMIFS(Cartera[Sin_Vencer],Cartera[Nombre tercero],clientes[[#This Row],[Clientes ]],Cartera[Dias],-6) -> 0 | P7: =SUM(clientes[[#This Row],[Hoy]:[5 días]]) -> 0
B8: A MANO SAS | C8: =IFERROR(AVERAGEIF(Cartera[Nombre tercero],clientes[[#This Row],[Clientes ]],Cartera[Plazo cliente]),0) -> 0 | D8: =SUMIF(Cartera[Nombre tercero],clientes[[#This Row],[Clientes ]],Cartera[Total vencido]) -> 0 | E8: =SUMIF(Cartera[Nombre tercero],clientes[[#This Row],[Clientes ]],Cartera[1_a_8]) -> 0 | F8: =SUMIF(Cartera[Nombre tercero],clientes[[#This Row],[Clientes ]],Cartera[Mas de 9])-G8 -> 0 | G8: =SUMIF(Cartera[Nombre tercero],clientes[[#This Row],[Clientes ]],Cartera[Mas de 100]) -> 0 | H8: =SUMIFS(Cartera[Sin_Vencer],Cartera[Nombre tercero],clientes[[#This Row],[Clientes ]],Cartera[Dias],0)+SUMIFS(Cartera[Sin_Vencer],Cartera[Nombre tercero],clientes[[#This Row],[Clientes ]],Cartera[Dias],-1)+SUMIFS(Cartera[Sin_Vencer],Cartera[Nombre tercero],clientes[[#This Row],[Clientes ]],Cartera[Dias],-2)+SUMIFS(Cartera[Sin_Vencer],Cartera[Nombre tercero],clientes[[#This Row],[Clientes ]],Cartera[Dias],-3)+SUMIFS(Cartera[Sin_Vencer],Cartera[Nombre tercero],clientes[[#This Row],[Clientes ]],Cartera[Dias],-4)+SUMIFS(Cartera[Sin_Vencer],Cartera[Nombre tercero],clientes[[#This Row],[Clientes ]],Cartera[Dias],-5) -> 0 | I8: =SUMIFS(Cartera[Saldo],Cartera[Nombre tercero],clientes[[#This Row],[Clientes ]],Cartera[Dias],0) -> 0 | J8: =SUMIFS(Cartera[Sin_Vencer],Cartera[Nombre tercero],clientes[[#This Row],[Clientes ]],Cartera[Dias],-1) -> 0 | K8: =SUMIFS(Cartera[Sin_Vencer],Cartera[Nombre tercero],clientes[[#This Row],[Clientes ]],Cartera[Dias],-2) -> 0 | L8: =SUMIFS(Cartera[Sin_Vencer],Cartera[Nombre tercero],clientes[[#This Row],[Clientes ]],Cartera[Dias],-3) -> 0 | M8: =SUMIFS(Cartera[Sin_Vencer],Cartera[Nombre tercero],clientes[[#This Row],[Clientes ]],Cartera[Dias],-4) -> 0 | N8: =SUMIFS(Cartera[Sin_Vencer],Cartera[Nombre tercero],clientes[[#This Row],[Clientes ]],Cartera[Dias],-5) -> 0 | O8: =SUMIFS(Cartera[Sin_Vencer],Cartera[Nombre tercero],clientes[[#This Row],[Clientes ]],Cartera[Dias],-6) -> 0 | P8: =SUM(clientes[[#This Row],[Hoy]:[5 días]]) -> 0
B9: A TEAM CG SAS | C9: =IFERROR(AVERAGEIF(Cartera[Nombre tercero],clientes[[#This Row],[Clientes ]],Cartera[Plazo cliente]),0) -> 29.999492 | D9: =SUMIF(Cartera[Nombre tercero],clientes[[#This Row],[Clientes ]],Cartera[Total vencido]) -> 2698500 | E9: =SUMIF(Cartera[Nombre tercero],clientes[[#This Row],[Clientes ]],Cartera[1_a_8]) -> 304500 | F9: =SUMIF(Cartera[Nombre tercero],clientes[[#This Row],[Clientes ]],Cartera[Mas de 9])-G9 -> 2394000 | G9: =SUMIF(Cartera[Nombre tercero],clientes[[#This Row],[Clientes ]],Cartera[Mas de 100]) -> 0 | H9: =SUMIFS(Cartera[Sin_Vencer],Cartera[Nombre tercero],clientes[[#This Row],[Clientes ]],Cartera[Dias],0)+SUMIFS(Cartera[Sin_Vencer],Cartera[Nombre tercero],clientes[[#This Row],[Clientes ]],Cartera[Dias],-1)+SUMIFS(Cartera[Sin_Vencer],Cartera[Nombre tercero],clientes[[#This Row],[Clientes ]],Cartera[Dias],-2)+SUMIFS(Cartera[Sin_Vencer],Cartera[Nombre tercero],clientes[[#This Row],[Clientes ]],Cartera[Dias],-3)+SUMIFS(Cartera[Sin_Vencer],Cartera[Nombre tercero],clientes[[#This Row],[Clientes ]],Cartera[Dias],-4)+SUMIFS(Cartera[Sin_Vencer],Cartera[Nombre tercero],clientes[[#This Row],[Clientes ]],Cartera[Dias],-5) -> 154900 | I9: =SUMIFS(Cartera[Saldo],Cartera[Nombre tercero],clientes[[#This Row],[Clientes ]],Cartera[Dias],0) -> 0 | J9: =SUMIFS(Cartera[Sin_Vencer],Cartera[Nombre tercero],clientes[[#This Row],[Clientes ]],Cartera[Dias],-1) -> 0 | K9: =SUMIFS(Cartera[Sin_Vencer],Cartera[Nombre tercero],clientes[[#This Row],[Clientes ]],Cartera[Dias],-2) -> 0 | L9: =SUMIFS(Cartera[Sin_Vencer],Cartera[Nombre tercero],clientes[[#This Row],[Clientes ]],Cartera[Dias],-3) -> 0 | M9: =SUMIFS(Cartera[Sin_Vencer],Cartera[Nombre tercero],clientes[[#This Row],[Clientes ]],Cartera[Dias],-4) -> 0 | N9: =SUMIFS(Cartera[Sin_Vencer],Cartera[Nombre tercero],clientes[[#This Row],[Clientes ]],Cartera[Dias],-5) -> 154900 | O9: =SUMIFS(Cartera[Sin_Vencer],Cartera[Nombre tercero],clientes[[#This Row],[Clientes ]],Cartera[Dias],-6) -> 0 | P9: =SUM(clientes[[#This Row],[Hoy]:[5 días]]) -> 154900
B10: ABDONINO POLOCHE BOSOS | C10: =IFERROR(AVERAGEIF(Cartera[Nombre tercero],clientes[[#This Row],[Clientes ]],Cartera[Plazo cliente]),0) -> 0 | D10: =SUMIF(Cartera[Nombre tercero],clientes[[#This Row],[Clientes ]],Cartera[Total vencido]) -> 0 | E10: =SUMIF(Cartera[Nombre tercero],clientes[[#This Row],[Clientes ]],Cartera[1_a_8]) -> 0 | F10: =SUMIF(Cartera[Nombre tercero],clientes[[#This Row],[Clientes ]],Cartera[Mas de 9])-G10 -> 0 | G10: =SUMIF(Cartera[Nombre tercero],clientes[[#This Row],[Clientes ]],Cartera[Mas de 100]) -> 0 | H10: =SUMIFS(Cartera[Sin_Vencer],Cartera[Nombre tercero],clientes[[#This Row],[Clientes ]],Cartera[Dias],0)+SUMIFS(Cartera[Sin_Vencer],Cartera[Nombre tercero],clientes[[#This Row],[Clientes ]],Cartera[Dias],-1)+SUMIFS(Cartera[Sin_Vencer],Cartera[Nombre tercero],clientes[[#This Row],[Clientes ]],Cartera[Dias],-2)+SUMIFS(Cartera[Sin_Vencer],Cartera[Nombre tercero],clientes[[#This Row],[Clientes ]],Cartera[Dias],-3)+SUMIFS(Cartera[Sin_Vencer],Cartera[Nombre tercero],clientes[[#This Row],[Clientes ]],Cartera[Dias],-4)+SUMIFS(Cartera[Sin_Vencer],Cartera[Nombre tercero],clientes[[#This Row],[Clientes ]],Cartera[Dias],-5) -> 0 | I10: =SUMIFS(Cartera[Saldo],Cartera[Nombre tercero],clientes[[#This Row],[Clientes ]],Cartera[Dias],0) -> 0 | J10: =SUMIFS(Cartera[Sin_Vencer],Cartera[Nombre tercero],clientes[[#This Row],[Clientes ]],Cartera[Dias],-1) -> 0 | K10: =SUMIFS(Cartera[Sin_Vencer],Cartera[Nombre tercero],clientes[[#This Row],[Clientes ]],Cartera[Dias],-2) -> 0 | L10: =SUMIFS(Cartera[Sin_Vencer],Cartera[Nombre tercero],clientes[[#This Row],[Clientes ]],Cartera[Dias],-3) -> 0 | M10: =SUMIFS(Cartera[Sin_Vencer],Cartera[Nombre tercero],clientes[[#This Row],[Clientes ]],Cartera[Dias],-4) -> 0 | N10: =SUMIFS(Cartera[Sin_Vencer],Cartera[Nombre tercero],clientes[[#This Row],[Clientes ]],Cartera[Dias],-5) -> 0 | O10: =SUMIFS(Cartera[Sin_Vencer],Cartera[Nombre tercero],clientes[[#This Row],[Clientes ]],Cartera[Dias],-6) -> 0 | P10: =SUM(clientes[[#This Row],[Hoy]:[5 días]]) -> 0
B11: ABEL Y SOFIA SAS | C11: =IFERROR(AVERAGEIF(Cartera[Nombre tercero],clientes[[#This Row],[Clientes ]],Cartera[Plazo cliente]),0) -> 29.998679 | D11: =SUMIF(Cartera[Nombre tercero],clientes[[#This Row],[Clientes ]],Cartera[Total vencido]) -> 1.6017876e+08 | E11: =SUMIF(Cartera[Nombre tercero],clientes[[#This Row],[Clientes ]],Cartera[1_a_8]) -> 32641080 | F11: =SUMIF(Cartera[Nombre tercero],clientes[[#This Row],[Clientes ]],Cartera[Mas de 9])-G11 -> 1.2745338e+08 | G11: =SUMIF(Cartera[Nombre tercero],clientes[[#This Row],[Clientes ]],Cartera[Mas de 100]) -> 84299.99 | H11: =SUMIFS(Cartera[Sin_Vencer],Cartera[Nombre tercero],clientes[[#This Row],[Clientes ]],Cartera[Dias],0)+SUMIFS(Cartera[Sin_Vencer],Cartera[Nombre tercero],clientes[[#This Row],[Clientes ]],Cartera[Dias],-1)+SUMIFS(Cartera[Sin_Vencer],Cartera[Nombre tercero],clientes[[#This Row],[Clientes ]],Cartera[Dias],-2)+SUMIFS(Cartera[Sin_Vencer],Cartera[Nombre tercero],clientes[[#This Row],[Clientes ]],Cartera[Dias],-3)+SUMIFS(Cartera[Sin_Vencer],Cartera[Nombre tercero],clientes[[#This Row],[Clientes ]],Cartera[Dias],-4)+SUMIFS(Cartera[Sin_Vencer],Cartera[Nombre tercero],clientes[[#This Row],[Clientes ]],Cartera[Dias],-5) -> 27005650 | I11: =SUMIFS(Cartera[Saldo],Cartera[Nombre tercero],clientes[[#This Row],[Clientes ]],Cartera[Dias],0) -> 1263200 | J11: =SUMIFS(Cartera[Sin_Vencer],Cartera[Nombre tercero],clientes[[#This Row],[Clientes ]],Cartera[Dias],-1) -> 2164700 | K11: =SUMIFS(Cartera[Sin_Vencer],Cartera[Nombre tercero],clientes[[#This Row],[Clientes ]],Cartera[Dias],-2) -> 7898550 | L11: =SUMIFS(Cartera[Sin_Vencer],Cartera[Nombre tercero],clientes[[#This Row],[Clientes ]],Cartera[Dias],-3) -> 2288300 | M11: =SUMIFS(Cartera[Sin_Vencer],Cartera[Nombre tercero],clientes[[#This Row],[Clientes ]],Cartera[Dias],-4) -> 3289200 | N11: =SUMIFS(Cartera[Sin_Vencer],Cartera[Nombre tercero],clientes[[#This Row],[Clientes ]],Cartera[Dias],-5) -> 10101700 | O11: =SUMIFS(Cartera[Sin_Vencer],Cartera[Nombre tercero],clientes[[#This Row],[Clientes ]],Cartera[Dias],-6) -> 0 | P11: =SUM(clientes[[#This Row],[Hoy]:[5 días]]) -> 27005650
B12: ADRIANA BERMUDEZ RAMIREZ | C12: =IFERROR(AVERAGEIF(Cartera[Nombre tercero],clientes[[#This Row],[Clientes ]],Cartera[Plazo cliente]),0) -> 7.9998302 | D12: =SUMIF(Cartera[Nombre tercero],clientes[[#This Row],[Clientes ]],Cartera[Total vencido]) -> 2004840 | E12: =SUMIF(Cartera[Nombre tercero],clientes[[#This Row],[Clientes ]],Cartera[1_a_8]) -> 0 | F12: =SUMIF(Cartera[Nombre tercero],clientes[[#This Row],[Clientes ]],Cartera[Mas de 9])-G12 -> 1773200 | G12: =SUMIF(Cartera[Nombre tercero],clientes[[#This Row],[Clientes ]],Cartera[Mas de 100]) -> 231640 | H12: =SUMIFS(Cartera[Sin_Vencer],Cartera[Nombre tercero],clientes[[#This Row],[Clientes ]],Cartera[Dias],0)+SUMIFS(Cartera[Sin_Vencer],Cartera[Nombre tercero],clientes[[#This Row],[Clientes ]],Cartera[Dias],-1)+SUMIFS(Cartera[Sin_Vencer],Cartera[Nombre tercero],clientes[[#This Row],[Clientes ]],Cartera[Dias],-2)+SUMIFS(Cartera[Sin_Vencer],Cartera[Nombre tercero],clientes[[#This Row],[Clientes ]],Cartera[Dias],-3)+SUMIFS(Cartera[Sin_Vencer],Cartera[Nombre tercero],clientes[[#This Row],[Clientes ]],Cartera[Dias],-4)+SUMIFS(Cartera[Sin_Vencer],Cartera[Nombre tercero],clientes[[#This Row],[Clientes ]],Cartera[Dias],-5) -> 0 | I12: =SUMIFS(Cartera[Saldo],Cartera[Nombre tercero],clientes[[#This Row],[Clientes ]],Cartera[Dias],0) -> 0 | J12: =SUMIFS(Cartera[Sin_Vencer],Cartera[Nombre tercero],clientes[[#This Row],[Clientes ]],Cartera[Dias],-1) -> 0 | K12: =SUMIFS(Cartera[Sin_Vencer],Cartera[Nombre tercero],clientes[[#This Row],[Clientes ]],Cartera[Dias],-2) -> 0 | L12: =SUMIFS(Cartera[Sin_Vencer],Cartera[Nombre tercero],clientes[[#This Row],[Clientes ]],Cartera[Dias],-3) -> 0 | M12: =SUMIFS(Cartera[Sin_Vencer],Cartera[Nombre tercero],clientes[[#This Row],[Clientes ]],Cartera[Dias],-4) -> 0 | N12: =SUMIFS(Cartera[Sin_Vencer],Cartera[Nombre tercero],clientes[[#This Row],[Clientes ]],Cartera[Dias],-5) -> 0 | O12: =SUMIFS(Cartera[Sin_Vencer],Cartera[Nombre tercero],clientes[[#This Row],[Clientes ]],Cartera[Dias],-6) -> 0 | P12: =SUM(clientes[[#This Row],[Hoy]:[5 días]]) -> 0
B13: ALBA MARIA GONZALEZ IBAÑEZ | C13: =IFERROR(AVERAGEIF(Cartera[Nombre tercero],clientes[[#This Row],[Clientes ]],Cartera[Plazo cliente]),0) -> 0.97866898 | D13: =SUMIF(Cartera[Nombre tercero],clientes[[#This Row],[Clientes ]],Cartera[Total vencido]) -> 497700 | E13: =SUMIF(Cartera[Nombre tercero],clientes[[#This Row],[Clientes ]],Cartera[1_a_8]) -> 0 | F13: =SUMIF(Cartera[Nombre tercero],clientes[[#This Row],[Clientes ]],Cartera[Mas de 9])-G13 -> 497700 | G13: =SUMIF(Cartera[Nombre tercero],clientes[[#This Row],[Clientes ]],Cartera[Mas de 100]) -> 0 | H13: =SUMIFS(Cartera[Sin_Vencer],Cartera[Nombre tercero],clientes[[#This Row],[Clientes ]],Cartera[Dias],0)+SUMIFS(Cartera[Sin_Vencer],Cartera[Nombre tercero],clientes[[#This Row],[Clientes ]],Cartera[Dias],-1)+SUMIFS(Cartera[Sin_Vencer],Cartera[Nombre tercero],clientes[[#This Row],[Clientes ]],Cartera[Dias],-2)+SUMIFS(Cartera[Sin_Vencer],Cartera[Nombre tercero],clientes[[#This Row],[Clientes ]],Cartera[Dias],-3)+SUMIFS(Cartera[Sin_Vencer],Cartera[Nombre tercero],clientes[[#This Row],[Clientes ]],Cartera[Dias],-4)+SUMIFS(Cartera[Sin_Vencer],Cartera[Nombre tercero],clientes[[#This Row],[Clientes ]],Cartera[Dias],-5) -> 0 | I13: =SUMIFS(Cartera[Saldo],Cartera[Nombre tercero],clientes[[#This Row],[Clientes ]],Cartera[Dias],0) -> 0 | J13: =SUMIFS(Cartera[Sin_Vencer],Cartera[Nombre tercero],clientes[[#This Row],[Clientes ]],Cartera[Dias],-1) -> 0 | K13: =SUMIFS(Cartera[Sin_Vencer],Cartera[Nombre tercero],clientes[[#This Row],[Clientes ]],Cartera[Dias],-2) -> 0 | L13: =SUMIFS(Cartera[Sin_Vencer],Cartera[Nombre tercero],clientes[[#This Row],[Clientes ]],Cartera[Dias],-3) -> 0 | M13: =SUMIFS(Cartera[Sin_Vencer],Cartera[Nombre tercero],clientes[[#This Row],[Clientes ]],Cartera[Dias],-4) -> 0 | N13: =SUMIFS(Cartera[Sin_Vencer],Cartera[Nombre tercero],clientes[[#This Row],[Clientes ]],Cartera[Dias],-5) -> 0 | O13: =SUMIFS(Cartera[Sin_Vencer],Cartera[Nombre tercero],clientes[[#This Row],[Clientes ]],Cartera[Dias],-6) -> 0 | P13: =SUM(clientes[[#This Row],[Hoy]:[5 días]]) -> 0
B14: ALEJANDRO DURAN | C14: =IFERROR(AVERAGEIF(Cartera[Nombre tercero],clientes[[#This Row],[Clientes ]],Cartera[Plazo cliente]),0) -> 0.99988426 | D14: =SUMIF(Cartera[Nombre tercero],clientes[[#This Row],[Clientes ]],Cartera[Total vencido]) -> 1484405 | E14: =SUMIF(Cartera[Nombre tercero],clientes[[#This Row],[Clientes ]],Cartera[1_a_8]) -> 0 | F14: =SUMIF(Cartera[Nombre tercero],clientes[[#This Row],[Clientes ]],Cartera[Mas de 9])-G14 -> 1484405 | G14: =SUMIF(Cartera[Nombre tercero],clientes[[#This Row],[Clientes ]],Cartera[Mas de 100]) -> 0 | H14: =SUMIFS(Cartera[Sin_Vencer],Cartera[Nombre tercero],clientes[[#This Row],[Clientes ]],Cartera[Dias],0)+SUMIFS(Cartera[Sin_Vencer],Cartera[Nombre tercero],clientes[[#This Row],[Clientes ]],Cartera[Dias],-1)+SUMIFS(Cartera[Sin_Vencer],Cartera[Nombre tercero],clientes[[#This Row],[Clientes ]],Cartera[Dias],-2)+SUMIFS(Cartera[Sin_Vencer],Cartera[Nombre tercero],clientes[[#This Row],[Clientes ]],Cartera[Dias],-3)+SUMIFS(Cartera[Sin_Vencer],Cartera[Nombre tercero],clientes[[#This Row],[Clientes ]],Cartera[Dias],-4)+SUMIFS(Cartera[Sin_Vencer],Cartera[Nombre tercero],clientes[[#This Row],[Clientes ]],Cartera[Dias],-5) -> 0 | I14: =SUMIFS(Cartera[Saldo],Cartera[Nombre tercero],clientes[[#This Row],[Clientes ]],Cartera[Dias],0) -> 0 | J14: =SUMIFS(Cartera[Sin_Vencer],Cartera[Nombre tercero],clientes[[#This Row],[Clientes ]],Cartera[Dias],-1) -> 0 | K14: =SUMIFS(Cartera[Sin_Vencer],Cartera[Nombre tercero],clientes[[#This Row],[Clientes ]],Cartera[Dias],-2) -> 0 | L14: =SUMIFS(Cartera[Sin_Vencer],Cartera[Nombre tercero],clientes[[#This Row],[Clientes ]],Cartera[Dias],-3) -> 0 | M14: =SUMIFS(Cartera[Sin_Vencer],Cartera[Nombre tercero],clientes[[#This Row],[Clientes ]],Cartera[Dias],-4) -> 0 | N14: =SUMIFS(Cartera[Sin_Vencer],Cartera[Nombre tercero],clientes[[#This Row],[Clientes ]],Cartera[Dias],-5) -> 0 | O14: =SUMIFS(Cartera[Sin_Vencer],Cartera[Nombre tercero],clientes[[#This Row],[Clientes ]],Cartera[Dias],-6) -> 0 | P14: =SUM(clientes[[#This Row],[Hoy]:[5 días]]) -> 0
B15: ALIANZA DOC SAS | C15: =IFERROR(AVERAGEIF(Cartera[Nombre tercero],clientes[[#This Row],[Clientes ]],Cartera[Plazo cliente]),0) -> 7.9949479 | D15: =SUMIF(Cartera[Nombre tercero],clientes[[#This Row],[Clientes ]],Cartera[Total vencido]) -> 6296800 | E15: =SUMIF(Cartera[Nombre tercero],clientes[[#This Row],[Clientes ]],Cartera[1_a_8]) -> 4521700 | F15: =SUMIF(Cartera[Nombre tercero],clientes[[#This Row],[Clientes ]],Cartera[Mas de 9])-G15 -> 1775100 | G15: =SUMIF(Cartera[Nombre tercero],clientes[[#This Row],[Clientes ]],Cartera[Mas de 100]) -> 0 | H15: =SUMIFS(Cartera[Sin_Vencer],Cartera[Nombre tercero],clientes[[#This Row],[Clientes ]],Cartera[Dias],0)+SUMIFS(Cartera[Sin_Vencer],Cartera[Nombre tercero],clientes[[#This Row],[Clientes ]],Cartera[Dias],-1)+SUMIFS(Cartera[Sin_Vencer],Cartera[Nombre tercero],clientes[[#This Row],[Clientes ]],Cartera[Dias],-2)+SUMIFS(Cartera[Sin_Vencer],Cartera[Nombre tercero],clientes[[#This Row],[Clientes ]],Cartera[Dias],-3)+SUMIFS(Cartera[Sin_Vencer],Cartera[Nombre tercero],clientes[[#This Row],[Clientes ]],Cartera[Dias],-4)+SUMIFS(Cartera[Sin_Vencer],Cartera[Nombre tercero],clientes[[#This Row],[Clientes ]],Cartera[Dias],-5) -> 0 | I15: =SUMIFS(Cartera[Saldo],Cartera[Nombre tercero],clientes[[#This Row],[Clientes ]],Cartera[Dias],0) -> 0 | J15: =SUMIFS(Cartera[Sin_Vencer],Cartera[Nombre tercero],clientes[[#This Row],[Clientes ]],Cartera[Dias],-1) -> 0 | K15: =SUMIFS(Cartera[Sin_Vencer],Cartera[Nombre tercero],clientes[[#This Row],[Clientes ]],Cartera[Dias],-2) -> 0 | L15: =SUMIFS(Cartera[Sin_Vencer],Cartera[Nombre tercero],clientes[[#This Row],[Clientes ]],Cartera[Dias],-3) -> 0 | M15: =SUMIFS(Cartera[Sin_Vencer],Cartera[Nombre tercero],clientes[[#This Row],[Clientes ]],Cartera[Dias],-4) -> 0 | N15: =SUMIFS(Cartera[Sin_Vencer],Cartera[Nombre tercero],clientes[[#This Row],[Clientes ]],Cartera[Dias],-5) -> 0 | O15: =SUMIFS(Cartera[Sin_Vencer],Cartera[Nombre tercero],clientes[[#This Row],[Clientes ]],Cartera[Dias],-6) -> 0 | P15: =SUM(clientes[[#This Row],[Hoy]:[5 días]]) -> 0
