Workbook

Sheet LISTADO DE CLIENTES
A1: Nit | B1: Cliente | C1: Nombre comercial | D1: Correo cliente | E1: Vendedor | F1: Correo vendedor | G1: Canal | H1: Cupo | I1: Columna1
A2: 900993503 | B2: A MANO SAS | D2: cg629271@gmail.com | E2: JORGE PARDO | F2: j.gutierrez@grupolom.com | G2: HORECA | H2: =_xlfn.XLOOKUP(Tabla3[[#This Row],[Nit]],Hoja2!A2:A1425,Hoja2!C2:C1425) -> 3000000 | I2: =_xlfn.XLOOKUP(Tabla3[[#This Row],[Cliente]],'[1]Datos Contacto'!$A$2:$A$23,'[1]Datos Contacto'!$E$2:$E$23,0,0,1) -> 0
A3: 900539052 | B3: ABEL Y SOFIA SAS | D3: cg629271@gmail.com | E3: ANGELA SILVESTRE | F3: j.gutierrez@grupolom.com | G3: HORECA | H3: =_xlfn.XLOOKUP(Tabla3[[#This Row],[Nit]],Hoja2!A3:A1426,Hoja2!C3:C1426) -> 150000000 | I3: =_xlfn.XLOOKUP(Tabla3[[#This Row],[Cliente]],'[1]Datos Contacto'!$A$2:$A$23,'[1]Datos Contacto'!$E$2:$E$23,0,0,1) -> asistentetesoreria3@grupogordo.net
A4: 901017839 | B4: ACVL S.A.S | D4: cg629271@gmail.com | E4: JORGE PARDO | F4: j.gutierrez@grupolom.com | G4: Mayoristas | H4: =_xlfn.XLOOKUP(Tabla3[[#This Row],[Nit]],Hoja2!A4:A1427,Hoja2!C4:C1427) -> 1000000 | I4: =_xlfn.XLOOKUP(Tabla3[[#This Row],[Cliente]],'[1]Datos Contacto'!$A$2:$A$23,'[1]Datos Contacto'!$E$2:$E$23,0,0,1) -> 0
A5: 79643388 | B5: ADRIAN ALVAREZ | D5: cg629271@gmail.com | E5: ANGELA SILVESTRE | F5: j.gutierrez@grupolom.com | G5: Mayoristas | H5: =_xlfn.XLOOKUP(Tabla3[[#This Row],[Nit]],Hoja2!A5:A1428,Hoja2!C5:C1428) -> 2000000 | I5: =_xlfn.XLOOKUP(Tabla3[[#This Row],[Cliente]],'[1]Datos Contacto'!$A$2:$A$23,'[1]Datos Contacto'!$E$2:$E$23,0,0,1) -> 0
A6: 52074253 | B6: ADRIANA BERMUDEZ RAMIREZ | D6: cg629271@gmail.com | E6: JORGE PARDO | F6: j.gutierrez@grupolom.com | G6: HORECA | H6: =_xlfn.XLOOKUP(Tabla3[[#This Row],[Nit]],Hoja2!A6:A1429,Hoja2!C6:C1429) -> 4000000 | I6: =_xlfn.XLOOKUP(Tabla3[[#This Row],[Cliente]],'[1]Datos Contacto'!$A$2:$A$23,'[1]Datos Contacto'!$E$2:$E$23,0,0,1) -> 0
A7: 1018454730 | B7: ADRIANA RUBIO MARTINEZ | D7: cg629271@gmail.com | E7: ANGELA SILVESTRE | F7: j.gutierrez@grupolom.com | G7: Mostrador | H7: =_xlfn.XLOOKUP(Tabla3[[#This Row],[Nit]],Hoja2!A7:A1430,Hoja2!C7:C1430) -> 1000000 | I7: =_xlfn.XLOOKUP(Tabla3[[#This Row],[Cliente]],'[1]Datos Contacto'!$A$2:$A$23,'[1]Datos Contacto'!$E$2:$E$23,0,0,1) -> 0
A8: 830059718 | B8: AECSA SAS | D8: cg629271@gmail.com | E8: ANGELA SILVESTRE | F8: j.gutierrez@grupolom.com | G8: HORECA | H8: =_xlfn.XLOOKUP(Tabla3[[#This Row],[Nit]],Hoja2!A8:A1431,Hoja2!C8:C1431) -> 1000000 | I8: =_xlfn.XLOOKUP(Tabla3[[#This Row],[Cliente]],'[1]Datos Contacto'!$A$2:$A$23,'[1]Datos Contacto'!$E$2:$E$23,0,0,1) -> 0
A9: 83056853 | B9: AGROMAS LTDA | D9: cg629271@gmail.com | E9: ANGELA SILVESTRE | F9: j.gutierrez@grupolom.com | G9: Mayoristas | H9: =_xlfn.XLOOKUP(Tabla3[[#This Row],[Nit]],Hoja2!A9:A1432,Hoja2!C9:C1432) -> 2000000 | I9: =_xlfn.XLOOKUP(Tabla3[[#This Row],[Cliente]],'[1]Datos Contacto'!$A$2:$A$23,'[1]Datos Contacto'!$E$2:$E$23,0,0,1) -> 0
A10: 900527483 | B10: AGROPECUARIA EL INGENIO SAS MAGROS CARNES DE CERDO | D10: cg629271@gmail.com | E10: ANGELA SILVESTRE | F10: j.gutierrez@grupolom.com | G10: Mayoristas | H10: =_xlfn.XLOOKUP(Tabla3[[#This Row],[Nit]],Hoja2!A10:A1433,Hoja2!C10:C1433) -> 1000000 | I10: =_xlfn.XLOOKUP(Tabla3[[#This Row],[Cliente]],'[1]Datos Contacto'!$A$2:$A$23,'[1]Datos Contacto'!$E$2:$E$23,0,0,1) -> 0
A11: 890207037 | B11: AGROPUCUARIA ALIAR S.A.S | D11: cg629271@gmail.com | E11: ANGELA SILVESTRE | F11: j.gutierrez@grupolom.com | G11: Industria | H11: =_xlfn.XLOOKUP(Tabla3[[#This Row],[Nit]],Hoja2!A11:A1434,Hoja2!C11:C1434) -> 1000000 | I11: =_xlfn.XLOOKUP(Tabla3[[#This Row],[Cliente]],'[1]Datos Contacto'!$A$2:$A$23,'[1]Datos Contacto'!$E$2:$E$23,0,0,1) -> 0
A12: 901746296 | B12: AGROTODO MENEGUA SAS | D12: cg629271@gmail.com | E12: ANGELA SILVESTRE | F12: j.gutierrez@grupolom.com | G12: Industria | H12: =_xlfn.XLOOKUP(Tabla3[[#This Row],[Nit]],Hoja2!A12:A1435,Hoja2!C12:C1435) -> 1000000 | I12: =_xlfn.XLOOKUP(Tabla3[[#This Row],[Cliente]],'[1]Datos Contacto'!$A$2:$A$23,'[1]Datos Contacto'!$E$2:$E$23,0,0,1) -> 0
A13: 901734623 | B13: AGUA DE AFLUENTES SAS | D13: cg629271@gmail.com | E13: ANGELA SILVESTRE | F13: j.gutierrez@grupolom.com | G13: HORECA | H13: =_xlfn.XLOOKUP(Tabla3[[#This Row],[Nit]],Hoja2!A13:A1436,Hoja2!C13:C1436) -> 1000000 | I13: =_xlfn.XLOOKUP(Tabla3[[#This Row],[Cliente]],'[1]Datos Contacto'!$A$2:$A$23,'[1]Datos Contacto'!$E$2:$E$23,0,0,1) -> 0
... A95: 79382679 | B95: CANDIDO CORTES | D95: cg629271@gmail.com | E95: ANGELA SILVESTRE | F95: j.gutierrez@grupolom.com | G95: Mayoristas | H95: =_xlfn.XLOOKUP(Tabla3[[#This Row],[Nit]],Hoja2!A95:A1518,Hoja2!C95:C1518) -> 1000000 | I95: =_xlfn.XLOOKUP(Tabla3[[#This Row],[Cliente]],'[1]Datos Contacto'!$A$2:$A$23,'[1]Datos Contacto'!$E$2:$E$23,0,0,1) -> 0
A96: 900906554 | B96: CANTINA LA 15 SAS | C96: Cantina la 15 | D96: cg629271@gmail.com | E96: JORGE PARDO | F96: j.gutierrez@grupolom.com | G96: HORECA | H96: =_xlfn.XLOOKUP(Tabla3[[#This Row],[Nit]],Hoja2!A96:A1519,Hoja2!C96:C1519) -> 120000000 | I96: =_xlfn.XLOOKUP(Tabla3[[#This Row],[Cliente]],'[1]Datos Contacto'!$A$2:$A$23,'[1]Datos Contacto'!$E$2:$E$23,0,0,1) -> facturacion@cantinala15.com.co
A97: 901627338 | B97: CAÑAS PERVER SAS | D97: cg629271@gmail.com | E97: ANGELA SILVESTRE | F97: j.gutierrez@grupolom.com | G97: Mayoristas | H97: =_xlfn.XLOOKUP(Tabla3[[#This Row],[Nit]],Hoja2!A97:A1520,Hoja2!C97:C1520) -> 1000000 | I97: =_xlfn.XLOOKUP(Tabla3[[#This Row],[Cliente]],'[1]Datos Contacto'!$A$2:$A$23,'[1]Datos Contacto'!$E$2:$E$23,0,0,1) -> 0
A98: 143 | B98: CARLOS AYALA | D98: cg629271@gmail.com | E98: ANGELA SILVESTRE | F98: j.gutierrez@grupolom.com | G98: Mayoristas | H98: =_xlfn.XLOOKUP(Tabla3[[#This Row],[Nit]],Hoja2!A98:A1521,Hoja2!C98:C1521) -> 1000000 | I98: =_xlfn.XLOOKUP(Tabla3[[#This Row],[Cliente]],'[1]Datos Contacto'!$A$2:$A$23,'[1]Datos Contacto'!$E$2:$E$23,0,0,1) -> 0
A99: 79126370 | B99: CARLOS CUBIDES | D99: cg629271@gmail.com | E99: ANGELA SILVESTRE | F99: j.gutierrez@grupolom.com | G99: HORECA | H99: =_xlfn.XLOOKUP(Tabla3[[#This Row],[Nit]],Hoja2!A99:A1522,Hoja2!C99:C1522) -> 1000000 | I99: =_xlfn.XLOOKUP(Tabla3[[#This Row],[Cliente]],'[1]Datos Contacto'!$A$2:$A$23,'[1]Datos Contacto'!$E$2:$E$23,0,0,1) -> 0
A100: 93392103 | B100: CARLOS FLOREZ | D100: cg629271@gmail.com | E100: ANGELA SILVESTRE | F100: j.gutierrez@grupolom.com | G100: Canal digital | H100: =_xlfn.XLOOKUP(Tabla3[[#This Row],[Nit]],Hoja2!A100:A1523,Hoja2!C100:C1523) -> 1000000 | I100: =_xlfn.XLOOKUP(Tabla3[[#This Row],[Cliente]],'[1]Datos Contacto'!$A$2:$A$23,'[1]Datos Contacto'!$E$2:$E$23,0,0,1) -> 0
A101: 451 | B101: CARLOS GALEANO | D101: cg629271@gmail.com | E101: ANGELA SILVESTRE | F101: j.gutierrez@grupolom.com | G101: Mayoristas | H101: =_xlfn.XLOOKUP(Tabla3[[#This Row],[Nit]],Hoja2!A101:A1524,Hoja2!C101:C1524) -> 1000000 | I101: =_xlfn.XLOOKUP(Tabla3[[#This Row],[Cliente]],'[1]Datos Contacto'!$A$2:$A$23,'[1]Datos Contacto'!$E$2:$E$23,0,0,1) -> 0
A102: 148 | B102: CARLOS LINARES | D102: cg629271@gmail.com | E102: ANGELA SILVESTRE | F102: j.gutierrez@grupolom.com | G102: Mostrador | H102: =_xlfn.XLOOKUP(Tabla3[[#This Row],[Nit]],Hoja2!A102:A1525,Hoja2!C102:C1525) -> 1000000 | I102: =_xlfn.XLOOKUP(Tabla3[[#This Row],[Cliente]],'[1]Datos Contacto'!$A$2:$A$23,'[1]Datos Contacto'!$E$2:$E$23,0,0,1) -> 0
A103: 19226024 | B103: CARLOS NAVARRO | D103: cg629271@gmail.com | E103: ANGELA SILVESTRE | F103: j.gutierrez@grupolom.com | G103: Mayoristas | H103: =_xlfn.XLOOKUP(Tabla3[[#This Row],[Nit]],Hoja2!A103:A1526,Hoja2!C103:C1526) -> 1000000 | I103: =_xlfn.XLOOKUP(Tabla3[[#This Row],[Cliente]],'[1]Datos Contacto'!$A$2:$A$23,'[1]Datos Contacto'!$E$2:$E$23,0,0,1) -> 0
A104: 162 | B104: CARLOS ALBERTO GARAY PLAZAS | D104: cg629271@gmail.com | E104: ANGELA SILVESTRE | F104: j.gutierrez@grupolom.com | G104: Mostrador | H104: =_xlfn.XLOOKUP(Tabla3[[#This Row],[Nit]],Hoja2!A104:A1527,Hoja2!C104:C1527) -> 1000000 | I104: =_xlfn.XLOOKUP(Tabla3[[#This Row],[Cliente]],'[1]Datos Contacto'!$A$2:$A$23,'[1]Datos Contacto'!$E$2:$E$23,0,0,1) -> 0
A105: 80109859 | B105: CARLOS ANDRES BALLESTEROS | D105: cg629271@gmail.com | E105: ANGELA SILVESTRE | F105: j.gutierrez@grupolom.com | G105: Mayoristas | H105: =_xlfn.XLOOKUP(Tabla3[[#This Row],[Nit]],Hoja2!A105:A1528,Hoja2!C105:C1528) -> 1000000 | I105: =_xlfn.XLOOKUP(Tabla3[[#This Row],[Cliente]],'[1]Datos Contacto'!$A$2:$A$23,'[1]Datos Contacto'!$E$2:$E$23,0,0,1) -> 0
A106: 80854452 | B106: CARLOS ANDRES CORTES PACHON | D106: cg629271@gmail.com | E106: ANGELA SILVESTRE | F106: j.gutierrez@grupolom.com | G106: Mayoristas | H106: =_xlfn.XLOOKUP(Tabla3[[#This Row],[Nit]],Hoja2!A106:A1529,Hoja2!C106:C1529) -> 1000000 | I106: =_xlfn.XLOOKUP(Tabla3[[#This Row],[Cliente]],'[1]Datos Contacto'!$A$2:$A$23,'[1]Datos Contacto'!$E$2:$E$23,0,0,1) -> 0
A107: 1042454473 | B107: CARLOS ANDRES HERNANDEZ MARTINEZ | D107: cg629271@gmail.com | E107: ANGELA SILVESTRE | F107: j.gutierrez@grupolom.com | G107: HORECA | H107: =_xlfn.XLOOKUP(Tabla3[[#This Row],[Nit]],Hoja2!A107:A1530,Hoja2!C107:C1530) -> 5000000 | I107: =_xlfn.XLOOKUP(Tabla3[[#This Row],[Cliente]],'[1]Datos Contacto'!$A$2:$A$23,'[1]Datos Contacto'!$E$2:$E$23,0,0,1) -> 0
A108: 1057736403 | B108: CARLOS ANDRES SEPEDA RUBIO | D108: cg629271@gmail.com | E108: ANGELA SILVESTRE | F108: j.gutierrez@grupolom.com | G108: HORECA | H108: =_xlfn.XLOOKUP(Tabla3[[#This Row],[Nit]],Hoja2!A108:A1531,Hoja2!C108:C1531) -> 1000000 | I108: =_xlfn.XLOOKUP(Tabla3[[#This Row],[Cliente]],'[1]Datos Contacto'!$A$2:$A$23,'[1]Datos Contacto'!$E$2:$E$23,0,0,1) -> 0
... A381: 901494655 | B381: INVERSIONES DIMASOL S.A.S | D381: cg629271@gmail.com | E381: ANGELA SILVESTRE | F381: j.gutierrez@grupolom.com | G381: HORECA | H381: =_xlfn.XLOOKUP(Tabla3[[#This Row],[Nit]],Hoja2!A381:A1804,Hoja2!C381:C1804) -> 1000000 | I381: =_xlfn.XLOOKUP(Tabla3[[#This Row],[Cliente]],'[1]Datos Contacto'!$A$2:$A$23,'[1]Datos Contacto'!$E$2:$E$23,0,0,1) -> 0
A382: 830115239 | B382: INVERSIONES EL CARNAL SAS | C382: El Carnal | D382: cg629271@gmail.com | E382: JORGE PARDO | F382: j.gutierrez@grupolom.com | G382: HORECA | H382: =_xlfn.XLOOKUP(Tabla3[[#This Row],[Nit]],Hoja2!A382:A1805,Hoja2!C382:C1805) -> 120000000 | I382: =_xlfn.XLOOKUP(Tabla3[[#This Row],[Cliente]],'[1]Datos Contacto'!$A$2:$A$23,'[1]Datos Contacto'!$E$2:$E$23,0,0,1) -> facturacion2@elcarnal.com.co
A383: 891856457 | B383: INVERSIONES EL DORADO SAS | D383: cg629271@gmail.com | E383: ANGELA SILVESTRE | F383: j.gutierrez@grupolom.com | G383: Industria | H383: =_xlfn.XLOOKUP(Tabla3[[#This Row],[Nit]],Hoja2!A383:A1806,Hoja2!C383:C1806) -> 1000000 | I383: =_xlfn.XLOOKUP(Tabla3[[#This Row],[Cliente]],'[1]Datos Contacto'!$A$2:$A$23,'[1]Datos Contacto'!$E$2:$E$23,0,0,1) -> 0
A384: 900675420 | B384: INVERSIONES GUATOQUE SAS | D384: cg629271@gmail.com | E384: ANGELA SILVESTRE | F384: j.gutierrez@grupolom.com | G384: Mostrador | H384: =_xlfn.XLOOKUP(Tabla3[[#This Row],[Nit]],Hoja2!A384:A1807,Hoja2!C384:C1807) -> 1000000 | I384: =_xlfn.XLOOKUP(Tabla3[[#This Row],[Cliente]],'[1]Datos Contacto'!$A$2:$A$23,'[1]Datos Contacto'!$E$2:$E$23,0,0,1) -> 0
A385: 901354603 | B385: INVERSIONES KHIMAIRA S.A.S | D385: cg629271@gmail.com | E385: ANGELA SILVESTRE | F385: j.gutierrez@grupolom.com | G385: Mayoristas | H385: =_xlfn.XLOOKUP(Tabla3[[#This Row],[Nit]],Hoja2!A385:A1808,Hoja2!C385:C1808) -> 1000000 | I385: =_xlfn.XLOOKUP(Tabla3[[#This Row],[Cliente]],'[1]Datos Contacto'!$A$2:$A$23,'[1]Datos Contacto'!$E$2:$E$23,0,0,1) -> 0
A386: 901494828 | B386: INVERSIONES LA ESPERANZA RBR SAS | D386: cg629271@gmail.com | E386: ANGELA SILVESTRE | F386: j.gutierrez@grupolom.com | G386: HORECA | H386: =_xlfn.XLOOKUP(Tabla3[[#This Row],[Nit]],Hoja2!A386:A1809,Hoja2!C386:C1809) -> 1000000 | I386: =_xlfn.XLOOKUP(Tabla3[[#This Row],[Cliente]],'[1]Datos Contacto'!$A$2:$A$23,'[1]Datos Contacto'!$E$2:$E$23,0,0,1) -> 0
A387: 900793046 | B387: INVERSIONES MARTINEZ FRUTIMAX S.A.S | D387: cg629271@gmail.com | E387: ANGELA SILVESTRE | F387: j.gutierrez@grupolom.com | G387: Industria | H387: =_xlfn.XLOOKUP(Tabla3[[#This Row],[Nit]],Hoja2!A387:A1810,Hoja2!C387:C1810) -> 1000000 | I387: =_xlfn.XLOOKUP(Tabla3[[#This Row],[Cliente]],'[1]Datos Contacto'!$A$2:$A$23,'[1]Datos Contacto'!$E$2:$E$23,0,0,1) -> 0
A388: 901240494 | B388: INVERSIONES MI TIERRITA SAS | D388: cg629271@gmail.com | E388: JORGE PARDO | F388: j.gutierrez@grupolom.com | G388: HORECA | H388: =_xlfn.XLOOKUP(Tabla3[[#This Row],[Nit]],Hoja2!A388:A1811,Hoja2!C388:C1811) -> 20000000 | I388: =_xlfn.XLOOKUP(Tabla3[[#This Row],[Cliente]],'[1]Datos Contacto'!$A$2:$A$23,'[1]Datos Contacto'!$E$2:$E$23,0,0,1) -> 0
A389: 901558589 | B389: INVERSIONES MSA SAS | D389: cg629271@gmail.com | E389: ANGELA SILVESTRE | F389: j.gutierrez@grupolom.com | G389: Mayoristas | H389: =_xlfn.XLOOKUP(Tabla3[[#This Row],[Nit]],Hoja2!A389:A1812,Hoja2!C389:C1812) -> 1000000 | I389: =_xlfn.XLOOKUP(Tabla3[[#This Row],[Cliente]],'[1]Datos Contacto'!$A$2:$A$23,'[1]Datos Contacto'!$E$2:$E$23,0,0,1) -> 0
A390: 901222813 | B390: INVERSIONES NGB & CO SAS | D390: cg629271@gmail.com | E390: ANGELA SILVESTRE | F390: j.gutierrez@grupolom.com | G390: HORECA | H390: =_xlfn.XLOOKUP(Tabla3[[#This Row],[Nit]],Hoja2!A390:A1813,Hoja2!C390:C1813) -> 5000000 | I390: =_xlfn.XLOOKUP(Tabla3[[#This Row],[Cliente]],'[1]Datos Contacto'!$A$2:$A$23,'[1]Datos Contacto'!$E$2:$E$23,0,0,1) -> 0
A391: 901261990 | B391: INVERSIONES ORANGE BLUE SAS | D391: cg629271@gmail.com | E391: ANGELA SILVESTRE | F391: j.gutierrez@grupolom.com | G391: HORECA | H391: =_xlfn.XLOOKUP(Tabla3[[#This Row],[Nit]],Hoja2!A391:A1814,Hoja2!C391:C1814) -> 1000000 | I391: =_xlfn.XLOOKUP(Tabla3[[#This Row],[Cliente]],'[1]Datos Contacto'!$A$2:$A$23,'[1]Datos Contacto'!$E$2:$E$23,0,0,1) -> 0
A392: 901498635 | B392: INVERSIONES PEDERNALES SAS | D392: cg629271@gmail.com | E392: ANGELA SILVESTRE | F392: j.gutierrez@grupolom.com | G392: HORECA | H392: =_xlfn.XLOOKUP(Tabla3[[#This Row],[Nit]],Hoja2!A392:A1815,Hoja2!C392:C1815) -> 1000000 | I392: =_xlfn.XLOOKUP(Tabla3[[#This Row],[Cliente]],'[1]Datos Contacto'!$A$2:$A$23,'[1]Datos Contacto'!$E$2:$E$23,0,0,1) -> 0
A393: 860039586 | B393: IPT INVERSIONES | D393: cg629271@gmail.com | E393: ANGELA SILVESTRE | F393: j.gutierrez@grupolom.com | G393: Mostrador | H393: =_xlfn.XLOOKUP(Tabla3[[#This Row],[Nit]],Hoja2!A393:A1816,Hoja2!C393:C1816) -> 1000000 | I393: =_xlfn.XLOOKUP(Tabla3[[#This Row],[Cliente]],'[1]Datos Contacto'!$A$2:$A$23,'[1]Datos Contacto'!$E$2:$E$23,0,0,1) -> 0
A394: 901322103 | B394: IRISH COMPANY COLOMBIA S A S | D394: cg629271@gmail.com | E394: ANGELA SILVESTRE | F394: j.gutierrez@grupolom.com | G394: HORECA | H394: =_xlfn.XLOOKUP(Tabla3[[#This Row],[Nit]],Hoja2!A394:A1817,Hoja2!C394:C1817) -> 1000000 | I394: =_xlfn.XLOOKUP(Tabla3[[#This Row],[Cliente]],'[1]Datos Contacto'!$A$2:$A$23,'[1]Datos Contacto'!$E$2:$E$23,0,0,1) -> 0
... A683: 379 | B683: SAN JOAQUIN | D683: cg629271@gmail.com | E683: ANGELA SILVESTRE | F683: j.gutierrez@grupolom.com | G683: Mayoristas | H683: =_xlfn.XLOOKUP(Tabla3[[#This Row],[Nit]],Hoja2!A683:A2106,Hoja2!C683:C2106) -> 1000000 | I683: =_xlfn.XLOOKUP(Tabla3[[#This Row],[Cliente]],'[1]Datos Contacto'!$A$2:$A$23,'[1]Datos Contacto'!$E$2:$E$23,0,0,1) -> 0
B684: SANDRA LILIANA GONGORA HERNANDEZ | D684: cg629271@gmail.com | E684: ANGELA SILVESTRE | F684: j.gutierrez@grupolom.com | G684: Mayoristas | H684: =_xlfn.XLOOKUP(Tabla3[[#This Row],[Nit]],Hoja2!A684:A2107,Hoja2!C684:C2107) -> 0 | I684: =_xlfn.XLOOKUP(Tabla3[[#This Row],[Cliente]],'[1]Datos Contacto'!$A$2:$A$23,'[1]Datos Contacto'!$E$2:$E$23,0,0,1) -> 0
A685: 901100074 | B685: SANSON SAS | D685: cg629271@gmail.com | E685: ANGELA SILVESTRE | F685: j.gutierrez@grupolom.com | G685: HORECA | H685: =_xlfn.XLOOKUP(Tabla3[[#This Row],[Nit]],Hoja2!A685:A2108,Hoja2!C685:C2108) -> 10000000 | I685: =_xlfn.XLOOKUP(Tabla3[[#This Row],[Cliente]],'[1]Datos Contacto'!$A$2:$A$23,'[1]Datos Contacto'!$E$2:$E$23,0,0,1) -> 0
A686: 900327148 | B686: SANTA COSTILLA S.A.S | D686: cg629271@gmail.com | E686: ANGELA SILVESTRE | F686: j.gutierrez@grupolom.com | G686: HORECA | H686: =_xlfn.XLOOKUP(Tabla3[[#This Row],[Nit]],Hoja2!A686:A2109,Hoja2!C686:C2109) -> 1000000 | I686: =_xlfn.XLOOKUP(Tabla3[[#This Row],[Cliente]],'[1]Datos Contacto'!$A$2:$A$23,'[1]Datos Contacto'!$E$2:$E$23,0,0,1) -> 0
A687: 900172069 | B687: SAPORE SAS | D687: cg629271@gmail.com | E687: WILLIAM DARIO PADILLA | F687: j.gutierrez@grupolom.com | G687: HORECA | H687: =_xlfn.XLOOKUP(Tabla3[[#This Row],[Nit]],Hoja2!A687:A2110,Hoja2!C687:C2110) -> 10000000 | I687: =_xlfn.XLOOKUP(Tabla3[[#This Row],[Cliente]],'[1]Datos Contacto'!$A$2:$A$23,'[1]Datos Contacto'!$E$2:$E$23,0,0,1) -> 0
A688: 419 | B688: SAUL NARANJO | D688: cg629271@gmail.com | E688: ANGELA SILVESTRE | F688: j.gutierrez@grupolom.com | G688: Mayoristas | H688: =_xlfn.XLOOKUP(Tabla3[[#This Row],[Nit]],Hoja2!A688:A2111,Hoja2!C688:C2111) -> 1000000 | I688: =_xlfn.XLOOKUP(Tabla3[[#This Row],[Cliente]],'[1]Datos Contacto'!$A$2:$A$23,'[1]Datos Contacto'!$E$2:$E$23,0,0,1) -> 0
A689: 1070325571 | B689: SAUL ROMERO BUITRAGO | D689: cg629271@gmail.com | E689: ANGELA SILVESTRE | F689: j.gutierrez@grupolom.com | G689: HORECA | H689: =_xlfn.XLOOKUP(Tabla3[[#This Row],[Nit]],Hoja2!A689:A2112,Hoja2!C689:C2112) -> 1000000 | I689: =_xlfn.XLOOKUP(Tabla3[[#This Row],[Cliente]],'[1]Datos Contacto'!$A$2:$A$23,'[1]Datos Contacto'!$E$2:$E$23,0,0,1) -> 0
A690: 53041717 | B690: SAYDY SIRLEY BOBADILLA HERNANDEZ | D690: cg629271@gmail.com | E690: ANGELA SILVESTRE | F690: j.gutierrez@grupolom.com | G690: Industria | H690: =_xlfn.XLOOKUP(Tabla3[[#This Row],[Nit]],Hoja2!A690:A2113,Hoja2!C690:C2113) -> 1000000 | I690: =_xlfn.XLOOKUP(Tabla3[[#This Row],[Cliente]],'[1]Datos Contacto'!$A$2:$A$23,'[1]Datos Contacto'!$E$2:$E$23,0,0,1) -> 0
A691: 901435824 | B691: SEBALI SAS | D691: cg629271@gmail.com | E691: ANGELA SILVESTRE | F691: j.gutierrez@grupolom.com | G691: HORECA | H691: =_xlfn.XLOOKUP(Tabla3[[#This Row],[Nit]],Hoja2!A691:A2114,Hoja2!C691:C2114) -> 10000000 | I691: =_xlfn.XLOOKUP(Tabla3[[#This Row],[Cliente]],'[1]Datos Contacto'!$A$2:$A$23,'[1]Datos Contacto'!$E$2:$E$23,0,0,1) -> 0
A692: 120801761 | B692: SEBASTIAN ESLAVA | D692: cg629271@gmail.com | E692: ANGELA SILVESTRE | F692: j.gutierrez@grupolom.com | G692: Mostrador | H692: =_xlfn.XLOOKUP(Tabla3[[#This Row],[Nit]],Hoja2!A692:A2115,Hoja2!C692:C2115) -> 1000000 | I692: =_xlfn.XLOOKUP(Tabla3[[#This Row],[Cliente]],'[1]Datos Contacto'!$A$2:$A$23,'[1]Datos Contacto'!$E$2:$E$23,0,0,1) -> 0
A693: 1020801761 | B693: SEBASTIAN ESLAVA DANGOND | D693: cg629271@gmail.com | E693: ANGELA SILVESTRE | F693: j.gutierrez@grupolom.com | G693: HORECA | H693: =_xlfn.XLOOKUP(Tabla3[[#This Row],[Nit]],Hoja2!A693:A2116,Hoja2!C693:C2116) -> 8000000 | I693: =_xlfn.XLOOKUP(Tabla3[[#This Row],[Cliente]],'[1]Datos Contacto'!$A$2:$A$23,'[1]Datos Contacto'!$E$2:$E$23,0,0,1) -> 0
A694: 1016090875 | B694: SEBASTIAN FELIPE VELASCO DIAZ | D694: cg629271@gmail.com | E694: ANGELA SILVESTRE | F694: j.gutierrez@grupolom.com | G694: Industria | H694: =_xlfn.XLOOKUP(Tabla3[[#This Row],[Nit]],Hoja2!A694:A2117,Hoja2!C694:C2117) -> 1000000 | I694: =_xlfn.XLOOKUP(Tabla3[[#This Row],[Cliente]],'[1]Datos Contacto'!$A$2:$A$23,'[1]Datos Contacto'!$E$2:$E$23,0,0,1) -> 0
A695: 830133449 | B695: SEGUROS CAPITAL LTDA ASESORES | D695: cg629271@gmail.com | E695: ANGELA SILVESTRE | F695: j.gutierrez@grupolom.com | G695: Mostrador | H695: =_xlfn.XLOOKUP(Tabla3[[#This Row],[Nit]],Hoja2!A695:A2118,Hoja2!C695:C2118) -> 1000000 | I695: =_xlfn.XLOOKUP(Tabla3[[#This Row],[Cliente]],'[1]Datos Contacto'!$A$2:$A$23,'[1]Datos Contacto'!$E$2:$E$23,0,0,1) -> 0
A696: 150 | B696: SERAFIN DIAZ | D696: cg629271@gmail.com | E696: ANGELA SILVESTRE | F696: j.gutierrez@grupolom.com | G696: Mayoristas | H696: =_xlfn.XLOOKUP(Tabla3[[#This Row],[Nit]],Hoja2!A696:A2119,Hoja2!C696:C2119) -> 1000000 | I696: =_xlfn.XLOOKUP(Tabla3[[#This Row],[Cliente]],'[1]Datos Contacto'!$A$2:$A$23,'[1]Datos Contacto'!$E$2:$E$23,0,0,1) -> 0
... A770: 830094751 | B770: ZX VENTURES COLOMBIA SAS | D770: cg629271@gmail.com | E770: WILLIAM DARIO PADILLA | F770: j.gutierrez@grupolom.com | G770: HORECA | H770: =_xlfn.XLOOKUP(Tabla3[[#This Row],[Nit]],Hoja2!A770:A2193,Hoja2!C770:C2193) -> 50000000 | I770: =_xlfn.XLOOKUP(Tabla3[[#This Row],[Cliente]],'[1]Datos Contacto'!$A$2:$A$23,'[1]Datos Contacto'!$E$2:$E$23,0,0,1) -> 0
B771: BALLEN LEON GOURMET SAS | D771: cg629271@gmail.com | E771: WILLIAM DARIO PADILLA | F771: j.gutierrez@grupolom.com | G771: HORECA | H771: =_xlfn.XLOOKUP(Tabla3[[#This Row],[Nit]],Hoja2!A771:A2194,Hoja2!C771:C2194) -> 0 | I771: =_xlfn.XLOOKUP(Tabla3[[#This Row],[Cliente]],'[1]Datos Contacto'!$A$2:$A$23,'[1]Datos Contacto'!$E$2:$E$23,0,0,1) -> 0
B772: CARNES & CIA SAS | D772: cg629271@gmail.com | E772: WILLIAM DARIO PADILLA | F772: j.gutierrez@grupolom.com | G772: HORECA | H772: =_xlfn.XLOOKUP(Tabla3[[#This Row],[Nit]],Hoja2!A772:A2195,Hoja2!C772:C2195) -> 0 | I772: =_xlfn.XLOOKUP(Tabla3[[#This Row],[Cliente]],'[1]Datos Contacto'!$A$2:$A$23,'[1]Datos Contacto'!$E$2:$E$23,0,0,1) -> 0
B773: JHON HENDERSON RODRIGUEZ MAHECHA | D773: cg629271@gmail.com | E773: WILLIAM DARIO PADILLA | F773: j.gutierrez@grupolom.com | G773: HORECA | H773: =_xlfn.XLOOKUP(Tabla3[[#This Row],[Nit]],Hoja2!A773:A2196,Hoja2!C773:C2196) -> 0 | I773: =_xlfn.XLOOKUP(Tabla3[[#This Row],[Cliente]],'[1]Datos Contacto'!$A$2:$A$23,'[1]Datos Contacto'!$E$2:$E$23,0,0,1) -> 0
B774: SEXTO RESTAURANTES SAS | D774: cg629271@gmail.com | E774: WILLIAM DARIO PADILLA | F774: j.gutierrez@grupolom.com | G774: HORECA | H774: =_xlfn.XLOOKUP(Tabla3[[#This Row],[Nit]],Hoja2!A774:A2197,Hoja2!C774:C2197) -> 0 | I774: =_xlfn.XLOOKUP(Tabla3[[#This Row],[Cliente]],'[1]Datos Contacto'!$A$2:$A$23,'[1]Datos Contacto'!$E$2:$E$23,0,0,1) -> 0
B775: TORRE E INVERSIONES SAS | D775: cg629271@gmail.com | E775: ANGELA SILVESTRE | F775: j.gutierrez@grupolom.com | G775: Mayoristas | H775: =_xlfn.XLOOKUP(Tabla3[[#This Row],[Nit]],Hoja2!A775:A2198,Hoja2!C775:C2198) -> 0 | I775: =_xlfn.XLOOKUP(Tabla3[[#This Row],[Cliente]],'[1]Datos Contacto'!$A$2:$A$23,'[1]Datos Contacto'!$E$2:$E$23,0,0,1) -> 0
B776: LUZ MARINA PELAYO ORTIZ | D776: cg629271@gmail.com | E776: WILLIAM DARIO PADILLA | F776: j.gutierrez@grupolom.com | G776: HORECA | H776: =_xlfn.XLOOKUP(Tabla3[[#This Row],[Nit]],Hoja2!A776:A2199,Hoja2!C776:C2199) -> 0 | I776: =_xlfn.XLOOKUP(Tabla3[[#This Row],[Cliente]],'[1]Datos Contacto'!$A$2:$A$23,'[1]Datos Contacto'!$E$2:$E$23,0,0,1) -> 0
B777: ANDRES FERNANDO CORTES HERNANDEZ | D777: cg629271@gmail.com | E777: WILLIAM DARIO PADILLA | F777: j.gutierrez@grupolom.com | G777: HORECA | H777: =_xlfn.XLOOKUP(Tabla3[[#This Row],[Nit]],Hoja2!A777:A2200,Hoja2!C777:C2200) -> 0 | I777: =_xlfn.XLOOKUP(Tabla3[[#This Row],[Cliente]],'[1]Datos Contacto'!$A$2:$A$23,'[1]Datos Contacto'!$E$2:$E$23,0,0,1) -> 0
B778: JHON HENDERSON RODRIGUEZ MAHECHA | D778: cg629271@gmail.com | E778: WILLIAM DARIO PADILLA | F778: j.gutierrez@grupolom.com | G778: HORECA | H778: =_xlfn.XLOOKUP(Tabla3[[#This Row],[Nit]],Hoja2!A778:A2201,Hoja2!C778:C2201) -> 0 | I778: =_xlfn.XLOOKUP(Tabla3[[#This Row],[Cliente]],'[1]Datos Contacto'!$A$2:$A$23,'[1]Datos Contacto'!$E$2:$E$23,0,0,1) -> 0
B779: INVERSIONES TRES MILAGROS SAS | D779: cg629271@gmail.com | E779: WILLIAM DARIO PADILLA | F779: j.gutierrez@grupolom.com | G779: HORECA | H779: =_xlfn.XLOOKUP(Tabla3[[#This Row],[Nit]],Hoja2!A779:A2202,Hoja2!C779:C2202) -> 0 | I779: =_xlfn.XLOOKUP(Tabla3[[#This Row],[Cliente]],'[1]Datos Contacto'!$A$2:$A$23,'[1]Datos Contacto'!$E$2:$E$23,0,0,1) -> 0
B780: CARNES Y HUEVOS K SAS | D780: cg629271@gmail.com | E780: WILLIAM DARIO PADILLA | F780: j.gutierrez@grupolom.com | G780: HORECA | H780: =_xlfn.XLOOKUP(Tabla3[[#This Row],[Nit]],Hoja2!A780:A2203,Hoja2!C780:C2203) -> 0 | I780: =_xlfn.XLOOKUP(Tabla3[[#This Row],[Cliente]],'[1]Datos Contacto'!$A$2:$A$23,'[1]Datos Contacto'!$E$2:$E$23,0,0,1) -> 0
B781: PEYBU SAS | D781: cg629271@gmail.com | E781: WILLIAM DARIO PADILLA | F781: j.gutierrez@grupolom.com | G781: HORECA | H781: =_xlfn.XLOOKUP(Tabla3[[#This Row],[Nit]],Hoja2!A781:A2204,Hoja2!C781:C2204) -> 0 | I781: =_xlfn.XLOOKUP(Tabla3[[#This Row],[Cliente]],'[1]Datos Contacto'!$A$2:$A$23,'[1]Datos Contacto'!$E$2:$E$23,0,0,1) -> 0
B782: OWS SPORT SAS | D782: cg629271@gmail.com | E782: ANGELA SILVESTRE | F782: j.gutierrez@grupolom.com | G782: Canales | H782: =_xlfn.XLOOKUP(Tabla3[[#This Row],[Nit]],Hoja2!A782:A2205,Hoja2!C782:C2205) -> 0 | I782: =_xlfn.XLOOKUP(Tabla3[[#This Row],[Cliente]],'[1]Datos Contacto'!$A$2:$A$23,'[1]Datos Contacto'!$E$2:$E$23,0,0,1) -> 0
... B784: ROBINFOOD COLOMBIA SAS | D784: cg629271@gmail.com | E784: WILLIAM DARIO PADILLA | F784: j.gutierrez@grupolom.com | G784: Mayoristas | H784: =_xlfn.XLOOKUP(Tabla3[[#This Row],[Nit]],Hoja2!A784:A2207,Hoja2!C784:C2207) -> 0 | I784: =_xlfn.XLOOKUP(Tabla3[[#This Row],[Cliente]],'[1]Datos Contacto'!$A$2:$A$23,'[1]Datos Contacto'!$E$2:$E$23,0,0,1) -> facturacion@robinfood.com
A785: 901676975 | B785: SAGRADO BGTA SAS | D785: cg629271@gmail.com | E785: JORGE PARDO | F785: j.gutierrez@grupolom.com | G785: HORECA | H785: =_xlfn.XLOOKUP(Tabla3[[#This Row],[Nit]],Hoja2!A785:A2208,Hoja2!C785:C2208) -> 20000000 | I785: =_xlfn.XLOOKUP(Tabla3[[#This Row],[Cliente]],'[1]Datos Contacto'!$A$2:$A$23,'[1]Datos Contacto'!$E$2:$E$23,0,0,1) -> 0
B786: DUFLO SERVICIOS INTEGRALES S.A.S. | D786: cg629271@gmail.com | E786: WILLIAM DARIO PADILLA | F786: j.gutierrez@grupolom.com | G786: HORECA | H786: =_xlfn.XLOOKUP(Tabla3[[#This Row],[Nit]],Hoja2!A786:A2209,Hoja2!C786:C2209) -> 0 | I786: =_xlfn.XLOOKUP(Tabla3[[#This Row],[Cliente]],'[1]Datos Contacto'!$A$2:$A$23,'[1]Datos Contacto'!$E$2:$E$23,0,0,1) -> recepcionfacturas@duflosas.com
B787: CATEDRAL SAS | D787: cg629271@gmail.com | E787: WILLIAM DARIO PADILLA | F787: j.gutierrez@grupolom.com | G787: HORECA | H787: =_xlfn.XLOOKUP(Tabla3[[#This Row],[Nit]],Hoja2!A787:A2210,Hoja2!C787:C2210) -> 0 | I787: =_xlfn.XLOOKUP(Tabla3[[#This Row],[Cliente]],'[1]Datos Contacto'!$A$2:$A$23,'[1]Datos Contacto'!$E$2:$E$23,0,0,1) -> 0
B788: PCC SA | D788: cg629271@gmail.com | E788: JORGE PARDO | F788: j.gutierrez@grupolom.com | G788: HORECA | H788: =_xlfn.XLOOKUP(Tabla3[[#This Row],[Nit]],Hoja2!A788:A2211,Hoja2!C788:C2211) -> 0 | I788: =_xlfn.XLOOKUP(Tabla3[[#This Row],[Cliente]],'[1]Datos Contacto'!$A$2:$A$23,'[1]Datos Contacto'!$E$2:$E$23,0,0,1) -> 0
B789: ARIAS GUERRA Y ASOCIADOS | D789: cg629271@gmail.com | E789: ANGELA SILVESTRE | F789: j.gutierrez@grupolom.com | G789: Mayoristas | H789: =_xlfn.XLOOKUP(Tabla3[[#This Row],[Nit]],Hoja2!A789:A2212,Hoja2!C789:C2212) -> 0 | I789: =_xlfn.XLOOKUP(Tabla3[[#This Row],[Cliente]],'[1]Datos Contacto'!$A$2:$A$23,'[1]Datos Contacto'!$E$2:$E$23,0,0,1) -> 0
B790: JUAN MANUEL PALLARES ARRIETA | D790: cg629271@gmail.com | E790: WILLIAM DARIO PADILLA | F790: j.gutierrez@grupolom.com | G790: HORECA | H790: =_xlfn.XLOOKUP(Tabla3[[#This Row],[Nit]],Hoja2!A790:A2213,Hoja2!C790:C2213) -> 0 | I790: =_xlfn.XLOOKUP(Tabla3[[#This Row],[Cliente]],'[1]Datos Contacto'!$A$2:$A$23,'[1]Datos Contacto'!$E$2:$E$23,0,0,1) -> 0
B791: PANTRY FOOD SAS | D791: cg629271@gmail.com | E791: WILLIAM DARIO PADILLA | F791: j.gutierrez@grupolom.com | G791: HORECA | H791: =_xlfn.XLOOKUP(Tabla3[[#This Row],[Nit]],Hoja2!A791:A2214,Hoja2!C791:C2214) -> 0 | I791: =_xlfn.XLOOKUP(Tabla3[[#This Row],[Cliente]],'[1]Datos Contacto'!$A$2:$A$23,'[1]Datos Contacto'!$E$2:$E$23,0,0,1) -> 0
B792: SOSTENIBILIDAD S.A.S. | D792: cg629271@gmail.com | E792: WILLIAM DARIO PADILLA | F792: j.gutierrez@grupolom.com | G792: Mayoristas | H792: =_xlfn.XLOOKUP(Tabla3[[#This Row],[Nit]],Hoja2!A792:A2215,Hoja2!C792:C2215) -> 0 | I792: =_xlfn.XLOOKUP(Tabla3[[#This Row],[Cliente]],'[1]Datos Contacto'!$A$2:$A$23,'[1]Datos Contacto'!$E$2:$E$23,0,0,1) -> 0
B793: GRUPO LA LA LA SAS | D793: cg629271@gmail.com | E793: JORGE PARDO | F793: j.gutierrez@grupolom.com | G793: HORECA | H793: =_xlfn.XLOOKUP(Tabla3[[#This Row],[Nit]],Hoja2!A793:A2216,Hoja2!C793:C2216) -> 0 | I793: =_xlfn.XLOOKUP(Tabla3[[#This Row],[Cliente]],'[1]Datos Contacto'!$A$2:$A$23,'[1]Datos Contacto'!$E$2:$E$23,0,0,1) -> 0
B794: COLEGIOS COLOMBIANOS SAS | D794: cg629271@gmail.com | E794: JORGE PARDO | F794: j.gutierrez@grupolom.com | G794: HORECA | H794: =_xlfn.XLOOKUP(Tabla3[[#This Row],[Nit]],Hoja2!A794:A2217,Hoja2!C794:C2217) -> 0 | I794: =_xlfn.XLOOKUP(Tabla3[[#This Row],[Cliente]],'[1]Datos Contacto'!$A$2:$A$23,'[1]Datos Contacto'!$E$2:$E$23,0,0,1) -> 0
B795: M&R GASTRONOMY SAS | D795: cg629271@gmail.com | E795: JORGE PARDO | F795: j.gutierrez@grupolom.com | G795: HORECA | H795: =_xlfn.XLOOKUP(Tabla3[[#This Row],[Nit]],Hoja2!A795:A2218,Hoja2!C795:C2218) -> 0 | I795: =_xlfn.XLOOKUP(Tabla3[[#This Row],[Cliente]],'[1]Datos Contacto'!$A$2:$A$23,'[1]Datos Contacto'!$E$2:$E$23,0,0,1) -> 0
B796: INVERSIONES Y SOLUCIONES DE TRADICION SAS | D796: cg629271@gmail.com | E796: JORGE PARDO | F796: j.gutierrez@grupolom.com | G796: HORECA | H796: =_xlfn.XLOOKUP(Tabla3[[#This Row],[Nit]],Hoja2!A796:A2219,Hoja2!C796:C2219) -> 0 | I796: =_xlfn.XLOOKUP(Tabla3[[#This Row],[Cliente]],'[1]Datos Contacto'!$A$2:$A$23,'[1]Datos Contacto'!$E$2:$E$23,0,0,1) -> contabilidad.santopiquete@gmail.com
B797: GODDARD CATERING GROUP BOGOTA SAS | D797: cg629271@gmail.com | E797: WILLIAM DARIO PADILLA | F797: j.gutierrez@grupolom.com | G797: HORECA | H797: =_xlfn.XLOOKUP(Tabla3[[#This Row],[Nit]],Hoja2!A797:A2220,Hoja2!C797:C2220) -> 0 | I797: =_xlfn.XLOOKUP(Tabla3[[#This Row],[Cliente]],'[1]Datos Contacto'!$A$2:$A$23,'[1]Datos Contacto'!$E$2:$E$23,0,0,1) -> 0
... B817: ANDRES MAURICIO CUELLAR HERRERA | D817: cg629271@gmail.com | E817: WILLIAM DARIO PADILLA | F817: j.gutierrez@grupolom.com | G817: HORECA | H817: =_xlfn.XLOOKUP(Tabla3[[#This Row],[Nit]],Hoja2!A817:A2240,Hoja2!C817:C2240) -> 0 | I817: =_xlfn.XLOOKUP(Tabla3[[#This Row],[Cliente]],'[1]Datos Contacto'!$A$2:$A$23,'[1]Datos Contacto'!$E$2:$E$23,0,0,1) -> 0
A818: 79646110 | B818: JOHN DIEGO GUTIERREZ POLANCO | C818: MOKHA Pasteleria | D818: cg629271@gmail.com | E818: JENNIFER GONZALEZ TRIANA | F818: j.gutierrez@grupolom.com | G818: Mayoristas | H818: =_xlfn.XLOOKUP(Tabla3[[#This Row],[Cliente]],Hoja2!B2:B1425,Hoja2!C2:C1425) -> 1000000 | I818: =_xlfn.XLOOKUP(Tabla3[[#This Row],[Cliente]],'[1]Datos Contacto'!$A$2:$A$23,'[1]Datos Contacto'!$E$2:$E$23,0,0,1) -> 0
A819: 1120560126 | B819: ELIZABETH MURILLO VALENCIA | C819: Surtiaves tradicion y sabor | D819: cg629271@gmail.com | E819: JENNIFER GONZALEZ TRIANA | F819: j.gutierrez@grupolom.com | G819: Mayoristas | H819: =_xlfn.XLOOKUP(Tabla3[[#This Row],[Cliente]],Hoja2!B3:B1426,Hoja2!C3:C1426) -> 0 | I819: =_xlfn.XLOOKUP(Tabla3[[#This Row],[Cliente]],'[1]Datos Contacto'!$A$2:$A$23,'[1]Datos Contacto'!$E$2:$E$23,0,0,1) -> 0
A820: 79457023 | B820: IVAN RODRIGO LUQUE RESTREPO0 | C820: Las Vacas Gordas Parrilla | D820: cg629271@gmail.com | E820: JENNIFER GONZALEZ TRIANA | F820: j.gutierrez@grupolom.com | G820: HORECA | H820: 5000000 | I820: =_xlfn.XLOOKUP(Tabla3[[#This Row],[Cliente]],'[1]Datos Contacto'!$A$2:$A$23,'[1]Datos Contacto'!$E$2:$E$23,0,0,1) -> 0
A821: 79457023 | B821: IVAN RODRIGO LUQUE RESTREPO | C821: Las Vacas Gordas Parrilla | D821: cg629271@gmail.com | E821: JENNIFER GONZALEZ TRIANA | F821: j.gutierrez@grupolom.com | G821: HORECA | H821: =_xlfn.XLOOKUP(Tabla3[[#This Row],[Cliente]],Hoja2!B5:B1428,Hoja2!C5:C1428) -> 5000000 | I821: =_xlfn.XLOOKUP(Tabla3[[#This Row],[Cliente]],'[1]Datos Contacto'!$A$2:$A$23,'[1]Datos Contacto'!$E$2:$E$23,0,0,1) -> 0
A822: 80251957 | B822: DIEGO ARMANDO CESPEDES | C822: Restaurante caseros | D822: cg629271@gmail.com | E822: JENNIFER GONZALEZ TRIANA | F822: j.gutierrez@grupolom.com | G822: Mayoristas | H822: =_xlfn.XLOOKUP(Tabla3[[#This Row],[Cliente]],Hoja2!B6:B1429,Hoja2!C6:C1429) -> 0 | I822: =_xlfn.XLOOKUP(Tabla3[[#This Row],[Cliente]],'[1]Datos Contacto'!$A$2:$A$23,'[1]Datos Contacto'!$E$2:$E$23,0,0,1) -> 0
A823: 901789519 | B823: ALIANZA DOC SAS | C823: Restaurante DOC SAS | D823: cg629271@gmail.com | E823: JENNIFER GONZALEZ TRIANA | F823: j.gutierrez@grupolom.com | G823: Mayoristas | H823: =_xlfn.XLOOKUP(Tabla3[[#This Row],[Cliente]],Hoja2!B7:B1430,Hoja2!C7:C1430) -> 5000000 | I823: =_xlfn.XLOOKUP(Tabla3[[#This Row],[Cliente]],'[1]Datos Contacto'!$A$2:$A$23,'[1]Datos Contacto'!$E$2:$E$23,0,0,1) -> 0
A824: 1022365147 | B824: MIJAIR ANDRES CALDERON ARGOTY | C824: Rio Bistro Café Gastro Bar | D824: cg629271@gmail.com | E824: JENNIFER GONZALEZ TRIANA | F824: j.gutierrez@grupolom.com | G824: Mayoristas | H824: =_xlfn.XLOOKUP(Tabla3[[#This Row],[Nit]],Hoja2!A824:A2247,Hoja2!C824:C2247) -> 0 | I824: =_xlfn.XLOOKUP(Tabla3[[#This Row],[Cliente]],'[1]Datos Contacto'!$A$2:$A$23,'[1]Datos Contacto'!$E$2:$E$23,0,0,1) -> 0
A825: 1049018901 | B825: LILIANA DAZA RIAPIRA | C825: Sabor Santandereano de la82 | D825: cg629271@gmail.com | E825: JENNY ANDREA DIAZ | F825: j.gutierrez@grupolom.com | G825: Mayoristas | H825: =_xlfn.XLOOKUP(Tabla3[[#This Row],[Nit]],Hoja2!A825:A2248,Hoja2!C825:C2248) -> 0 | I825: =_xlfn.XLOOKUP(Tabla3[[#This Row],[Cliente]],'[1]Datos Contacto'!$A$2:$A$23,'[1]Datos Contacto'!$E$2:$E$23,0,0,1) -> 0
A826: 20610698 | B826: NIEVES GUTIERREZ CORREAL | C826: Casa de la Sazón | D826: cg629271@gmail.com | E826: JENNIFER GONZALEZ TRIANA | F826: j.gutierrez@grupolom.com | G826: Mayoristas | H826: =_xlfn.XLOOKUP(Tabla3[[#This Row],[Nit]],Hoja2!A826:A2249,Hoja2!C826:C2249) -> 0 | I826: =_xlfn.XLOOKUP(Tabla3[[#This Row],[Cliente]],'[1]Datos Contacto'!$A$2:$A$23,'[1]Datos Contacto'!$E$2:$E$23,0,0,1) -> 0
A827: 52973625 | B827: SONIA CONTANZA CARDENAS MURCIA | C827: Restaurante Fason | D827: cg629271@gmail.com | E827: JENNY ANDREA DIAZ | F827: j.gutierrez@grupolom.com | G827: Mayoristas | H827: =_xlfn.XLOOKUP(Tabla3[[#This Row],[Nit]],Hoja2!A827:A2250,Hoja2!C827:C2250) -> 0 | I827: =_xlfn.XLOOKUP(Tabla3[[#This Row],[Cliente]],'[1]Datos Contacto'!$A$2:$A$23,'[1]Datos Contacto'!$E$2:$E$23,0,0,1) -> 0
A828: 52899303 | B828: DOLLY EDITH SANABRIA CANTOR | C828: Tres caminos Café restaurante | D828: cg629271@gmail.com | E828: JENNIFER GONZALEZ TRIANA | F828: j.gutierrez@grupolom.com | G828: Mayoristas | H828: =_xlfn.XLOOKUP(Tabla3[[#This Row],[Cliente]],Hoja2!B12:B1435,Hoja2!C12:C1435) -> 0 | I828: =_xlfn.XLOOKUP(Tabla3[[#This Row],[Cliente]],'[1]Datos Contacto'!$A$2:$A$23,'[1]Datos Contacto'!$E$2:$E$23,0,0,1) -> 0
A829: 35378811 | B829: YALINDI BONILLA GRANADOS | C829: Restaurante Angol | D829: cg629271@gmail.com | E829: JENNY ANDREA DIAZ | F829: j.gutierrez@grupolom.com | G829: Mayoristas | H829: =_xlfn.XLOOKUP(Tabla3[[#This Row],[Nit]],Hoja2!A829:A2252,Hoja2!C829:C2252) -> 0 | I829: =_xlfn.XLOOKUP(Tabla3[[#This Row],[Cliente]],'[1]Datos Contacto'!$A$2:$A$23,'[1]Datos Contacto'!$E$2:$E$23,0,0,1) -> 0
A830: 1019145894 | B830: DIEGO ALEJANDRO ALZATE GONZALEZ | D830: cg629271@gmail.com | E830: JENNY ANDREA DIAZ | F830: j.gutierrez@grupolom.com | G830: Mayoristas | H830: =_xlfn.XLOOKUP(Tabla3[[#This Row],[Cliente]],Hoja2!B14:B1437,Hoja2!C14:C1437) -> 0 | I830: =_xlfn.XLOOKUP(Tabla3[[#This Row],[Cliente]],'[1]Datos Contacto'!$A$2:$A$23,'[1]Datos Contacto'!$E$2:$E$23,0,0,1) -> 0
A831: 52352150 | B831: SANDRA MILENA VARGAS QUIROGA | C831: El Grill de la abuela | D831: cg629271@gmail.com | E831: JENNIFER GONZALEZ TRIANA | F831: j.gutierrez@grupolom.com | G831: Mayoristas | H831: =_xlfn.XLOOKUP(Tabla3[[#This Row],[Nit]],Hoja2!A831:A2254,Hoja2!C831:C2254) -> 0 | I831: =_xlfn.XLOOKUP(Tabla3[[#This Row],[Cliente]],'[1]Datos Contacto'!$A$2:$A$23,'[1]Datos Contacto'!$E$2:$E$23,0,0,1) -> 0
A832: 79486810 | B832: HELBERT ANDRES RAMIREZ TOCARRUNCHO | C832: Parrilla fusion café restaurante bar | D832: cg629271@gmail.com | E832: JENNIFER GONZALEZ TRIANA | F832: j.gutierrez@grupolom.com | G832: Mayoristas | H832: =_xlfn.XLOOKUP(Tabla3[[#This Row],[Cliente]],Hoja2!B16:B1439,Hoja2!C16:C1439) -> 0 | I832: =_xlfn.XLOOKUP(Tabla3[[#This Row],[Cliente]],'[1]Datos Contacto'!$A$2:$A$23,'[1]Datos Contacto'!$E$2:$E$23,0,0,1) -> 0
A833: 35331038 | B833: ANA LUCIA BAUTISTA MANCILLA | C833: Al fogón Carnes y sopas | D833: cg629271@gmail.com | E833: JENNIFER GONZALEZ TRIANA | F833: j.gutierrez@grupolom.com | G833: Mayoristas | H833: =_xlfn.XLOOKUP(Tabla3[[#This Row],[Cliente]],Hoja2!B17:B1440,Hoja2!C17:C1440) -> 0 | I833: =_xlfn.XLOOKUP(Tabla3[[#This Row],[Cliente]],'[1]Datos Contacto'!$A$2:$A$23,'[1]Datos Contacto'!$E$2:$E$23,0,0,1) -> 0
A834: 79975592 | B834: DARWIN GEOVANNI OCHOA MERCHAN | C834: Los Saboros del sabor | D834: cg629271@gmail.com | E834: JENNY ANDREA DIAZ | F834: j.gutierrez@grupolom.com | G834: Mayoristas | H834: =_xlfn.XLOOKUP(Tabla3[[#This Row],[Cliente]],Hoja2!B18:B1441,Hoja2!C18:C1441) -> 0 | I834: =_xlfn.XLOOKUP(Tabla3[[#This Row],[Cliente]],'[1]Datos Contacto'!$A$2:$A$23,'[1]Datos Contacto'!$E$2:$E$23,0,0,1) -> 0
...

Sheet Hoja2
A1: Nit | B1: Nombre | C1: cupo
A2: 901460509 | B2: INGENIERIA SAS | C2: 0
A3: 4047154 | B3: JAIRO NICODEMUS DIAZ ARAGON | C3: 2000000
A4: 901889936 | B4: 4G FOOD SAS | C4: 10000000
A5: 900993503 | B5: A MANO SAS | C5: 3000000
A6: 900539052 | B6: ABEL Y SOFIA SAS | C6: 150000000
A7: 901017839 | B7: ACVL S.A.S | C7: 1000000
A8: 52074253 | B8: ADRIANA BERMUDEZ RAMIREZ | C8: 4000000
A9: 1018454730 | B9: ADRIANA RUBIO MARTINEZ | C9: 1000000
A10: 79643388 | B10: ADRIANO ALVAREZ LOZANO | C10: 2000000
A11: 830059718 | B11: AECSA SAS | C11: 1000000
A12: 83056853 | B12: AGROMAS LTDA | C12: 2000000
A13: 900527483 | B13: AGROPECUARIA EL INGENIO SAS MAGROS CARNES DE CERDO | C13: 1000000
... A1425: 830094751 | B1425: ZX VENTURES COLOMBIA SAS | C1425: 50000000
